Workbook

Sheet COMISIONES
A1: VENDEDOR | B1: SUCURSAL | C1: BULTOS | D1: UNIDAD DE MEDIDA | E1: IMPORTE | F1: COMISIÓN POR IMPORTE FIJO | G1: COMISIÓN POR PORCENTAJE | H1: COMISIÓN TOTAL
A2: 0 - TODOS LOS VENDEDORES | B2: 0 | C2: 13183.924 | D2: 58834.985 | E2: 2.3249327e+08 | F2: 0 | G2: 114436.09 | H2: 114436.08
A3: 1 - VERA ERNESTO | B3: 1 | C3: 167.27163 | D3: 302.86322 | E3: 3814536.4 | F3: 0 | G3: 114436.09 | H3: 114436.08
A4: 2 - OJEDA NORBERTO | B4: 1 | C4: 165.92619 | D4: 211.02518 | E4: 3406960.3 | F4: 0 | G4: 0 | H4: 0
A5: 3 - VIDAL NAHUEL | B5: 1 | C5: 207.20415 | D5: 524.62053 | E5: 4721350.1 | F5: 0 | G5: 0 | H5: 0
A6: 4 - TUR SPRINGER FERNANDO | B6: 1 | C6: 237.33539 | D6: 536.19244 | E6: 5343904.4 | F6: 0 | G6: 0 | H6: 0
A7: 5 - SCHELOVER RAUL | B7: 1 | C7: 262.04554 | D7: 597.11226 | E7: 5443341.4 | F7: 0 | G7: 0 | H7: 0
A8: 7 - VALLEJOS EDUARDO | B8: 1 | C8: 72.077778 | D8: 242.515 | E8: 1280810.5 | F8: 0 | G8: 0 | H8: 0
A9: 8 - PARRA MAXIMILIANO | B9: 1 | C9: 119.92685 | D9: 273.94869 | E9: 2446732.8 | F9: 0 | G9: 0 | H9: 0
A10: 9 - ESTIGARRIBIA DAVID | B10: 1 | C10: 109.23688 | D10: 280.07251 | E10: 2512781.6 | F10: 0 | G10: 0 | H10: 0
A11: 10 - BRITEZ EMMANUEL | B11: 1 | C11: 125.12569 | D11: 289.77952 | E11: 2295395.1 | F11: 0 | G11: 0 | H11: 0
A12: 11 - SANCHEZ RICARDO | B12: 1 | C12: 261.23373 | D12: 563.02 | E12: 4592584.7 | F12: 0 | G12: 0 | H12: 0
A13: 12 - GUTIERREZ MARCOS DAVID | B13: 1 | C13: 508.50794 | D13: 463.96387 | E13: 5665351.9 | F13: 0 | G13: 0 | H13: 0
... A46: 123 - TORRES ROLANDO | B46: 1 | C46: 18.030754 | D46: 60 | E46: 429907.21 | F46: 0 | G46: 0 | H46: 0

Sheet AVANCE
A1: SUPERVISOR | B1: VENDEDOR | C1: OBJETIVO | D1: FACTURACION ACUMULADA | F1: FACTURACION DEL DIA | G1: AVANCE VS OBJETIVO | H1: PROYECCION | I1: CUMPLIMIENTO PROYECTADO | J1: MEDIA REAL | K1: MEDIA NECESARIA | L1: COBRO
A2: MARTIN PREVENTA | B2: 20 - FLORES JAVIER | C2: 33912398 | D2: =IFERROR(+VLOOKUP(B2,COMISIONES!A:E,5,FALSE),"0")*1 -> 7450150.3 | E2: 3465580.1 | F2: =+D2-E2 -> 3984570.1 | G2: =+D2/C2 -> 0.2196881 | H2: =+D2/$N$3*$N$4 -> 62084586 | I2: =+H2/C2 -> 1.8307342 | J2: =+D2/$N$3 -> 2483383.4 | K2: =+(C2-D2)/$N$2 -> 1202829.4 | L2: {=+_xlfn.IFS(I2>114%,H2*0.02,I2>109%,H2*0.015,I2>104%,H2*0.0125,I2>99%,H2*0.01,I2<99%,H2*0)} -> 1241691.7 | M2: DIAS DE TRABAJO RESTANTES | N2: 22
B3: 19 - GONZALEZ MARCELO | C3: 32550454 | D3: =IFERROR(+VLOOKUP(B3,COMISIONES!A:E,5,FALSE),"0")*1 -> 6128669.1 | E3: 4360010.1 | F3: =+D3-E3 -> 1768659 | G3: =+D3/C3 -> 0.18828214 | H3: =+D3/$N$3*$N$4 -> 51072243 | I3: =+H3/C3 -> 1.5690178 | J3: =+D3/$N$3 -> 2042889.7 | K3: =+(C3-D3)/$N$2 -> 1200990.2 | L3: {=+_xlfn.IFS(I3>114%,H3*0.02,I3>109%,H3*0.015,I3>104%,H3*0.0125,I3>99%,H3*0.01,I3<99%,H3*0)} -> 1021444.9 | M3: DIAS TRABAJADOS | N3: =N4-N2 -> 3
B4: 16 - GOMEZ MATÍAS | C4: 29826567 | D4: =IFERROR(+VLOOKUP(B4,COMISIONES!A:E,5,FALSE),"0")*1 -> 4269220.1 | E4: 2579799.6 | F4: =+D4-E4 -> 1689420.5 | G4: =+D4/C4 -> 0.14313481 | H4: =+D4/$N$3*$N$4 -> 35576834 | I4: =+H4/C4 -> 1.1927901 | J4: =+D4/$N$3 -> 1423073.4 | K4: =+(C4-D4)/$N$2 -> 1161697.6 | L4: {=+_xlfn.IFS(I4>114%,H4*0.02,I4>109%,H4*0.015,I4>104%,H4*0.0125,I4>99%,H4*0.01,I4<99%,H4*0)} -> 711536.68 | M4: DIAS DE TRABAJO MES | N4: 25
B5: 12 - GUTIERREZ MARCOS DAVID | C5: 29826567 | D5: =IFERROR(+VLOOKUP(B5,COMISIONES!A:E,5,FALSE),"0")*1 -> 5665351.9 | E5: 3933982.6 | F5: =+D5-E5 -> 1731369.4 | G5: =+D5/C5 -> 0.18994315 | H5: =+D5/$N$3*$N$4 -> 47211266 | I5: =+H5/C5 -> 1.5828596 | J5: =+D5/$N$3 -> 1888450.6 | K5: =+(C5-D5)/$N$2 -> 1098237 | L5: {=+_xlfn.IFS(I5>114%,H5*0.02,I5>109%,H5*0.015,I5>104%,H5*0.0125,I5>99%,H5*0.01,I5<99%,H5*0)} -> 944225.32
B6: 11 - SANCHEZ RICARDO | C6: 24719278 | D6: =IFERROR(+VLOOKUP(B6,COMISIONES!A:E,5,FALSE),"0")*1 -> 4592584.7 | E6: 2492962.1 | F6: =+D6-E6 -> 2099622.6 | G6: =+D6/C6 -> 0.1857896 | H6: =+D6/$N$3*$N$4 -> 38271539 | I6: =+H6/C6 -> 1.5482466 | J6: =+D6/$N$3 -> 1530861.6 | K6: =+(C6-D6)/$N$2 -> 914849.7 | L6: {=+_xlfn.IFS(I6>114%,H6*0.02,I6>109%,H6*0.015,I6>104%,H6*0.0125,I6>99%,H6*0.01,I6<99%,H6*0)} -> 765430.78
B7: 8 - PARRA MAXIMILIANO | C7: 29145595 | D7: =IFERROR(+VLOOKUP(B7,COMISIONES!A:E,5,FALSE),"0")*1 -> 2446732.8 | E7: 1599561.9 | F7: =+D7-E7 -> 847170.91 | G7: =+D7/C7 -> 0.083948631 | H7: =+D7/$N$3*$N$4 -> 20389440 | I7: =+H7/C7 -> 0.69957193 | J7: =+D7/$N$3 -> 815577.6 | K7: =+(C7-D7)/$N$2 -> 1213584.6 | L7: {=+_xlfn.IFS(I7>114%,H7*0.02,I7>109%,H7*0.015,I7>104%,H7*0.0125,I7>99%,H7*0.01,I7<99%,H7*0)} -> 0
B8: 5 - SCHELOVER RAUL | C8: 37644124 | D8: =IFERROR(+VLOOKUP(B8,COMISIONES!A:E,5,FALSE),"0")*1 -> 5443341.4 | E8: 3931733.2 | F8: =+D8-E8 -> 1511608.2 | G8: =+D8/C8 -> 0.14460003 | H8: =+D8/$N$3*$N$4 -> 45361178 | I8: =+H8/C8 -> 1.2050002 | J8: =+D8/$N$3 -> 1814447.1 | K8: =+(C8-D8)/$N$2 -> 1463671.9 | L8: {=+_xlfn.IFS(I8>114%,H8*0.02,I8>109%,H8*0.015,I8>104%,H8*0.0125,I8>99%,H8*0.01,I8<99%,H8*0)} -> 907223.56
B9: 4 - TUR SPRINGER FERNANDO | C9: 37644124 | D9: =IFERROR(+VLOOKUP(B9,COMISIONES!A:E,5,FALSE),"0")*1 -> 5343904.4 | E9: 3168065.4 | F9: =+D9-E9 -> 2175839 | G9: =+D9/C9 -> 0.14195853 | H9: =+D9/$N$3*$N$4 -> 44532536 | I9: =+H9/C9 -> 1.1829877 | J9: =+D9/$N$3 -> 1781301.5 | K9: =+(C9-D9)/$N$2 -> 1468191.8 | L9: {=+_xlfn.IFS(I9>114%,H9*0.02,I9>109%,H9*0.015,I9>104%,H9*0.0125,I9>99%,H9*0.01,I9<99%,H9*0)} -> 890650.73
C10: =SUM(C2:C9) -> 2.5526911e+08 | D10: =+SUM(D2:D9) -> 41339955 | E10: 25531695 | F10: =+D10-E10 -> 15808260 | G10: =+D10/C10 -> 0.16194656 | H10: =+D10/$N$3*$N$4 -> 3.4449962e+08 | I10: =+H10/C10 -> 1.3495547 | J10: =+D10/$N$3 -> 13779985 | K10: =+(C10-D10)/$N$2 -> 9724052.3
A11: MARTIN | B11: 22 - ALMIRON NICOLAS | C11: 1.0187873e+08 | D11: =IFERROR(+VLOOKUP(B11,COMISIONES!A:E,5,FALSE),"0")*1 -> 8820125.1 | E11: 6733266.6 | F11: =+D11-E11 -> 2086858.6 | G11: =+D11/C11 -> 0.086574746 | H11: =+D11/$N$3*$N$4 -> 73501043 | I11: =+H11/C11 -> 0.72145622 | J11: =+D11/$N$3 -> 2940041.7 | K11: =+(C11-D11)/$N$2 -> 4229936.5 | L11: {=+_xlfn.IFS(I11>114%,H11*0.0125,I11>109%,H11*0.01,I11>104%,H11*0.0075,I11>99%,H11*0.005,I11<99%,H11*0)} -> 0
B12: 15 - GALARZA GERARDO | C12: 1.3485913e+08 | D12: =IFERROR(+VLOOKUP(B12,COMISIONES!A:E,5,FALSE),"0")*1 -> 27943403 | E12: 17294265 | F12: =+D12-E12 -> 10649138 | G12: =+D12/C12 -> 0.20720438 | H12: =+D12/$N$3*$N$4 -> 2.3286169e+08 | I12: =+H12/C12 -> 1.7267032 | J12: =+D12/$N$3 -> 9314467.6 | K12: =+(C12-D12)/$N$2 -> 4859805.8 | L12: {=+_xlfn.IFS(I12>114%,H12*0.0125,I12>109%,H12*0.01,I12>104%,H12*0.0075,I12>99%,H12*0.005,I12<99%,H12*0)} -> 2910771.1 | M12: AUMENTO OBJ | N12: 0.02
B13: 52 - RAVAROTTO EMANUEL | C13: 44596980 | D13: =IFERROR(+VLOOKUP(B13,COMISIONES!A:E,5,FALSE),"0")*1 -> 6420674.1 | E13: 5100158.1 | F13: =+D13-E13 -> 1320516 | G13: =+D13/C13 -> 0.14397105 | H13: =+D13/$N$3*$N$4 -> 53505617 | I13: =+H13/C13 -> 1.1997588 | J13: =+D13/$N$3 -> 2140224.7 | K13: =+(C13-D13)/$N$2 -> 1735286.6 | L13: {=+_xlfn.IFS(I13>109%,H13*0.015,I13>104%,H13*0.0125,I13>99%,H13*0.01,I13<99%,H13*0)} -> 802584.26
B14: 53 - SANDOVAL RODRIGO | C14: 44596980 | D14: =IFERROR(+VLOOKUP(B14,COMISIONES!A:E,5,FALSE),"0")*1 -> 8129445.8 | E14: 6857277 | F14: =+D14-E14 -> 1272168.7 | G14: =+D14/C14 -> 0.18228691 | H14: =+D14/$N$3*$N$4 -> 67745382 | I14: =+H14/C14 -> 1.5190576 | J14: =+D14/$N$3 -> 2709815.3 | K14: =+(C14-D14)/$N$2 -> 1657615.2 | L14: {=+_xlfn.IFS(I14>109%,H14*0.015,I14>104%,H14*0.0125,I14>99%,H14*0.01,I14<99%,H14*0)} -> 1016180.7
C15: =SUM(C11:C14) -> 3.2593182e+08 | D15: =+SUM(D11:D14) -> 51313648 | E15: 35984967 | F15: =+D15-E15 -> 15328681 | G15: =+D15/C15 -> 0.15743675 | H15: =+D15/$N$3*$N$4 -> 4.2761373e+08 | I15: =+H15/C15 -> 1.311973 | J15: =+D15/$N$3 -> 17104549 | K15: =+(C15-D15)/$N$2 -> 12482644
A16: CRISTIAN | B16: 2 - OJEDA NORBERTO | C16: 28840000 | D16: =IFERROR(+VLOOKUP(B16,COMISIONES!A:E,5,FALSE),"0")*1 -> 3406960.3 | E16: 2307421.1 | F16: =+D16-E16 -> 1099539.2 | G16: =+D16/C16 -> 0.11813316 | H16: =+D16/$N$3*$N$4 -> 28391336 | I16: =+H16/C16 -> 0.98444299 | J16: =+D16/$N$3 -> 1135653.4 | K16: =+(C16-D16)/$N$2 -> 1156047.3 | L16: {=+_xlfn.IFS(I16>114%,H16*0.02,I16>109%,H16*0.015,I16>104%,H16*0.0125,I16>99%,H16*0.01,I16<99%,H16*0)} -> 0
B17: 3 - VIDAL NAHUEL | C17: 26429800 | D17: =IFERROR(+VLOOKUP(B17,COMISIONES!A:E,5,FALSE),"0")*1 -> 4721350.1 | E17: 3665110.4 | F17: =+D17-E17 -> 1056239.8 | G17: =+D17/C17 -> 0.17863738 | H17: =+D17/$N$3*$N$4 -> 39344584 | I17: =+H17/C17 -> 1.4886448 | J17: =+D17/$N$3 -> 1573783.4 | K17: =+(C17-D17)/$N$2 -> 986747.72 | L17: {=+_xlfn.IFS(I17>114%,H17*0.02,I17>109%,H17*0.015,I17>104%,H17*0.0125,I17>99%,H17*0.01,I17<99%,H17*0)} -> 786891.68
B18: 18 - HERRERA PABLO | C18: 26800600 | D18: =IFERROR(+VLOOKUP(B18,COMISIONES!A:E,5,FALSE),"0")*1 -> 3346205 | E18: 1899369.2 | F18: =+D18-E18 -> 1446835.7 | G18: =+D18/C18 -> 0.1248556 | H18: =+D18/$N$3*$N$4 -> 27885041 | I18: =+H18/C18 -> 1.0404633 | J18: =+D18/$N$3 -> 1115401.7 | K18: =+(C18-D18)/$N$2 -> 1066108.9 | L18: {=+_xlfn.IFS(I18>114%,H18*0.02,I18>109%,H18*0.015,I18>104%,H18*0.0125,I18>99%,H18*0.01,I18<99%,H18*0)} -> 348563.02
B19: 21 - CATAN MATIAS | C19: 37286618 | D19: =IFERROR(+VLOOKUP(B19,COMISIONES!A:E,5,FALSE),"0")*1 -> 6974519.4 | E19: 4746780.9 | F19: =+D19-E19 -> 2227738.5 | G19: =+D19/C19 -> 0.18705154 | H19: =+D19/$N$3*$N$4 -> 58120995 | I19: =+H19/C19 -> 1.5587629 | J19: =+D19/$N$3 -> 2324839.8 | K19: =+(C19-D19)/$N$2 -> 1377822.7 | L19: {=+_xlfn.IFS(I19>114%,H19*0.02,I19>109%,H19*0.015,I19>104%,H19*0.0125,I19>99%,H19*0.01,I19<99%,H19*0)} -> 1162419.9
B20: 23 - DELGADO JOSÉ | C20: 27420660 | D20: =IFERROR(+VLOOKUP(B20,COMISIONES!A:E,5,FALSE),"0")*1 -> 3353505.2 | E20: 2086968 | F20: =+D20-E20 -> 1266537.1 | G20: =+D20/C20 -> 0.12229848 | H20: =+D20/$N$3*$N$4 -> 27945876 | I20: =+H20/C20 -> 1.019154 | J20: =+D20/$N$3 -> 1117835.1 | K20: =+(C20-D20)/$N$2 -> 1093961.6 | L20: {=+_xlfn.IFS(I20>114%,H20*0.02,I20>109%,H20*0.015,I20>104%,H20*0.0125,I20>99%,H20*0.01,I20<99%,H20*0)} -> 279458.76
B21: 31 - RENZO RAMOS | C21: 34257800 | D21: =IFERROR(+VLOOKUP(B21,COMISIONES!A:E,5,FALSE),"0")*1 -> 4809073.5 | E21: 2581541.5 | F21: =+D21-E21 -> 2227532 | G21: =+D21/C21 -> 0.14037894 | H21: =+D21/$N$3*$N$4 -> 40075613 | I21: =+H21/C21 -> 1.1698245 | J21: =+D21/$N$3 -> 1603024.5 | K21: =+(C21-D21)/$N$2 -> 1338578.5 | L21: {=+_xlfn.IFS(I21>114%,H21*0.02,I21>109%,H21*0.015,I21>104%,H21*0.0125,I21>99%,H21*0.01,I21<99%,H21*0)} -> 801512.25
B22: 44 - MONGES CESAR LUIS | C22: 29478600 | D22: =IFERROR(+VLOOKUP(B22,COMISIONES!A:E,5,FALSE),"0")*1 -> 3452485.4 | E22: 2138082.6 | F22: =+D22-E22 -> 1314402.9 | G22: =+D22/C22 -> 0.11711836 | H22: =+D22/$N$3*$N$4 -> 28770712 | I22: =+H22/C22 -> 0.97598637 | J22: =+D22/$N$3 -> 1150828.5 | K22: =+(C22-D22)/$N$2 -> 1183005.2 | L22: {=+_xlfn.IFS(I22>114%,H22*0.02,I22>109%,H22*0.015,I22>104%,H22*0.0125,I22>99%,H22*0.01,I22<99%,H22*0)} -> 0
B23: 54 - BARTSCHAT EMILIANO NAHUEL | C23: 39140000 | D23: =IFERROR(+VLOOKUP(B23,COMISIONES!A:E,5,FALSE),"0")*1 -> 5129094.8 | E23: 3226315.5 | F23: =+D23-E23 -> 1902779.4 | G23: =+D23/C23 -> 0.13104483 | H23: =+D23/$N$3*$N$4 -> 42742457 | I23: =+H23/C23 -> 1.0920403 | J23: =+D23/$N$3 -> 1709698.3 | K23: =+(C23-D23)/$N$2 -> 1545950.2 | L23: {=+_xlfn.IFS(I23>114%,H23*0.02,I23>109%,H23*0.015,I23>104%,H23*0.0125,I23>99%,H23*0.01,I23<99%,H23*0)} -> 641136.85
C24: =SUM(C16:C23) -> 249654078 | D24: =+SUM(D16:D23) -> 35193194 | E24: 22651589 | F24: =+D24-E24 -> 12541605 | G24: =+D24/C24 -> 0.14096783 | H24: =+D24/$N$3*$N$4 -> 2.9327661e+08 | I24: =+H24/C24 -> 1.1747319 | J24: =+D24/$N$3 -> 11731065 | K24: =+(C24-D24)/$N$2 -> 9748222
A25: GONZALO | B25: 32 - CABRAL GONZALO | C25: 89144395 | D25: =IFERROR(+VLOOKUP(B25,COMISIONES!A:E,5,FALSE),"0")*1 -> 6424682 | E25: 3002778.1 | F25: =+D25-E25 -> 3421903.9 | G25: =+D25/C25 -> 0.07207051 | H25: =+D25/$N$3*$N$4 -> 53539016 | I25: =+H25/C25 -> 0.60058758 | J25: =+D25/$N$3 -> 2141560.7 | K25: =+(C25-D25)/$N$2 -> 3759987 | L25: {=+_xlfn.IFS(I25>114%,H25*0.0125,I25>109%,H25*0.01,I25>104%,H25*0.0075,I25>99%,H25*0.005,I25<99%,H25*0)} -> 0
B26: 36 - IBARROLA JORGE | C26: 24731127 | D26: =IFERROR(+VLOOKUP(B26,COMISIONES!A:E,5,FALSE),"0")*1 -> 1484315.7 | E26: 874709.21 | F26: =+D26-E26 -> 609606.51 | G26: =+D26/C26 -> 0.060018118 | H26: =+D26/$N$3*$N$4 -> 12369298 | I26: =+H26/C26 -> 0.50015098 | J26: =+D26/$N$3 -> 494771.91 | K26: =+(C26-D26)/$N$2 -> 1056673.3 | L26: {=+_xlfn.IFS(I26>114%,H26*0.02,I26>109%,H26*0.015,I26>104%,H26*0.0125,I26>99%,H26*0.01,I26<99%,H26*0)} -> 0
B27: 9 - ESTIGARRIBIA DAVID | C27: 27718182 | D27: =IFERROR(+VLOOKUP(B27,COMISIONES!A:E,5,FALSE),"0")*1 -> 2512781.6 | E27: 1980733.4 | F27: =+D27-E27 -> 532048.21 | G27: =+D27/C27 -> 0.090654632 | H27: =+D27/$N$3*$N$4 -> 20939847 | I27: =+H27/C27 -> 0.75545527 | J27: =+D27/$N$3 -> 837593.86 | K27: =+(C27-D27)/$N$2 -> 1145700 | L27: {=+_xlfn.IFS(I27>114%,H27*0.02,I27>109%,H27*0.015,I27>104%,H27*0.0125,I27>99%,H27*0.01,I27<99%,H27*0)} -> 0
B28: 40 - SOLIS EMMANUEL | C28: 40364706 | D28: =IFERROR(+VLOOKUP(B28,COMISIONES!A:E,5,FALSE),"0")*1 -> 3444667.7 | E28: 955339.39 | F28: =+D28-E28 -> 2489328.3 | G28: =+D28/C28 -> 0.085338604 | H28: =+D28/$N$3*$N$4 -> 28705564 | I28: =+H28/C28 -> 0.71115503 | J28: =+D28/$N$3 -> 1148222.6 | K28: =+(C28-D28)/$N$2 -> 1678183.6 | L28: {=+_xlfn.IFS(I28>114%,H28*0.02,I28>109%,H28*0.015,I28>104%,H28*0.0125,I28>99%,H28*0.01,I28<99%,H28*0)} -> 0
B29: 27 - GOMEZ ADRIÁN | C29: 27707000 | D29: =IFERROR(+VLOOKUP(B29,COMISIONES!A:E,5,FALSE),"0")*1 -> 2771512.9 | E29: 1680099.3 | F29: =+D29-E29 -> 1091413.6 | G29: =+D29/C29 -> 0.10002934 | H29: =+D29/$N$3*$N$4 -> 23095940 | I29: =+H29/C29 -> 0.83357781 | J29: =+D29/$N$3 -> 923837.62 | K29: =+(C29-D29)/$N$2 -> 1133431.2 | L29: {=+_xlfn.IFS(I29>114%,H29*0.02,I29>109%,H29*0.015,I29>104%,H29*0.0125,I29>99%,H29*0.01,I29<99%,H29*0)} -> 0
B30: 10 - BRITEZ EMMANUEL | C30: 26604900 | D30: =IFERROR(+VLOOKUP(B30,COMISIONES!A:E,5,FALSE),"0")*1 -> 2295395.1 | E30: 1341768.4 | F30: =+D30-E30 -> 953626.66 | G30: =+D30/C30 -> 0.086277154 | H30: =+D30/$N$3*$N$4 -> 19128292 | I30: =+H30/C30 -> 0.71897629 | J30: =+D30/$N$3 -> 765131.69 | K30: =+(C30-D30)/$N$2 -> 1104977.5 | L30: {=+_xlfn.IFS(I30>114%,H30*0.02,I30>109%,H30*0.015,I30>104%,H30*0.0125,I30>99%,H30*0.01,I30<99%,H30*0)} -> 0
B31: 28 - GOMEZ PABLO | C31: 28533060 | D31: =IFERROR(+VLOOKUP(B31,COMISIONES!A:E,5,FALSE),"0")*1 -> 2694074.2 | E31: 2031918.6 | F31: =+D31-E31 -> 662155.54 | G31: =+D31/C31 -> 0.094419392 | H31: =+D31/$N$3*$N$4 -> 22450618 | I31: =+H31/C31 -> 0.78682827 | J31: =+D31/$N$3 -> 898024.73 | K31: =+(C31-D31)/$N$2 -> 1174499.4 | L31: {=+_xlfn.IFS(I31>114%,H31*0.02,I31>109%,H31*0.015,I31>104%,H31*0.0125,I31>99%,H31*0.01,I31<99%,H31*0)} -> 0
B32: 33 - ESQUIVEL NICOLAS | C32: 24731127 | D32: =IFERROR(+VLOOKUP(B32,COMISIONES!A:E,5,FALSE),"0")*1 -> 1510107.3 | E32: 915628.2 | F32: =+D32-E32 -> 594479.14 | G32: =+D32/C32 -> 0.061060999 | H32: =+D32/$N$3*$N$4 -> 12584228 | I32: =+H32/C32 -> 0.50884166 | J32: =+D32/$N$3 -> 503369.12 | K32: =+(C32-D32)/$N$2 -> 1055500.9 | L32: {=+_xlfn.IFS(I32>114%,H32*0.02,I32>109%,H32*0.015,I32>104%,H32*0.0125,I32>99%,H32*0.01,I32<99%,H32*0)} -> 0
B33: 37 - SALAJ EMILIO | C33: 26553552 | D33: =IFERROR(+VLOOKUP(B33,COMISIONES!A:E,5,FALSE),"0")*1 -> 886833.2 | E33: 582347.37 | F33: =+D33-E33 -> 304485.83 | G33: =+D33/C33 -> 0.033397912 | H33: =+D33/$N$3*$N$4 -> 7390276.7 | I33: =+H33/C33 -> 0.27831593 | J33: =+D33/$N$3 -> 295611.07 | K33: =+(C33-D33)/$N$2 -> 1166669.1 | L33: {=+_xlfn.IFS(I33>114%,H33*0.02,I33>109%,H33*0.015,I33>104%,H33*0.0125,I33>99%,H33*0.01,I33<99%,H33*0)} -> 0
B34: 24 - AZULA NICOLAS | C34: 27174688 | D34: =IFERROR(+VLOOKUP(B34,COMISIONES!A:E,5,FALSE),"0")*1 -> 1487555.9 | E34: 830537.61 | F34: =+D34-E34 -> 657018.34 | G34: =+D34/C34 -> 0.054740498 | H34: =+D34/$N$3*$N$4 -> 12396300 | I34: =+H34/C34 -> 0.45617082 | J34: =+D34/$N$3 -> 495851.98 | K34: =+(C34-D34)/$N$2 -> 1167596.9 | L34: {=+_xlfn.IFS(I34>114%,H34*0.02,I34>109%,H34*0.015,I34>104%,H34*0.0125,I34>99%,H34*0.01,I34<99%,H34*0)} -> 0
B35: 7 - VALLEJOS EDUARDO | C35: 1.2881391e+08 | D35: =IFERROR(+VLOOKUP(B35,COMISIONES!A:E,5,FALSE),"0")*1 -> 1280810.5 | E35: -78051.42 | F35: =+D35-E35 -> 1358861.9 | G35: =+D35/C35 -> 0.0099431077 | H35: =+D35/$N$3*$N$4 -> 10673421 | I35: =+H35/C35 -> 0.082859231 | J35: =+D35/$N$3 -> 426936.84 | K35: =+(C35-D35)/$N$2 -> 5796958.8 | L35: {=+_xlfn.IFS(I35>114%,H35*0.0125,I35>109%,H35*0.01,I35>104%,H35*0.0075,I35>99%,H35*0.005,I35<99%,H35*0)} -> 0
B36: 57 - FEDERRATH MARTIN | C36: 40000000 | D36: =IFERROR(+VLOOKUP(B36,COMISIONES!A:E,5,FALSE),"0")*1 -> 8976329.5 | E36: 2660036.3 | F36: =+D36-E36 -> 6316293.2 | G36: =+D36/C36 -> 0.22440824 | H36: =+D36/$N$3*$N$4 -> 74802746 | I36: =+H36/C36 -> 1.8700687 | J36: =+D36/$N$3 -> 2992109.8 | K36: =+(C36-D36)/$N$2 -> 1410166.8 | L36: {=+_xlfn.IFS(I36>109%,H36*0.015,I36>104%,H36*0.0125,I36>99%,H36*0.01,I36<99%,H36*0)} -> 1122041.2
B37: 1 - VERA ERNESTO | C37: 38388577 | D37: =IFERROR(+VLOOKUP(B37,COMISIONES!A:E,5,FALSE),"0")*1 -> 3814536.4 | E37: 2481853 | F37: =+D37-E37 -> 1332683.4 | G37: =+D37/C37 -> 0.099366443 | H37: =+D37/$N$3*$N$4 -> 31787803 | I37: =+H37/C37 -> 0.82805369 | J37: =+D37/$N$3 -> 1271512.1 | K37: =+(C37-D37)/$N$2 -> 1571547.3 | L37: {=+_xlfn.IFS(I37>114%,H37*0.02,I37>109%,H37*0.015,I37>104%,H37*0.0125,I37>99%,H37*0.01,I37<99%,H37*0)} -> 0
C38: =SUM(C25:C37) -> 5.5046522e+08 | D38: =+SUM(D25:D37) -> 39583602 | E38: 19259697 | F38: =+D38-E38 -> 20323904 | G38: =+D38/C38 -> 0.07190936 | H38: =+D38/$N$3*$N$4 -> 3.2986335e+08 | I38: =+H38/C38 -> 0.59924467 | J38: =+D38/$N$3 -> 13194534 | K38: =+(C38-D38)/$N$2 -> 23221892
A39: MAXI | B39: 58 - BLADIMIR LEZCANO | C39: 45000000 | D39: =IFERROR(+VLOOKUP(B39,COMISIONES!A:E,5,FALSE),"0")*1 -> 5539801 | E39: 0 | F39: =+D39-E39 -> 5539801 | G39: =+D39/C39 -> 0.12310669 | H39: =+D39/$N$3*$N$4 -> 46165008 | I39: =+H39/C39 -> 1.0258891 | J39: =+D39/$N$3 -> 1846600.3 | K39: =+(C39-D39)/$N$2 -> 1793645.4 | L39: {=+_xlfn.IFS(I39>114%,H39*0.02,I39>109%,H39*0.015,I39>104%,H39*0.0125,I39>99%,H39*0.01,I39<99%,H39*0)} -> 461650.08
B40: 59 - LEIVA SILVIO | C40: 30000000 | D40: =IFERROR(+VLOOKUP(B40,COMISIONES!A:E,5,FALSE),"0")*1 -> 3747230 | E40: 0 | F40: =+D40-E40 -> 3747230 | G40: =+D40/C40 -> 0.12490767 | H40: =+D40/$N$3*$N$4 -> 31226917 | I40: =+H40/C40 -> 1.0408972 | J40: =+D40/$N$3 -> 1249076.7 | K40: =+(C40-D40)/$N$2 -> 1193307.7 | L40: {=+_xlfn.IFS(I40>114%,H40*0.02,I40>109%,H40*0.015,I40>104%,H40*0.0125,I40>99%,H40*0.01,I40<99%,H40*0)} -> 390336.46
B41: 49 - ESCOBAR RAÚL | C41: 50000000 | D41: =IFERROR(+VLOOKUP(B41,COMISIONES!A:E,5,FALSE),"0")*1 -> -379355.66 | E41: -379355.66 | F41: =+D41-E41 -> 0 | G41: =+D41/C41 -> -0.0075871131 | H41: =+D41/$N$3*$N$4 -> -3161297.1 | I41: =+H41/C41 -> -0.063225943 | J41: =+D41/$N$3 -> -126451.89 | K41: =+(C41-D41)/$N$2 -> 2289970.7 | L41: {=+_xlfn.IFS(I41>114%,H41*0.02,I41>109%,H41*0.015,I41>104%,H41*0.0125,I41>99%,H41*0.01,I41<99%,H41*0)} -> 0
B42: 56 - JUAN ANDRES SANCHEZ | C42: 65000000 | D42: =IFERROR(+VLOOKUP(B42,COMISIONES!A:E,5,FALSE),"0")*1 -> 11461106 | E42: 11461106 | F42: =+D42-E42 -> 0 | G42: =+D42/C42 -> 0.1763247 | H42: =+D42/$N$3*$N$4 -> 95509214 | I42: =+H42/C42 -> 1.4693725 | J42: =+D42/$N$3 -> 3820368.6 | K42: =+(C42-D42)/$N$2 -> 2433586.1 | L42: {=+_xlfn.IFS(I42>114%,H42*0.02,I42>109%,H42*0.015,I42>104%,H42*0.0125,I42>99%,H42*0.01,I42<99%,H42*0)} -> 1910184.3
B43: 26 - PUJOL ERNESTO | C43: 100000000 | D43: =IFERROR(+VLOOKUP(B43,COMISIONES!A:E,5,FALSE),"0")*1 -> 18154894 | E43: 18228911 | F43: =+D43-E43 -> -74017.32 | G43: =+D43/C43 -> 0.18154894 | H43: =+D43/$N$3*$N$4 -> 1.5129078e+08 | I43: =+H43/C43 -> 1.5129078 | J43: =+D43/$N$3 -> 6051631.2 | K43: =+(C43-D43)/$N$2 -> 3720232.1 | L43: {=+_xlfn.IFS(I43>114%,H43*0.02,I43>109%,H43*0.015,I43>104%,H43*0.0125,I43>99%,H43*0.01,I43<99%,H43*0)} -> 3025815.6
B44: 25 - KALATAKI GUSTAVO | C44: 100000000 | D44: =IFERROR(+VLOOKUP(B44,COMISIONES!A:E,5,FALSE),"0")*1 -> 15947351 | E44: 0 | F44: =+D44-E44 -> 15947351 | G44: =+D44/C44 -> 0.15947351 | H44: =+D44/$N$3*$N$4 -> 1.328946e+08 | I44: =+H44/C44 -> 1.328946 | J44: =+D44/$N$3 -> 5315783.8 | K44: =+(C44-D44)/$N$2 -> 3820574.9 | L44: {=+_xlfn.IFS(I44>114%,H44*0.02,I44>109%,H44*0.015,I44>104%,H44*0.0125,I44>99%,H44*0.01,I44<99%,H44*0)} -> 2657891.9
B45: 60 - SILVA ADRIAN | C45: 65000000 | D45: =IFERROR(+VLOOKUP(B45,COMISIONES!A:E,5,FALSE),"0")*1 -> 6162448.5 | E45: 6177235.9 | F45: =+D45-E45 -> -14787.365 | G45: =+D45/C45 -> 0.0948069 | H45: =+D45/$N$3*$N$4 -> 51353737 | I45: =+H45/C45 -> 0.7900575 | J45: =+D45/$N$3 -> 2054149.5 | K45: =+(C45-D45)/$N$2 -> 2674434.2 | L45: {=+_xlfn.IFS(I45>114%,H45*0.02,I45>109%,H45*0.015,I45>104%,H45*0.0125,I45>99%,H45*0.01,I45<99%,H45*0)} -> 0
B46: 43 - COLHER DIEGO | C46: 50000000 | D46: =IFERROR(+VLOOKUP(B46,COMISIONES!A:E,5,FALSE),"0")*1 -> 0 | E46: 0 | F46: =+D46-E46 -> 0 | G46: =+D46/C46 -> 0 | H46: =+D46/$N$3*$N$4 -> 0 | I46: =+H46/C46 -> 0 | J46: =+D46/$N$3 -> 0 | K46: =+(C46-D46)/$N$2 -> 2272727.3 | L46: {=+_xlfn.IFS(I46>114%,H46*0.02,I46>109%,H46*0.015,I46>104%,H46*0.0125,I46>99%,H46*0.01,I46<99%,H46*0)} -> 0
C47: =SUM(C39:C46) -> 505000000 | D47: =SUM(D39:D46) -> 60633475 | E47: 35487897 | F47: =+SUM(F39:F46) -> 25145578 | G47: =+D47/C47 -> 0.12006629 | H47: =+D47/$N$3*$N$4 -> 5.0527896e+08 | I47: =+H47/C47 -> 1.0005524 | J47: =+D47/$N$3 -> 20211158 | K47: =+(C47-D47)/$N$2 -> 20198478
A48: GENERAL | C48: =+C10+C15+C24+C38+C47 -> 1.8863202e+09 | D48: =+D38+D24+D10+D15+D47 -> 2.2806387e+08 | E48: 1.3891585e+08 | F48: =+D48-E48 -> 89148027 | G48: =+D48/C48 -> 0.12090411 | H48: =+D48/$N$3*$N$4 -> 1.9005323e+09 | I48: =+H48/C48 -> 1.0075343 | J48: =+D48/$N$3 -> 76021291 | K48: =+(C48-D48)/$N$2 -> 75375289

Sheet COBERTURA
A1: SUPERVISOR | C1: VENDEDOR | D1: COBERTURA TOTAL | E1: DIA ANTERIOR | F1: INCREMENTO DIARIO | G1: CARTERA TOTAL | H1: CCC | I1: CCC FALTANTE 85% | P1: Cod vdor | R1: Cobertura x Un de negocio
A2: MARTIN (SUPERVISOR) | B2: 22 | C2: =+AVANCE!B11 -> 22 - ALMIRON NICOLAS | D2: =H2/G2 -> 0.24050633 | E2: 33 | F2: =+H2-E2 -> -14 | G2: =VLOOKUP(B2,'Base Cobertura'!$A:$C,3,FALSE) -> 79 | H2: =VLOOKUP(B2,'Base Cobertura'!$A:$C,2,FALSE) -> 19 | I2: =(+G2*$M$2)-H2 -> 48.15 | J2: bien | K2: bien | L2: OBJETIVO | M2: 0.85 | P2: 25 | Q2: =VLOOKUP(P2,$B:$C,2,FALSE) -> 25 - KALATAKI GUSTAVO | R2: =VLOOKUP(P2,$B:$C,2,FALSE) -> 25 - KALATAKI GUSTAVO | S2: CCC | T2: CARTERA TOTAL | U2: % ALCANZADO
B3: 20 | C3: =+AVANCE!B2 -> 20 - FLORES JAVIER | D3: =H3/G3 -> 0.27826087 | E3: 126 | F3: =+H3-E3 -> -62 | G3: =VLOOKUP(B3,'Base Cobertura'!$A:$C,3,FALSE) -> 230 | H3: =VLOOKUP(B3,'Base Cobertura'!$A:$C,2,FALSE) -> 64 | I3: =(+G3*$M$2)-H3 -> 131.5 | J3: mal | K3: chaca | P3: {=+_xlfn._xlws.FILTER('Base Cobertura'!E:I,'Base Cobertura'!E:E=COBERTURA!P2)} -> 25 | Q3: 25 | R3: 135 - ALMACEN | S3: 0 | T3: 174 | U3: =+S3/T3 -> 0
B4: 15 | C4: =+AVANCE!B12 -> 15 - GALARZA GERARDO | D4: =H4/G4 -> 0.12307692 | E4: 21 | F4: =+H4-E4 -> -13 | G4: =VLOOKUP(B4,'Base Cobertura'!$A:$C,3,FALSE) -> 65 | H4: =VLOOKUP(B4,'Base Cobertura'!$A:$C,2,FALSE) -> 8 | I4: =(+G4*$M$2)-H4 -> 47.25 | J4: re bien | K4: muy bien | P4: 25 | Q4: 0 | R4: 135 - Articulos Sin Asociar Agrupacion | S4: 0 | T4: 174 | U4: =+S4/T4 -> 0
B5: 19 | C5: =+AVANCE!B3 -> 19 - GONZALEZ MARCELO | D5: =H5/G5 -> 0.26315789 | E5: 100 | F5: =+H5-E5 -> -45 | G5: =VLOOKUP(B5,'Base Cobertura'!$A:$C,3,FALSE) -> 209 | H5: =VLOOKUP(B5,'Base Cobertura'!$A:$C,2,FALSE) -> 55 | I5: =(+G5*$M$2)-H5 -> 122.65 | K5: muy bien | P5: 25 | Q5: 0 | R5: 135 - BEBIDAS | S5: 0 | T5: 174 | U5: =+S5/T5 -> 0
B6: 16 | C6: =+AVANCE!B4 -> 16 - GOMEZ MATÍAS | D6: =H6/G6 -> 0.17910448 | E6: 81 | F6: =+H6-E6 -> -45 | G6: =VLOOKUP(B6,'Base Cobertura'!$A:$C,3,FALSE) -> 201 | H6: =VLOOKUP(B6,'Base Cobertura'!$A:$C,2,FALSE) -> 36 | I6: =(+G6*$M$2)-H6 -> 134.85 | J6: apretarlo | K6: apretarlo | P6: 25 | Q6: 0 | R6: 135 - CHOCOLATE | S6: 0 | T6: 174 | U6: =+S6/T6 -> 0
B7: 12 | C7: =+AVANCE!B5 -> 12 - GUTIERREZ MARCOS DAVID | D7: =H7/G7 -> 0.21596244 | E7: 89 | F7: =+H7-E7 -> -43 | G7: =VLOOKUP(B7,'Base Cobertura'!$A:$C,3,FALSE) -> 213 | H7: =VLOOKUP(B7,'Base Cobertura'!$A:$C,2,FALSE) -> 46 | I7: =(+G7*$M$2)-H7 -> 135.05 | J7: apretarlo | K7: apretarlo | P7: 25 | Q7: 0 | R7: 135 - GALLETITAS | S7: 0 | T7: 174 | U7: =+S7/T7 -> 0
B8: 11 | C8: =+AVANCE!B6 -> 11 - SANCHEZ RICARDO | D8: =H8/G8 -> 0.25 | E8: 92 | F8: =+H8-E8 -> -50 | G8: =VLOOKUP(B8,'Base Cobertura'!$A:$C,3,FALSE) -> 168 | H8: =VLOOKUP(B8,'Base Cobertura'!$A:$C,2,FALSE) -> 42 | I8: =(+G8*$M$2)-H8 -> 100.8 | J8: bien | K8: apretarlo | P8: 25 | Q8: 0 | R8: 135 - GOLOSINAS | S8: 0 | T8: 174 | U8: =+S8/T8 -> 0
B9: 8 | C9: =+AVANCE!B7 -> 8 - PARRA MAXIMILIANO | D9: =H9/G9 -> 0.21674877 | E9: 64 | F9: =+H9-E9 -> -20 | G9: =VLOOKUP(B9,'Base Cobertura'!$A:$C,3,FALSE) -> 203 | H9: =VLOOKUP(B9,'Base Cobertura'!$A:$C,2,FALSE) -> 44 | I9: =(+G9*$M$2)-H9 -> 128.55 | J9: bien | K9: apretarlo con ema | P9: 25 | Q9: 0 | R9: 135 - MASCOTAS | S9: 0 | T9: 174 | U9: =+S9/T9 -> 0
B10: 52 | C10: =+AVANCE!B13 -> 52 - RAVAROTTO EMANUEL | D10: =H10/G10 -> 0.11214953 | E10: 19 | F10: =+H10-E10 -> -7 | G10: =VLOOKUP(B10,'Base Cobertura'!$A:$C,3,FALSE) -> 107 | H10: =VLOOKUP(B10,'Base Cobertura'!$A:$C,2,FALSE) -> 12 | I10: =(+G10*$M$2)-H10 -> 78.95 | J10: apretarlo | K10: apretarlo | P10: 25 | Q10: 0 | R10: 135 - NO PERECEDEROS | S10: 0 | T10: 174 | U10: =+S10/T10 -> 0
B11: 53 | C11: =+AVANCE!B14 -> 53 - SANDOVAL RODRIGO | D11: =H11/G11 -> 0.1047619 | E11: 24 | F11: =+H11-E11 -> -13 | G11: =VLOOKUP(B11,'Base Cobertura'!$A:$C,3,FALSE) -> 105 | H11: =VLOOKUP(B11,'Base Cobertura'!$A:$C,2,FALSE) -> 11 | I11: =(+G11*$M$2)-H11 -> 78.25 | J11: verlo | P11: 25 | Q11: 0 | R11: 135 - PILAS | S11: 0 | T11: 174 | U11: =+S11/T11 -> 0
B12: 5 | C12: =+AVANCE!B8 -> 5 - SCHELOVER RAUL | D12: =H12/G12 -> 0.30075188 | E12: 144 | F12: =+H12-E12 -> -64 | G12: =VLOOKUP(B12,'Base Cobertura'!$A:$C,3,FALSE) -> 266 | H12: =VLOOKUP(B12,'Base Cobertura'!$A:$C,2,FALSE) -> 80 | I12: =(+G12*$M$2)-H12 -> 146.1 | J12: verlo
B13: 4 | C13: =+AVANCE!B9 -> 4 - TUR SPRINGER FERNANDO | D13: =H13/G13 -> 0.2295082 | E13: 85 | F13: =+H13-E13 -> -43 | G13: =VLOOKUP(B13,'Base Cobertura'!$A:$C,3,FALSE) -> 183 | H13: =VLOOKUP(B13,'Base Cobertura'!$A:$C,2,FALSE) -> 42 | I13: =(+G13*$M$2)-H13 -> 113.55 | J13: re bien | K13: muy bien
F14: =+SUM(F1:F13) -> -419 | G14: =+SUM(G1:G13) -> 2029 | H14: =+SUM(H1:H13) -> 459 | J14: bien | K14: muy bien
A15: CRISTIAN (SUPERVISOR) | B15: 31 | C15: =+AVANCE!B21 -> 31 - RENZO RAMOS | D15: =H15/G15 -> 0.23121387 | E15: 90 | F15: =+H15-E15 -> -50 | G15: =VLOOKUP(B15,'Base Cobertura'!$A:$C,3,FALSE) -> 173 | H15: =VLOOKUP(B15,'Base Cobertura'!$A:$C,2,FALSE) -> 40 | I15: =(+G15*$M$2)-H15 -> 107.05 | J15: bien | K15: bien
B16: 54 | C16: =+AVANCE!B23 -> 54 - BARTSCHAT EMILIANO NAHUEL | D16: =H16/G16 -> 0.21463415 | E16: 92 | F16: =+H16-E16 -> -48 | G16: =VLOOKUP(B16,'Base Cobertura'!$A:$C,3,FALSE) -> 205 | H16: =VLOOKUP(B16,'Base Cobertura'!$A:$C,2,FALSE) -> 44 | I16: =(+G16*$M$2)-H16 -> 130.25 | J16: bien | K16: chaca
B17: 21 | C17: =+AVANCE!B19 -> 21 - CATAN MATIAS | D17: =H17/G17 -> 0.34337349 | E17: 88 | F17: =+H17-E17 -> -31 | G17: =VLOOKUP(B17,'Base Cobertura'!$A:$C,3,FALSE) -> 166 | H17: =VLOOKUP(B17,'Base Cobertura'!$A:$C,2,FALSE) -> 57 | I17: =(+G17*$M$2)-H17 -> 84.1 | J17: apretarlo | K17: bien
B18: 23 | C18: =+AVANCE!B20 -> 23 - DELGADO JOSÉ | D18: =H18/G18 -> 0.37341772 | E18: 95 | F18: =+H18-E18 -> -36 | G18: =VLOOKUP(B18,'Base Cobertura'!$A:$C,3,FALSE) -> 158 | H18: =VLOOKUP(B18,'Base Cobertura'!$A:$C,2,FALSE) -> 59 | I18: =(+G18*$M$2)-H18 -> 75.3 | J18: apretarlo | K18: muy bien
B19: 18 | C19: =+AVANCE!B18 -> 18 - HERRERA PABLO | D19: =H19/G19 -> 0.28571429 | E19: 83 | F19: =+H19-E19 -> -31 | G19: =VLOOKUP(B19,'Base Cobertura'!$A:$C,3,FALSE) -> 182 | H19: =VLOOKUP(B19,'Base Cobertura'!$A:$C,2,FALSE) -> 52 | I19: =(+G19*$M$2)-H19 -> 102.7 | J19: bien | K19: bien
B20: 44 | C20: =+AVANCE!B22 -> 44 - MONGES CESAR LUIS | D20: =H20/G20 -> 0.21264368 | E20: 64 | F20: =+H20-E20 -> -27 | G20: =VLOOKUP(B20,'Base Cobertura'!$A:$C,3,FALSE) -> 174 | H20: =VLOOKUP(B20,'Base Cobertura'!$A:$C,2,FALSE) -> 37 | I20: =(+G20*$M$2)-H20 -> 110.9 | J20: apretarlo | K20: muy bien
B21: 2 | C21: =+AVANCE!B16 -> 2 - OJEDA NORBERTO | D21: =H21/G21 -> 0.23387097 | E21: 70 | F21: =+H21-E21 -> -41 | G21: =VLOOKUP(B21,'Base Cobertura'!$A:$C,3,FALSE) -> 124 | H21: =VLOOKUP(B21,'Base Cobertura'!$A:$C,2,FALSE) -> 29 | I21: =(+G21*$M$2)-H21 -> 76.4 | J21: apretarlo | K21: apretar
B22: 3 | C22: =+AVANCE!B17 -> 3 - VIDAL NAHUEL | D22: =H22/G22 -> 0.33526012 | E22: 79 | F22: =+H22-E22 -> -21 | G22: =VLOOKUP(B22,'Base Cobertura'!$A:$C,3,FALSE) -> 173 | H22: =VLOOKUP(B22,'Base Cobertura'!$A:$C,2,FALSE) -> 58 | I22: =(+G22*$M$2)-H22 -> 89.05 | J22: abrazo | K22: muy bien
F23: =+SUM(F15:F22) -> -285 | G23: =+SUM(G15:G22) -> 1355 | H23: =+SUM(H15:H22) -> 376
A24: GONZALO (SUPERVISOR) | B24: 32 | C24: =+AVANCE!B25 -> 32 - CABRAL GONZALO | D24: =H24/G24 -> 0.10344828 | E24: 20 | F24: =+H24-E24 -> -14 | G24: =VLOOKUP(B24,'Base Cobertura'!$A:$C,3,FALSE) -> 58 | H24: =VLOOKUP(B24,'Base Cobertura'!$A:$C,2,FALSE) -> 6 | I24: =(+G24*$M$2)-H24 -> 43.3 | J24: bien | K24: apretar
B25: 36 | C25: =+AVANCE!B26 -> 36 - IBARROLA JORGE | D25: =H25/G25 -> 0.16149068 | E25: 68 | F25: =+H25-E25 -> -42 | G25: =VLOOKUP(B25,'Base Cobertura'!$A:$C,3,FALSE) -> 161 | H25: =VLOOKUP(B25,'Base Cobertura'!$A:$C,2,FALSE) -> 26 | I25: =(+G25*$M$2)-H25 -> 110.85 | J25: apretarlo | K25: apretar
B26: 9 | C26: =+AVANCE!B27 -> 9 - ESTIGARRIBIA DAVID | D26: =H26/G26 -> 0.25503356 | E26: 80 | F26: =+H26-E26 -> -42 | G26: =VLOOKUP(B26,'Base Cobertura'!$A:$C,3,FALSE) -> 149 | H26: =VLOOKUP(B26,'Base Cobertura'!$A:$C,2,FALSE) -> 38 | I26: =(+G26*$M$2)-H26 -> 88.65 | J26: apretarlo | K26: bien
B27: 40 | C27: =+AVANCE!B28 -> 40 - SOLIS EMMANUEL | D27: =H27/G27 -> 0.10572687 | E27: 68 | F27: =+H27-E27 -> -44 | G27: =VLOOKUP(B27,'Base Cobertura'!$A:$C,3,FALSE) -> 227 | H27: =VLOOKUP(B27,'Base Cobertura'!$A:$C,2,FALSE) -> 24 | I27: =(+G27*$M$2)-H27 -> 168.95 | J27: apretarlo | K27: apretar
B28: 27 | C28: =+AVANCE!B29 -> 27 - GOMEZ ADRIÁN | D28: =H28/G28 -> 0.30534351 | E28: 73 | F28: =+H28-E28 -> -33 | G28: =VLOOKUP(B28,'Base Cobertura'!$A:$C,3,FALSE) -> 131 | H28: =VLOOKUP(B28,'Base Cobertura'!$A:$C,2,FALSE) -> 40 | I28: =(+G28*$M$2)-H28 -> 71.35 | J28: bien | K28: apretar
B29: 10 | C29: =+AVANCE!B30 -> 10 - BRITEZ EMMANUEL | D29: =H29/G29 -> 0.18787879 | E29: 40 | F29: =+H29-E29 -> -9 | G29: =VLOOKUP(B29,'Base Cobertura'!$A:$C,3,FALSE) -> 165 | H29: =VLOOKUP(B29,'Base Cobertura'!$A:$C,2,FALSE) -> 31 | I29: =(+G29*$M$2)-H29 -> 109.25 | J29: apretarlo | K29: apretar
B30: 28 | C30: =+AVANCE!B31 -> 28 - GOMEZ PABLO | D30: =H30/G30 -> 0.29299363 | E30: 67 | F30: =+H30-E30 -> -21 | G30: =VLOOKUP(B30,'Base Cobertura'!$A:$C,3,FALSE) -> 157 | H30: =VLOOKUP(B30,'Base Cobertura'!$A:$C,2,FALSE) -> 46 | I30: =(+G30*$M$2)-H30 -> 87.45 | J30: apretarlo | K30: apretar
B31: 33 | C31: =+AVANCE!B32 -> 33 - ESQUIVEL NICOLAS | D31: =H31/G31 -> 0.15204678 | E31: 66 | F31: =+H31-E31 -> -40 | G31: =VLOOKUP(B31,'Base Cobertura'!$A:$C,3,FALSE) -> 171 | H31: =VLOOKUP(B31,'Base Cobertura'!$A:$C,2,FALSE) -> 26 | I31: =(+G31*$M$2)-H31 -> 119.35 | J31: apretarlo | K31: apretar
B32: 37 | C32: =+AVANCE!B33 -> 37 - SALAJ EMILIO | D32: =H32/G32 -> 0.14864865 | E32: 82 | F32: =+H32-E32 -> -60 | G32: =VLOOKUP(B32,'Base Cobertura'!$A:$C,3,FALSE) -> 148 | H32: =VLOOKUP(B32,'Base Cobertura'!$A:$C,2,FALSE) -> 22 | I32: =(+G32*$M$2)-H32 -> 103.8 | J32: bien | K32: apretar
B33: 24 | C33: =+AVANCE!B34 -> 24 - AZULA NICOLAS | D33: =H33/G33 -> 0.12716763 | E33: 81 | F33: =+H33-E33 -> -59 | G33: =VLOOKUP(B33,'Base Cobertura'!$A:$C,3,FALSE) -> 173 | H33: =VLOOKUP(B33,'Base Cobertura'!$A:$C,2,FALSE) -> 22 | I33: =(+G33*$M$2)-H33 -> 125.05 | J33: apretarlo | K33: apretar
B34: 7 | C34: =+AVANCE!B35 -> 7 - VALLEJOS EDUARDO | D34: =H34/G34 -> 0.0086206897 | E34: 0 | F34: =+H34-E34 -> 1 | G34: =VLOOKUP(B34,'Base Cobertura'!$A:$C,3,FALSE) -> 116 | H34: =VLOOKUP(B34,'Base Cobertura'!$A:$C,2,FALSE) -> 1 | I34: =(+G34*$M$2)-H34 -> 97.6 | J34: apretarlo
B35: 57 | C35: =+AVANCE!B36 -> 57 - FEDERRATH MARTIN | D35: =H35/G35 -> 0.12149533 | E35: 17 | F35: =+H35-E35 -> -4 | G35: =VLOOKUP(B35,'Base Cobertura'!$A:$C,3,FALSE) -> 107 | H35: =VLOOKUP(B35,'Base Cobertura'!$A:$C,2,FALSE) -> 13 | I35: =(+G35*$M$2)-H35 -> 77.95 | J35: verlo
B36: 1 | C36: =+AVANCE!B37 -> 1 - VERA ERNESTO | D36: =H36/G36 -> 0.29565217 | E36: 60 | F36: =+H36-E36 -> -26 | G36: =VLOOKUP(B36,'Base Cobertura'!$A:$C,3,FALSE) -> 115 | H36: =VLOOKUP(B36,'Base Cobertura'!$A:$C,2,FALSE) -> 34 | I36: =(+G36*$M$2)-H36 -> 63.75 | J36: bien | K36: bien
F37: =+SUM(F24:F36) -> -393 | G37: =+SUM(G24:G36) -> 1878 | H37: =+SUM(H24:H36) -> 329
A38: MAXI (SUPERVISOR) | B38: 58 | C38: =+AVANCE!B39 -> 58 - BLADIMIR LEZCANO | D38: =H38/G38 -> 0 | E38: 60 | F38: =+H38-E38 -> -60 | G38: =VLOOKUP(B38,'Base Cobertura'!$A:$C,3,FALSE) -> 83 | H38: =VLOOKUP(B38,'Base Cobertura'!$A:$C,2,FALSE) -> 0 | I38: =(+G38*$M$2)-H38 -> 70.55
B39: 59 | C39: =+AVANCE!B40 -> 59 - LEIVA SILVIO | D39: =H39/G39 -> 0 | E39: 60 | F39: =+H39-E39 -> -60 | G39: =VLOOKUP(B39,'Base Cobertura'!$A:$C,3,FALSE) -> 128 | H39: =VLOOKUP(B39,'Base Cobertura'!$A:$C,2,FALSE) -> 0 | I39: =(+G39*$M$2)-H39 -> 108.8
B40: 49 | C40: =+AVANCE!B41 -> 49 - ESCOBAR RAÚL | D40: =H40/G40 -> 0 | E40: 60 | F40: =+H40-E40 -> -60 | G40: =VLOOKUP(B40,'Base Cobertura'!$A:$C,3,FALSE) -> 247 | H40: =VLOOKUP(B40,'Base Cobertura'!$A:$C,2,FALSE) -> 0 | I40: =(+G40*$M$2)-H40 -> 209.95
B41: 56 | C41: =+AVANCE!B42 -> 56 - JUAN ANDRES SANCHEZ | D41: =H41/G41 -> 0.15841584 | E41: 60 | F41: =+H41-E41 -> -28 | G41: =VLOOKUP(B41,'Base Cobertura'!$A:$C,3,FALSE) -> 202 | H41: =VLOOKUP(B41,'Base Cobertura'!$A:$C,2,FALSE) -> 32 | I41: =(+G41*$M$2)-H41 -> 139.7
B42: 26 | C42: =+AVANCE!B43 -> 26 - PUJOL ERNESTO | D42: =H42/G42 -> 0.22988506 | E42: 60 | F42: =+H42-E42 -> -20 | G42: =VLOOKUP(B42,'Base Cobertura'!$A:$C,3,FALSE) -> 174 | H42: =VLOOKUP(B42,'Base Cobertura'!$A:$C,2,FALSE) -> 40 | I42: =(+G42*$M$2)-H42 -> 107.9
B43: 25 | C43: =+AVANCE!B44 -> 25 - KALATAKI GUSTAVO | D43: =H43/G43 -> 0 | E43: 60 | F43: =+H43-E43 -> -60 | G43: =VLOOKUP(B43,'Base Cobertura'!$A:$C,3,FALSE) -> 174 | H43: =VLOOKUP(B43,'Base Cobertura'!$A:$C,2,FALSE) -> 0 | I43: =(+G43*$M$2)-H43 -> 147.9
B44: 60 | C44: =+AVANCE!B45 -> 60 - SILVA ADRIAN | D44: =H44/G44 -> 0.14606742 | E44: 61 | F44: =+H44-E44 -> -48 | G44: =VLOOKUP(B44,'Base Cobertura'!$A:$C,3,FALSE) -> 89 | H44: =VLOOKUP(B44,'Base Cobertura'!$A:$C,2,FALSE) -> 13 | I44: =(+G44*$M$2)-H44 -> 62.65
B45: 43 | C45: =+AVANCE!B46 -> 43 - COLHER DIEGO | D45: =H45/G45 -> 0 | E45: 60 | F45: =+H45-E45 -> -60 | G45: =VLOOKUP(B45,'Base Cobertura'!$A:$C,3,FALSE) -> 93 | H45: =VLOOKUP(B45,'Base Cobertura'!$A:$C,2,FALSE) -> 0 | I45: =(+G45*$M$2)-H45 -> 79.05
G46: =+SUM(G32:G45) -> 3727 | H46: =+SUM(H32:H45) -> 506 | L46: TOTAL CANALES
A47: LOPEZ ENZO | F47: =+SUM(F37+F23+#REF!) -> #REF! | G47: =+G46+G23+G37+G14 -> 8989 | H47: =+H46+H23+H37+H14 -> 1670 | L47: =+H47/G47 -> 0.18578262

Sheet Cantidad Sku
B1: Cantidad skus
A2: Supervisor Cristian | E2: Vendedores Mayoristas | G2: Cantidad skus
A3: Cod vdor | C3: Cantidad skus | E3: 15 | F3: GALARZA GERARDO | G3: =SUMIFS('Base SKU'!$AM:$AM,'Base SKU'!$E:$E,E3,'Base SKU'!$AM:$AM,1) -> 72
A4: 2 | B4: OJEDA NORBERTO | C4: =SUMIFS('Base SKU'!$AM:$AM,'Base SKU'!$E:$E,A4,'Base SKU'!$AM:$AM,1) -> 135 | E4: 7 | F4: VALLEJOS EDUARDO | G4: 128
A5: 3 | B5: VIDAL NAHUEL | C5: =SUMIFS('Base SKU'!$AM:$AM,'Base SKU'!$E:$E,A5,'Base SKU'!$AM:$AM,1) -> 203
A6: 18 | B6: HERRERA PABLO | C6: =SUMIFS('Base SKU'!$AM:$AM,'Base SKU'!$E:$E,A6,'Base SKU'!$AM:$AM,1) -> 178
A7: 21 | B7: CATAN MATIAS | C7: =SUMIFS('Base SKU'!$AM:$AM,'Base SKU'!$E:$E,A7,'Base SKU'!$AM:$AM,1) -> 202
A8: 23 | B8: DELGADO JOSÉ | C8: =SUMIFS('Base SKU'!$AM:$AM,'Base SKU'!$E:$E,A8,'Base SKU'!$AM:$AM,1) -> 171 | E8: Vendedores Supermercados | G8: Cantidad skus
A9: 31 | B9: RENZO RAMOS | C9: =SUMIFS('Base SKU'!$AM:$AM,'Base SKU'!$E:$E,A9,'Base SKU'!$AM:$AM,1) -> 201 | E9: 22 | F9: ALMIRON NICOLAS | G9: =SUMIFS('Base SKU'!$AM:$AM,'Base SKU'!$E:$E,E9,'Base SKU'!$AM:$AM,1) -> 207
A10: 44 | B10: MONGES CESAR LUIS | C10: =SUMIFS('Base SKU'!$AM:$AM,'Base SKU'!$E:$E,A10,'Base SKU'!$AM:$AM,1) -> 149 | E10: 32 | F10: CABRAL GONZALO | G10: =SUMIFS('Base SKU'!$AM:$AM,'Base SKU'!$E:$E,E10,'Base SKU'!$AM:$AM,1) -> 100
A11: 54 | B11: BARTSCHAT EMILIANO NAHUEL | C11: =SUMIFS('Base SKU'!$AM:$AM,'Base SKU'!$E:$E,A11,'Base SKU'!$AM:$AM,1) -> 191
A12: Totales | E12: Supervisior Maxi | G12: Cantidad skus
A13: Supervisor Martin | C13: Cantidad skus | E13: 58 | F13: BLADIMIR LEZCANO | G13: =SUMIFS('Base SKU'!$AM:$AM,'Base SKU'!$E:$E,E13,'Base SKU'!$AM:$AM,1) -> 125
A14: 4 | B14: TUR SPRINGER FERNANDO | C14: =SUMIFS('Base SKU'!$AM:$AM,'Base SKU'!$E:$E,A14,'Base SKU'!$AM:$AM,1) -> 174 | E14: 59 | F14: LEIVA SILVIO | G14: =SUMIFS('Base SKU'!$AM:$AM,'Base SKU'!$E:$E,E14,'Base SKU'!$AM:$AM,1) -> 107
A15: 5 | B15: SCHELOVER RAUL | C15: =SUMIFS('Base SKU'!$AM:$AM,'Base SKU'!$E:$E,A15,'Base SKU'!$AM:$AM,1) -> 207 | E15: 60 | F15: SILVA ADRIAN | G15: =SUMIFS('Base SKU'!$AM:$AM,'Base SKU'!$E:$E,E15,'Base SKU'!$AM:$AM,1) -> 74
A16: 8 | B16: PARRA MAXIMILIANO | C16: =SUMIFS('Base SKU'!$AM:$AM,'Base SKU'!$E:$E,A16,'Base SKU'!$AM:$AM,1) -> 133 | E16: 56 | F16: JUAN ANDRES SANCHEZ | G16: =SUMIFS('Base SKU'!$AM:$AM,'Base SKU'!$E:$E,E16,'Base SKU'!$AM:$AM,1) -> 149
A17: 11 | B17: SANCHEZ RICARDO | C17: =SUMIFS('Base SKU'!$AM:$AM,'Base SKU'!$E:$E,A17,'Base SKU'!$AM:$AM,1) -> 153 | E17: 26 | F17: PUJOL ERNESTO | G17: =SUMIFS('Base SKU'!$AM:$AM,'Base SKU'!$E:$E,E17,'Base SKU'!$AM:$AM,1) -> 166
A18: 12 | B18: GUTIERREZ MARCOS DAVID | C18: =SUMIFS('Base SKU'!$AM:$AM,'Base SKU'!$E:$E,A18,'Base SKU'!$AM:$AM,1) -> 157 | E18: 25 | F18: KALATAKI GUSTAVO | G18: =SUMIFS('Base SKU'!$AM:$AM,'Base SKU'!$E:$E,E18,'Base SKU'!$AM:$AM,1) -> 182
A19: 16 | B19: GOMEZ MATÍAS | C19: =SUMIFS('Base SKU'!$AM:$AM,'Base SKU'!$E:$E,A19,'Base SKU'!$AM:$AM,1) -> 130 | E19: 43 | F19: COLHER DIEGO | G19: =SUMIFS('Base SKU'!$AM:$AM,'Base SKU'!$E:$E,E19,'Base SKU'!$AM:$AM,1) -> 0
A20: 19 | B20: GONZALEZ MARCELO | C20: =SUMIFS('Base SKU'!$AM:$AM,'Base SKU'!$E:$E,A20,'Base SKU'!$AM:$AM,1) -> 195 | E20: 49 | F20: ESCOBAR RAÚL | G20: =SUMIFS('Base SKU'!$AM:$AM,'Base SKU'!$E:$E,E20,'Base SKU'!$AM:$AM,1) -> 13
A21: 20 | B21: FLORES JAVIER | C21: =SUMIFS('Base SKU'!$AM:$AM,'Base SKU'!$E:$E,A21,'Base SKU'!$AM:$AM,1) -> 186
A22: Totales | E22: Vendedores PETS | G22: Cantidad skus
A23: Supervision Corrientes | C23: Cantidad skus | E23: 52 | F23: RAVAROTTO EMANUEL | G23: =SUMIFS('Base SKU'!$AM:$AM,'Base SKU'!$E:$E,E23,'Base SKU'!$AM:$AM,1) -> 61
A24: 1 | B24: VERA ERNESTO | C24: =SUMIFS('Base SKU'!$AM:$AM,'Base SKU'!$E:$E,A24,'Base SKU'!$AM:$AM,1) -> 165 | E24: 53 | F24: SANDOVAL RODRIGO | G24: =SUMIFS('Base SKU'!$AM:$AM,'Base SKU'!$E:$E,E24,'Base SKU'!$AM:$AM,1) -> 66
A25: 9 | B25: ESTIGARRIBIA DAVID | C25: =SUMIFS('Base SKU'!$AM:$AM,'Base SKU'!$E:$E,A25,'Base SKU'!$AM:$AM,1) -> 133 | E25: 57 | F25: FEDERRATH MARTIN | G25: =SUMIFS('Base SKU'!$AM:$AM,'Base SKU'!$E:$E,E25,'Base SKU'!$AM:$AM,1) -> 56
A26: 10 | B26: BRITEZ EMMANUEL | C26: =SUMIFS('Base SKU'!$AM:$AM,'Base SKU'!$E:$E,A26,'Base SKU'!$AM:$AM,1) -> 127
A27: 24 | B27: SOLIS EMMANUEL | C27: =SUMIFS('Base SKU'!$AM:$AM,'Base SKU'!$E:$E,A27,'Base SKU'!$AM:$AM,1) -> 90
A28: 27 | B28: GOMEZ ADRIÁN | C28: =SUMIFS('Base SKU'!$AM:$AM,'Base SKU'!$E:$E,A28,'Base SKU'!$AM:$AM,1) -> 153
A29: 28 | B29: GOMEZ PABLO | C29: =SUMIFS('Base SKU'!$AM:$AM,'Base SKU'!$E:$E,A29,'Base SKU'!$AM:$AM,1) -> 145
A30: 33 | B30: NICOLAS AZULA | C30: =SUMIFS('Base SKU'!$AM:$AM,'Base SKU'!$E:$E,A30,'Base SKU'!$AM:$AM,1) -> 109
A31: 36 | B31: COSARINSKI DIEGO | C31: =SUMIFS('Base SKU'!$AM:$AM,'Base SKU'!$E:$E,A31,'Base SKU'!$AM:$AM,1) -> 88
A32: 37 | B32: SALAJ EMILIO | C32: =SUMIFS('Base SKU'!$AM:$AM,'Base SKU'!$E:$E,A32,'Base SKU'!$AM:$AM,1) -> 69
A33: 40 | B33: IBARROLA JORGE | C33: =SUMIFS('Base SKU'!$AM:$AM,'Base SKU'!$E:$E,A33,'Base SKU'!$AM:$AM,1) -> 152
A34: Totales

Sheet Base SKU
A1: Periodos | B1: Cod. Período | C1: Descripción Período | D1: Vendedor según comprobante | E1: Código | F1: Descripción | G1: Artículos | H1: Código | I1: Descripción | J1: Marca | K1: Descripción | L1: Detalle | M1: Calibre | N1: Descripción | O1: Detalle | P1: División | Q1: Descripción | R1: Detalle | S1: Producto Estadístico | T1: Descripción | U1: Detalle | V1: Sabor | W1: Descripción | X1: Detalle | Y1: Unidad de Negocio | Z1: Descripción | AA1: Detalle | AB1: P.P.P. Neto | AC1: P.P.P. Final | AD1: Cantidades CON Cargo | AE1: Cantidades SIN Cargo | AF1: Cantidades Totales | AG1: Pesos Totales | AH1: Importes Netos | AI1: Importes Finales | AJ1: Cantidad de Facturas | AK1: Bultos Promedio | AL1: Cantidades en Combos
A2: (001) 01 SEP 2026 - 03 SEP 2026 | B2: 1 | C2: 01 SEP 2026 - 03 SEP 2026 | D2: Suc: 001 (000001) VERA ERNESTO | E2: 1 | F2: VERA ERNESTO | G2: (000001) PILA E 91AA X 4U ENERGIZER ALCALINA | H2: 1 | I2: PILA E 91AA X 4U ENERGIZER ALCALINA | J2: 1019 | K2: ENERGIZER | L2: 1019 - ENERGIZER | P2: 1020 | Q2: PILA | R2: 1020 - PILA | Y2: 1402 | Z2: PILAS | AA2: 1402 - PILAS | AB2: 246389.6 | AC2: 301827.26 | AD2: 0.1 | AE2: 0 | AF2: 0.1 | AG2: 0 | AH2: 24638.96 | AI2: 30182.73 | AJ2: 1 | AK2: 0.1 | AL2: 0 | AM2: 1 | AN2: =VLOOKUP(H2,'Base Art'!$A:$AJ,36,FALSE) -> ENERGIZER ARGENTINA S.A.
A3: (001) 01 SEP 2026 - 03 SEP 2026 | B3: 1 | C3: 01 SEP 2026 - 03 SEP 2026 | D3: Suc: 001 (000001) VERA ERNESTO | E3: 1 | F3: VERA ERNESTO | G3: (000005) BATERIA 9V X 1U -522BP ENERGIZER ALCALIN | H3: 5 | I3: BATERIA 9V X 1U -522BP ENERGIZER ALCALIN | J3: 1019 | K3: ENERGIZER | L3: 1019 - ENERGIZER | P3: 1020 | Q3: PILA | R3: 1020 - PILA | Y3: 1402 | Z3: PILAS | AA3: 1402 - PILAS | AB3: 177045.47 | AC3: 216880.7 | AD3: 0.0833 | AE3: 0 | AF3: 0.0833 | AG3: 0 | AH3: 14753.79 | AI3: 18073.39 | AJ3: 1 | AK3: 0.08 | AL3: 0 | AM3: 1 | AN3: =VLOOKUP(H3,'Base Art'!$A:$AJ,36,FALSE) -> ENERGIZER ARGENTINA S.A.
A4: (001) 01 SEP 2026 - 03 SEP 2026 | B4: 1 | C4: 01 SEP 2026 - 03 SEP 2026 | D4: Suc: 001 (000001) VERA ERNESTO | E4: 1 | F4: VERA ERNESTO | G4: (000027) PEDIGREE ADTO RAZ PEQ ETAPA2 X1,5KG | H4: 27 | I4: PEDIGREE ADTO RAZ PEQ ETAPA2 X1,5KG | J4: 1194 | K4: PEDIGREE MARCA | L4: 1194 - PEDIGREE MARCA | P4: 1098 | Q4: PAQUETERIA WHISKAS Y PEDIG | R4: 1098 - PAQUETERIA WHISKAS Y PEDIG | Y4: 1375 | Z4: MASCOTAS | AA4: 1375 - MASCOTAS | AB4: 37205.401 | AC4: 45576.619 | AD4: 0.2222 | AE4: 0 | AF4: 0.2222 | AG4: 0 | AH4: 8267.87 | AI4: 10128.14 | AJ4: 0 | AK4: 0 | AL4: 0 | AM4: 1 | AN4: =VLOOKUP(H4,'Base Art'!$A:$AJ,36,FALSE) -> MASTERFOODS ARGENTINA LTD.
A5: (001) 01 SEP 2026 - 03 SEP 2026 | B5: 1 | C5: 01 SEP 2026 - 03 SEP 2026 | D5: Suc: 001 (000001) VERA ERNESTO | E5: 1 | F5: VERA ERNESTO | G5: (000156) LA GOTITA X 2 ML CHICA | H5: 156 | I5: LA GOTITA X 2 ML CHICA | J5: 1437 | K5: LA GOTITA | L5: 1437 - LA GOTITA | Y5: 1376 | Z5: NO PERECEDEROS | AA5: 1376 - NO PERECEDEROS | AB5: 352614.34 | AC5: 431952.58 | AD5: 0.175 | AE5: 0 | AF5: 0.175 | AG5: 0 | AH5: 61707.51 | AI5: 75591.7 | AJ5: 3 | AK5: 0.06 | AL5: 0 | AM5: 1 | AN5: =VLOOKUP(H5,'Base Art'!$A:$AJ,36,FALSE) -> JORGE LUIS SUAREZ
A6: (001) 01 SEP 2026 - 03 SEP 2026 | B6: 1 | C6: 01 SEP 2026 - 03 SEP 2026 | D6: Suc: 001 (000001) VERA ERNESTO | E6: 1 | F6: VERA ERNESTO | G6: (000158) LA GOTITA GEL X 3 GR CHICO | H6: 158 | I6: LA GOTITA GEL X 3 GR CHICO | J6: 1437 | K6: LA GOTITA | L6: 1437 - LA GOTITA | Y6: 1376 | Z6: NO PERECEDEROS | AA6: 1376 - NO PERECEDEROS | AB6: 421734.78 | AC6: 516625.09 | AD6: 0.125 | AE6: 0 | AF6: 0.125 | AG6: 0 | AH6: 52716.85 | AI6: 64578.14 | AJ6: 0 | AK6: 0 | AL6: 0 | AM6: 1 | AN6: =VLOOKUP(H6,'Base Art'!$A:$AJ,36,FALSE) -> JORGE LUIS SUAREZ
A7: (001) 01 SEP 2026 - 03 SEP 2026 | B7: 1 | C7: 01 SEP 2026 - 03 SEP 2026 | D7: Suc: 001 (000001) VERA ERNESTO | E7: 1 | F7: VERA ERNESTO | G7: (000164) POXIPOL 10' X 14 ML. TPTE. CHICO | H7: 164 | I7: POXIPOL 10' X 14 ML. TPTE. CHICO | J7: 1439 | K7: POXIPOL | L7: 1439 - POXIPOL | Y7: 1376 | Z7: NO PERECEDEROS | AA7: 1376 - NO PERECEDEROS | AB7: 1097448.9 | AC7: 1344374.9 | AD7: 0.025 | AE7: 0 | AF7: 0.025 | AG7: 0 | AH7: 27436.22 | AI7: 33609.37 | AJ7: 0 | AK7: 0 | AL7: 0 | AM7: 1 | AN7: =VLOOKUP(H7,'Base Art'!$A:$AJ,36,FALSE) -> JORGE LUIS SUAREZ
A8: (001) 01 SEP 2026 - 03 SEP 2026 | B8: 1 | C8: 01 SEP 2026 - 03 SEP 2026 | D8: Suc: 001 (000001) VERA ERNESTO | E8: 1 | F8: VERA ERNESTO | G8: (000273) ALKA CARAMELOS STRONG X 800 GR | H8: 273 | I8: ALKA CARAMELOS STRONG X 800 GR | J8: 1413 | K8: ALKA | L8: 1413 - ALKA | Y8: 1374 | Z8: GOLOSINAS | AA8: 1374 - GOLOSINAS | AB8: 80232.279 | AC8: 99086.869 | AD8: 0.3 | AE8: 0 | AF8: 0.3 | AG8: 0 | AH8: 24069.68 | AI8: 29726.06 | AJ8: 0 | AK8: 0 | AL8: 0 | AM8: 1 | AN8: =VLOOKUP(H8,'Base Art'!$A:$AJ,36,FALSE) -> ARCOR S.A.I.C.
A9: (001) 01 SEP 2026 - 03 SEP 2026 | B9: 1 | C9: 01 SEP 2026 - 03 SEP 2026 | D9: Suc: 001 (000001) VERA ERNESTO | E9: 1 | F9: VERA ERNESTO | G9: (000400) PILA 377 / 376 X 5U ESP RELOJERIA PLATA | H9: 400 | I9: PILA 377 / 376 X 5U ESP RELOJERIA PLATA | J9: 1019 | K9: ENERGIZER | L9: 1019 - ENERGIZER | P9: 1020 | Q9: PILA | R9: 1020 - PILA | Y9: 1402 | Z9: PILAS | AA9: 1402 - PILAS | AB9: 141264 | AC9: 175167.36 | AD9: 0.2 | AE9: 0 | AF9: 0.2 | AG9: 0 | AH9: 28252.8 | AI9: 35033.47 | AJ9: 1 | AK9: 0.2 | AL9: 0 | AM9: 1 | AN9: =VLOOKUP(H9,'Base Art'!$A:$AJ,36,FALSE) -> ENERGIZER ARGENTINA S.A.
A10: (001) 01 SEP 2026 - 03 SEP 2026 | B10: 1 | C10: 01 SEP 2026 - 03 SEP 2026 | D10: Suc: 001 (000001) VERA ERNESTO | E10: 1 | F10: VERA ERNESTO | G10: (000461) MATE LISTO TARAGUI X 35 GR | H10: 461 | I10: MATE LISTO TARAGUI X 35 GR | J10: 1006 | K10: TARAGUI | L10: 1006 - TARAGUI | P10: 1004 | Q10: INFUSIONES | R10: 1004 - INFUSIONES | Y10: 1369 | Z10: ALMACEN | AA10: 1369 - ALMACEN | AB10: 19339.909 | AC10: 24271.588 | AD10: 0.3333 | AE10: 0 | AF10: 0.3333 | AG10: 0 | AH10: 6446.64 | AI10: 8090.53 | AJ10: 0 | AK10: 0 | AL10: 0 | AM10: 1 | AN10: =VLOOKUP(H10,'Base Art'!$A:$AJ,36,FALSE) -> EST. LAS MARIAS S.A.C.I.F.A.
A11: (001) 01 SEP 2026 - 03 SEP 2026 | B11: 1 | C11: 01 SEP 2026 - 03 SEP 2026 | D11: Suc: 001 (000001) VERA ERNESTO | E11: 1 | F11: VERA ERNESTO | G11: (000462) BOTELLA TERMICA MATE LISTO | H11: 462 | I11: BOTELLA TERMICA MATE LISTO | J11: 1006 | K11: TARAGUI | L11: 1006 - TARAGUI | Y11: 1369 | Z11: ALMACEN | AA11: 1369 - ALMACEN | AB11: 15679.431 | AC11: 19677.688 | AD11: 0.3333 | AE11: 0 | AF11: 0.3333 | AG11: 0 | AH11: 5226.48 | AI11: 6559.23 | AJ11: 0 | AK11: 0 | AL11: 0 | AM11: 1 | AN11: =VLOOKUP(H11,'Base Art'!$A:$AJ,36,FALSE) -> EST. LAS MARIAS S.A.C.I.F.A.
A12: (001) 01 SEP 2026 - 03 SEP 2026 | B12: 1 | C12: 01 SEP 2026 - 03 SEP 2026 | D12: Suc: 001 (000001) VERA ERNESTO | E12: 1 | F12: VERA ERNESTO | G12: (000542) PILA ECR-2032 X 5U ESP CALCULADORA | H12: 542 | I12: PILA ECR-2032 X 5U ESP CALCULADORA | J12: 1019 | K12: ENERGIZER | L12: 1019 - ENERGIZER | P12: 1020 | Q12: PILA | R12: 1020 - PILA | Y12: 1402 | Z12: PILAS | AA12: 1402 - PILAS | AB12: 125705.25 | AC12: 153988.93 | AD12: 0.15 | AE12: 0 | AF12: 0.15 | AG12: 0 | AH12: 18855.79 | AI12: 23098.34 | AJ12: 1 | AK12: 0.15 | AL12: 0 | AM12: 1 | AN12: =VLOOKUP(H12,'Base Art'!$A:$AJ,36,FALSE) -> ENERGIZER ARGENTINA S.A.
A13: (001) 01 SEP 2026 - 03 SEP 2026 | B13: 1 | C13: 01 SEP 2026 - 03 SEP 2026 | D13: Suc: 001 (000001) VERA ERNESTO | E13: 1 | F13: VERA ERNESTO | G13: (000559) UNI-POX X 25 ML. CHICO | H13: 559 | I13: UNI-POX X 25 ML. CHICO | J13: 1442 | K13: UNI-POX | L13: 1442 - UNI-POX | P13: 1090 | Q13: PEGAMENTOS | R13: 1090 - PEGAMENTOS | Y13: 1376 | Z13: NO PERECEDEROS | AA13: 1376 - NO PERECEDEROS | AB13: 220169.87 | AC13: 269708.09 | AD13: 0.075 | AE13: 0 | AF13: 0.075 | AG13: 0 | AH13: 16512.74 | AI13: 20228.11 | AJ13: 0 | AK13: 0 | AL13: 0 | AM13: 1 | AN13: =VLOOKUP(H13,'Base Art'!$A:$AJ,36,FALSE) -> JORGE LUIS SUAREZ
A14: (001) 01 SEP 2026 - 03 SEP 2026 | B14: 1 | C14: 01 SEP 2026 - 03 SEP 2026 | D14: Suc: 001 (000001) VERA ERNESTO | E14: 1 | F14: VERA ERNESTO | G14: (000568) BUBBALOO 60'S UVA | H14: 568 | I14: BUBBALOO 60'S UVA | Y14: 1374 | Z14: GOLOSINAS | AA14: 1374 - GOLOSINAS | AB14: 144342.45 | AC14: 176819.49 | AD14: 0.0313 | AE14: 0 | AF14: 0.0313 | AG14: 0 | AH14: 4510.7 | AI14: 5525.61 | AJ14: 0 | AK14: 0 | AL14: 0 | AM14: 1 | AN14: =VLOOKUP(H14,'Base Art'!$A:$AJ,36,FALSE) -> MONDELEZ ARGENTINA S.A.
A15: (001) 01 SEP 2026 - 03 SEP 2026 | B15: 1 | C15: 01 SEP 2026 - 03 SEP 2026 | D15: Suc: 001 (000001) VERA ERNESTO | E15: 1 | F15: VERA ERNESTO | G15: (000639) BATERIA A23 -12V X 5U -ENERGIZER ALCALINA | H15: 639 | I15: BATERIA A23 -12V X 5U -ENERGIZER ALCALINA | J15: 1019 | K15: ENERGIZER | L15: 1019 - ENERGIZER | P15: 1020 | Q15: PILA | R15: 1020 - PILA | Y15: 1402 | Z15: PILAS | AA15: 1402 - PILAS | AB15: 158898.3 | AC15: 194650.42 | AD15: 0.15 | AE15: 0 | AF15: 0.15 | AG15: 0 | AH15: 23834.75 | AI15: 29197.56 | AJ15: 0 | AK15: 0 | AL15: 0 | AM15: 1 | AN15: =VLOOKUP(H15,'Base Art'!$A:$AJ,36,FALSE) -> ENERGIZER ARGENTINA S.A.
A16: (001) 01 SEP 2026 - 03 SEP 2026 | B16: 1 | C16: 01 SEP 2026 - 03 SEP 2026 | D16: Suc: 001 (000001) VERA ERNESTO | E16: 1 | F16: VERA ERNESTO | G16: (000653) CARAM MAST SURT MISKY X800 GR | H16: 653 | I16: CARAM MAST SURT MISKY X800 GR | J16: 1414 | K16: MISKY | L16: 1414 - MISKY | P16: 1072 | Q16: MISKY CARAM | R16: 1072 - MISKY CARAM | Y16: 1374 | Z16: GOLOSINAS | AA16: 1374 - GOLOSINAS | AB16: 50907.528 | AC16: 63125.328 | AD16: 0.1 | AE16: 0 | AF16: 0.1 | AG16: 0 | AH16: 5090.75 | AI16: 6312.53 | AJ16: 0 | AK16: 0 | AL16: 0 | AM16: 1 | AN16: =VLOOKUP(H16,'Base Art'!$A:$AJ,36,FALSE) -> ARCOR S.A.I.C.
A17: (001) 01 SEP 2026 - 03 SEP 2026 | B17: 1 | C17: 01 SEP 2026 - 03 SEP 2026 | D17: Suc: 001 (000001) VERA ERNESTO | E17: 1 | F17: VERA ERNESTO | G17: (000710) PILA ECR-2025 X 5U ESP CALCULADORA | H17: 710 | I17: PILA ECR-2025 X 5U ESP CALCULADORA | J17: 1019 | K17: ENERGIZER | L17: 1019 - ENERGIZER | P17: 1020 | Q17: PILA | R17: 1020 - PILA | Y17: 1402 | Z17: PILAS | AA17: 1402 - PILAS | AB17: 118162.93 | AC17: 144749.61 | AD17: 0.05 | AE17: 0 | AF17: 0.05 | AG17: 0 | AH17: 5908.15 | AI17: 7237.48 | AJ17: 1 | AK17: 0.05 | AL17: 0 | AM17: 1 | AN17: =VLOOKUP(H17,'Base Art'!$A:$AJ,36,FALSE) -> ENERGIZER ARGENTINA S.A.
A18: (001) 01 SEP 2026 - 03 SEP 2026 | B18: 1 | C18: 01 SEP 2026 - 03 SEP 2026 | D18: Suc: 001 (000001) VERA ERNESTO | E18: 1 | F18: VERA ERNESTO | G18: (000731) POLVORITAS VAINILLA X 81 GR | H18: 731 | I18: POLVORITAS VAINILLA X 81 GR | J18: 1422 | K18: POLVORITAS | L18: 1422 - POLVORITAS | P18: 1067 | Q18: POLVORITAS 80G Y 147G | R18: 1067 - POLVORITAS 80G Y 147G | Y18: 1373 | Z18: GALLETITAS | AA18: 1373 - GALLETITAS | AB18: 17387.677 | AC18: 21499.839 | AD18: 0.45 | AE18: 0.025 | AF18: 0.475 | AG18: 0 | AH18: 8259.15 | AI18: 10212.42 | AJ18: 0 | AK18: 0 | AL18: 0 | AM18: 1 | AN18: =VLOOKUP(H18,'Base Art'!$A:$AJ,36,FALSE) -> ARCOR S.A.I.C.
A19: (001) 01 SEP 2026 - 03 SEP 2026 | B19: 1 | C19: 01 SEP 2026 - 03 SEP 2026 | D19: Suc: 001 (000001) VERA ERNESTO | E19: 1 | F19: VERA ERNESTO | G19: (000877) PETACA SAN VICENTE ANIS X 200CC | H19: 877 | I19: PETACA SAN VICENTE ANIS X 200CC | P19: 1102 | Q19: PETACAS | R19: 1102 - PETACAS | Y19: 1370 | Z19: BEBIDAS | AA19: 1370 - BEBIDAS | AB19: 12653.26 | AC19: 15500.241 | AD19: 0.3333 | AE19: 0 | AF19: 0.3333 | AG19: 0 | AH19: 4217.75 | AI19: 5166.75 | AJ19: 1 | AK19: 0.33 | AL19: 0 | AM19: 1 | AN19: =VLOOKUP(H19,'Base Art'!$A:$AJ,36,FALSE) -> LICORES ARGENTINOS SA
A20: (001) 01 SEP 2026 - 03 SEP 2026 | B20: 1 | C20: 01 SEP 2026 - 03 SEP 2026 | D20: Suc: 001 (000001) VERA ERNESTO | E20: 1 | F20: VERA ERNESTO | G20: (001116) MAURI FAUNA SURTIDA X 150 GS | H20: 1116 | I20: MAURI FAUNA SURTIDA X 150 GS | Y20: 1373 | Z20: GALLETITAS | AA20: 1373 - GALLETITAS | AB20: 16858.42 | AC20: 20651.566 | AD20: 0.1071 | AE20: 0 | AF20: 0.1071 | AG20: 0 | AH20: 1806.26 | AI20: 2212.67 | AJ20: 0 | AK20: 0 | AL20: 0 | AM20: 1 | AN20: =VLOOKUP(H20,'Base Art'!$A:$AJ,36,FALSE) -> MAURI S.A.
A21: (001) 01 SEP 2026 - 03 SEP 2026 | B21: 1 | C21: 01 SEP 2026 - 03 SEP 2026 | D21: Suc: 001 (000001) VERA ERNESTO | E21: 1 | F21: VERA ERNESTO | G21: (001118) MAURI VAINILLAS X 80 GS | H21: 1118 | I21: MAURI VAINILLAS X 80 GS | P21: 1335 | Q21: VAINILLAS MAURI | R21: 1335 - VAINILLAS MAURI | Y21: 1373 | Z21: GALLETITAS | AA21: 1373 - GALLETITAS | AB21: 15866.81 | AC21: 19619.142 | AD21: 1.3056 | AE21: 0 | AF21: 1.3056 | AG21: 0 | AH21: 20715 | AI21: 25613.88 | AJ21: 0 | AK21: 0 | AL21: 0 | AM21: 1 | AN21: =VLOOKUP(H21,'Base Art'!$A:$AJ,36,FALSE) -> MAURI S.A.
A22: (001) 01 SEP 2026 - 03 SEP 2026 | B22: 1 | C22: 01 SEP 2026 - 03 SEP 2026 | D22: Suc: 001 (000001) VERA ERNESTO | E22: 1 | F22: VERA ERNESTO | G22: (001119) MAURI VAINILLAS X 160 GS | H22: 1119 | I22: MAURI VAINILLAS X 160 GS | P22: 1335 | Q22: VAINILLAS MAURI | R22: 1335 - VAINILLAS MAURI | Y22: 1373 | Z22: GALLETITAS | AA22: 1373 - GALLETITAS | AB22: 29045.447 | AC22: 35899.058 | AD22: 0.5938 | AE22: 0 | AF22: 0.5938 | AG22: 0 | AH22: 17245.73 | AI22: 21315.07 | AJ22: 0 | AK22: 0 | AL22: 0 | AM22: 1 | AN22: =VLOOKUP(H22,'Base Art'!$A:$AJ,36,FALSE) -> MAURI S.A.
A23: (001) 01 SEP 2026 - 03 SEP 2026 | B23: 1 | C23: 01 SEP 2026 - 03 SEP 2026 | D23: Suc: 001 (000001) VERA ERNESTO | E23: 1 | F23: VERA ERNESTO | G23: (001341) CHOCOLATIN JACK BLANCO X20U X14G | H23: 1341 | I23: CHOCOLATIN JACK BLANCO X20U X14G | Y23: 1372 | Z23: CHOCOLATE | AA23: 1372 - CHOCOLATE | AB23: 413186.45 | AC23: 518548.98 | AD23: 0.1667 | AE23: 0 | AF23: 0.1667 | AG23: 0 | AH23: 68864.41 | AI23: 86424.83 | AJ23: 0 | AK23: 0 | AL23: 0 | AM23: 1 | AN23: =VLOOKUP(H23,'Base Art'!$A:$AJ,36,FALSE) -> LA DELICIA FELIPE FORT S.A.
A24: (001) 01 SEP 2026 - 03 SEP 2026 | B24: 1 | C24: 01 SEP 2026 - 03 SEP 2026 | D24: Suc: 001 (000001) VERA ERNESTO | E24: 1 | F24: VERA ERNESTO | G24: (001345) PARAGUITAS FELFORT X 40U. X 13G | H24: 1345 | I24: PARAGUITAS FELFORT X 40U. X 13G | Y24: 1372 | Z24: CHOCOLATE | AA24: 1372 - CHOCOLATE | AB24: 261523.6 | AC24: 320366.41 | AD24: 0.1667 | AE24: 0 | AF24: 0.1667 | AG24: 0 | AH24: 43587.27 | AI24: 53394.4 | AJ24: 2 | AK24: 0.08 | AL24: 0 | AM24: 1 | AN24: =VLOOKUP(H24,'Base Art'!$A:$AJ,36,FALSE) -> LA DELICIA FELIPE FORT S.A.
A25: (001) 01 SEP 2026 - 03 SEP 2026 | B25: 1 | C25: 01 SEP 2026 - 03 SEP 2026 | D25: Suc: 001 (000001) VERA ERNESTO | E25: 1 | F25: VERA ERNESTO | G25: (001352) DOS CORAZONES X20U X26G CHOCO C/POESIA | H25: 1352 | I25: DOS CORAZONES X20U X26G CHOCO C/POESIA | Y25: 1372 | Z25: CHOCOLATE | AA25: 1372 - CHOCOLATE | AB25: 220487.41 | AC25: 271402.97 | AD25: 0.8333 | AE25: 0 | AF25: 0.8333 | AG25: 0 | AH25: 183739.51 | AI25: 226169.14 | AJ25: 2 | AK25: 0.42 | AL25: 0 | AM25: 1 | AN25: =VLOOKUP(H25,'Base Art'!$A:$AJ,36,FALSE) -> LA DELICIA FELIPE FORT S.A.
A26: (001) 01 SEP 2026 - 03 SEP 2026 | B26: 1 | C26: 01 SEP 2026 - 03 SEP 2026 | D26: Suc: 001 (000001) VERA ERNESTO | E26: 1 | F26: VERA ERNESTO | G26: (001353) MENTITAS BOMBON MENTA AL CHOC X30U. X16G | H26: 1353 | I26: MENTITAS BOMBON MENTA AL CHOC X30U. X16G | Y26: 1372 | Z26: CHOCOLATE | AA26: 1372 - CHOCOLATE | AB26: 150700.36 | AC26: 189128.94 | AD26: 0.0833 | AE26: 0 | AF26: 0.0833 | AG26: 0 | AH26: 12558.36 | AI26: 15760.75 | AJ26: 0 | AK26: 0 | AL26: 0 | AM26: 1 | AN26: =VLOOKUP(H26,'Base Art'!$A:$AJ,36,FALSE) -> LA DELICIA FELIPE FORT S.A.
A27: (001) 01 SEP 2026 - 03 SEP 2026 | B27: 1 | C27: 01 SEP 2026 - 03 SEP 2026 | D27: Suc: 001 (000001) VERA ERNESTO | E27: 1 | F27: VERA ERNESTO | G27: (001354) BOCADITOS MARROC X60U X14G | H27: 1354 | I27: BOCADITOS MARROC X60U X14G | Y27: 1372 | Z27: CHOCOLATE | AA27: 1372 - CHOCOLATE | AB27: 251102.66 | AC27: 310041.05 | AD27: 0.375 | AE27: 0 | AF27: 0.375 | AG27: 0 | AH27: 94163.5 | AI27: 116265.39 | AJ27: 0 | AK27: 0 | AL27: 0 | AM27: 1 | AN27: =VLOOKUP(H27,'Base Art'!$A:$AJ,36,FALSE) -> LA DELICIA FELIPE FORT S.A.
A28: (001) 01 SEP 2026 - 03 SEP 2026 | B28: 1 | C28: 01 SEP 2026 - 03 SEP 2026 | D28: Suc: 001 (000001) VERA ERNESTO | E28: 1 | F28: VERA ERNESTO | G28: (001410) BAZOOKA TUTI FRUTTI X80U | H28: 1410 | I28: BAZOOKA TUTI FRUTTI X80U | J28: 1427 | K28: BAZOOKA | L28: 1427 - BAZOOKA | Y28: 1374 | Z28: GOLOSINAS | AA28: 1374 - GOLOSINAS | AB28: 86362.65 | AC28: 105794.27 | AD28: 0.0556 | AE28: 0 | AF28: 0.0556 | AG28: 0 | AH28: 4797.93 | AI28: 5877.46 | AJ28: 0 | AK28: 0 | AL28: 0 | AM28: 1 | AN28: =VLOOKUP(H28,'Base Art'!$A:$AJ,36,FALSE) -> GEORGALOS HNOS. S.A.I.C.A.
A29: (001) 01 SEP 2026 - 03 SEP 2026 | B29: 1 | C29: 01 SEP 2026 - 03 SEP 2026 | D29: Suc: 001 (000001) VERA ERNESTO | E29: 1 | F29: VERA ERNESTO | G29: (001419) PALITOS DE LA SELVA X 660GR | H29: 1419 | I29: PALITOS DE LA SELVA X 660GR | J29: 1429 | K29: PAL DE LA SELVA | L29: 1429 - PAL DE LA SELVA | Y29: 1374 | Z29: GOLOSINAS | AA29: 1374 - GOLOSINAS | AB29: 86500.213 | AC29: 105962.76 | AD29: 0.25 | AE29: 0 | AF29: 0.25 | AG29: 0 | AH29: 21625.05 | AI29: 26490.69 | AJ29: 0 | AK29: 0 | AL29: 0 | AM29: 1 | AN29: =VLOOKUP(H29,'Base Art'!$A:$AJ,36,FALSE) -> GEORGALOS HNOS. S.A.I.C.A.
A30: (001) 01 SEP 2026 - 03 SEP 2026 | B30: 1 | C30: 01 SEP 2026 - 03 SEP 2026 | D30: Suc: 001 (000001) VERA ERNESTO | E30: 1 | F30: VERA ERNESTO | G30: (001594) POLVORITAS FRUTILLA X 81 GR | H30: 1594 | I30: POLVORITAS FRUTILLA X 81 GR | J30: 1422 | K30: POLVORITAS | L30: 1422 - POLVORITAS | P30: 1067 | Q30: POLVORITAS 80G Y 147G | R30: 1067 - POLVORITAS 80G Y 147G | Y30: 1373 | Z30: GALLETITAS | AA30: 1373 - GALLETITAS | AB30: 18089.197 | AC30: 22593.408 | AD30: 0.5 | AE30: 0 | AF30: 0.5 | AG30: 0 | AH30: 9044.6 | AI30: 11296.7 | AJ30: 0 | AK30: 0 | AL30: 0 | AM30: 1 | AN30: =VLOOKUP(H30,'Base Art'!$A:$AJ,36,FALSE) -> ARCOR S.A.I.C.
A31: (001) 01 SEP 2026 - 03 SEP 2026 | B31: 1 | C31: 01 SEP 2026 - 03 SEP 2026 | D31: Suc: 001 (000001) VERA ERNESTO | E31: 1 | F31: VERA ERNESTO | G31: (001641) 9 DE ORO AGRIDULCE X 200 GR | H31: 1641 | I31: 9 DE ORO AGRIDULCE X 200 GR | J31: 1064 | K31: 9 DE ORO | L31: 1064 - 9 DE ORO | P31: 1066 | Q31: BIZCOCHOS 9 DE ORO | R31: 1066 - BIZCOCHOS 9 DE ORO | Y31: 1373 | Z31: GALLETITAS | AA31: 1373 - GALLETITAS | AB31: 16571.043 | AC31: 20389.587 | AD31: 0.9 | AE31: 0.05 | AF31: 0.95 | AG31: 0 | AH31: 15742.49 | AI31: 19370.11 | AJ31: 1 | AK31: 0.95 | AL31: 0 | AM31: 1 | AN31: =VLOOKUP(H31,'Base Art'!$A:$AJ,36,FALSE) -> MOLINO CAÑUELAS S.A.C.I.F.I.A.
A32: (001) 01 SEP 2026 - 03 SEP 2026 | B32: 1 | C32: 01 SEP 2026 - 03 SEP 2026 | D32: Suc: 001 (000001) VERA ERNESTO | E32: 1 | F32: VERA ERNESTO | G32: (001642) 9 DE ORO SCONCITOS X 200 GR | H32: 1642 | I32: 9 DE ORO SCONCITOS X 200 GR | J32: 1064 | K32: 9 DE ORO | L32: 1064 - 9 DE ORO | P32: 1066 | Q32: BIZCOCHOS 9 DE ORO | R32: 1066 - BIZCOCHOS 9 DE ORO | Y32: 1373 | Z32: GALLETITAS | AA32: 1373 - GALLETITAS | AB32: 19432.18 | AC32: 24095.9 | AD32: 0.3 | AE32: 0 | AF32: 0.3 | AG32: 0 | AH32: 5829.65 | AI32: 7228.77 | AJ32: 0 | AK32: 0 | AL32: 0 | AM32: 1 | AN32: =VLOOKUP(H32,'Base Art'!$A:$AJ,36,FALSE) -> MOLINO CAÑUELAS S.A.C.I.F.I.A.
A33: (001) 01 SEP 2026 - 03 SEP 2026 | B33: 1 | C33: 01 SEP 2026 - 03 SEP 2026 | D33: Suc: 001 (000001) VERA ERNESTO | E33: 1 | F33: VERA ERNESTO | G33: (001643) PASEO CRACKERS X 300GR | H33: 1643 | I33: PASEO CRACKERS X 300GR | J33: 1065 | K33: PASEO | L33: 1065 - PASEO | Y33: 1373 | Z33: GALLETITAS | AA33: 1373 - GALLETITAS | AB33: 14410.413 | AC33: 17652.755 | AD33: 1 | AE33: 0 | AF33: 1 | AG33: 0 | AH33: 14410.41 | AI33: 17652.75 | AJ33: 2 | AK33: 0.5 | AL33: 0 | AM33: 1 | AN33: =VLOOKUP(H33,'Base Art'!$A:$AJ,36,FALSE) -> MOLINO CAÑUELAS S.A.C.I.F.I.A.
A34: (001) 01 SEP 2026 - 03 SEP 2026 | B34: 1 | C34: 01 SEP 2026 - 03 SEP 2026 | D34: Suc: 001 (000001) VERA ERNESTO | E34: 1 | F34: VERA ERNESTO | G34: (001646) 9 DE ORO CLASICO X 200 GR | H34: 1646 | I34: 9 DE ORO CLASICO X 200 GR | J34: 1064 | K34: 9 DE ORO | L34: 1064 - 9 DE ORO | P34: 1066 | Q34: BIZCOCHOS 9 DE ORO | R34: 1066 - BIZCOCHOS 9 DE ORO | Y34: 1373 | Z34: GALLETITAS | AA34: 1373 - GALLETITAS | AB34: 21142.085 | AC34: 25947.944 | AD34: 1.7083 | AE34: 0.0417 | AF34: 1.75 | AG34: 0 | AH34: 36998.65 | AI34: 45408.9 | AJ34: 0 | AK34: 0 | AL34: 0 | AM34: 1 | AN34: =VLOOKUP(H34,'Base Art'!$A:$AJ,36,FALSE) -> MOLINO CAÑUELAS S.A.C.I.F.I.A.
A35: (001) 01 SEP 2026 - 03 SEP 2026 | B35: 1 | C35: 01 SEP 2026 - 03 SEP 2026 | D35: Suc: 001 (000001) VERA ERNESTO | E35: 1 | F35: VERA ERNESTO | G35: (001648) POLVORITAS CHOCOLATE X 81 GR | H35: 1648 | I35: POLVORITAS CHOCOLATE X 81 GR | J35: 1422 | K35: POLVORITAS | L35: 1422 - POLVORITAS | P35: 1067 | Q35: POLVORITAS 80G Y 147G | R35: 1067 - POLVORITAS 80G Y 147G | Y35: 1373 | Z35: GALLETITAS | AA35: 1373 - GALLETITAS | AB35: 18315.879 | AC35: 22540.32 | AD35: 0.525 | AE35: 0 | AF35: 0.525 | AG35: 0 | AH35: 9615.84 | AI35: 11833.67 | AJ35: 0 | AK35: 0 | AL35: 0 | AM35: 1 | AN35: =VLOOKUP(H35,'Base Art'!$A:$AJ,36,FALSE) -> ARCOR S.A.I.C.
A36: (001) 01 SEP 2026 - 03 SEP 2026 | B36: 1 | C36: 01 SEP 2026 - 03 SEP 2026 | D36: Suc: 001 (000001) VERA ERNESTO | E36: 1 | F36: VERA ERNESTO | G36: (001696) PAÑUELITO CANDELA 1RA CALIDAD 10X6U. | H36: 1696 | I36: PAÑUELITO CANDELA 1RA CALIDAD 10X6U. | J36: 1460 | K36: CANDELA | L36: 1460 - CANDELA | Y36: 1369 | Z36: ALMACEN | AA36: 1369 - ALMACEN | AB36: 62035.826 | AC36: 75993.887 | AD36: 0.4792 | AE36: 0 | AF36: 0.4792 | AG36: 0 | AH36: 29725.5 | AI36: 36413.74 | AJ36: 3 | AK36: 0.16 | AL36: 0 | AM36: 1 | AN36: =VLOOKUP(H36,'Base Art'!$A:$AJ,36,FALSE) -> IMPORTADORA SUDAMERICANA S.R.L.
A37: (001) 01 SEP 2026 - 03 SEP 2026 | B37: 1 | C37: 01 SEP 2026 - 03 SEP 2026 | D37: Suc: 001 (000001) VERA ERNESTO | E37: 1 | F37: VERA ERNESTO | G37: (001699) SALSA PIZZA NOEL DOY PACK X340 | H37: 1699 | I37: SALSA PIZZA NOEL DOY PACK X340 | J37: 1419 | K37: NOEL | L37: 1419 - NOEL | P37: 1255 | Q37: SALSAS NOEL | R37: 1255 - SALSAS NOEL | Y37: 1369 | Z37: ALMACEN | AA37: 1369 - ALMACEN | AB37: 21759.32 | AC37: 26655.162 | AD37: 0.1667 | AE37: 0 | AF37: 0.1667 | AG37: 0 | AH37: 3626.55 | AI37: 4442.53 | AJ37: 1 | AK37: 0.17 | AL37: 0 | AM37: 1 | AN37: =VLOOKUP(H37,'Base Art'!$A:$AJ,36,FALSE) -> ARCOR S.A.I.C.
A38: (001) 01 SEP 2026 - 03 SEP 2026 | B38: 1 | C38: 01 SEP 2026 - 03 SEP 2026 | D38: Suc: 001 (000001) VERA ERNESTO | E38: 1 | F38: VERA ERNESTO | G38: (001808) CHUPETIN PICO DULCE POTE X48U | H38: 1808 | I38: CHUPETIN PICO DULCE POTE X48U | J38: 1470 | K38: PICO DULCE | L38: 1470 - PICO DULCE | Y38: 1374 | Z38: GOLOSINAS | AA38: 1374 - GOLOSINAS | AB38: 101800.88 | AC38: 125715.23 | AD38: 0.5 | AE38: 0 | AF38: 0.5 | AG38: 0 | AH38: 50900.44 | AI38: 62857.62 | AJ38: 1 | AK38: 0.5 | AL38: 0 | AM38: 1 | AN38: =VLOOKUP(H38,'Base Art'!$A:$AJ,36,FALSE) -> LHERITIER ARGENTINA S.A.
A39: (001) 01 SEP 2026 - 03 SEP 2026 | B39: 1 | C39: 01 SEP 2026 - 03 SEP 2026 | D39: Suc: 001 (000001) VERA ERNESTO | E39: 1 | F39: VERA ERNESTO | G39: (001870) TIC TAC X12U MENTA | H39: 1870 | I39: TIC TAC X12U MENTA | J39: 1351 | K39: TICTACS | L39: 1351 - TICTACS | P39: 1141 | Q39: TIC TAC | R39: 1141 - TIC TAC | Y39: 1372 | Z39: CHOCOLATE | AA39: 1372 - CHOCOLATE | AB39: 264368.62 | AC39: 323851.56 | AD39: 0.0833 | AE39: 0 | AF39: 0.0833 | AG39: 0 | AH39: 22030.72 | AI39: 26987.63 | AJ39: 1 | AK39: 0.08 | AL39: 0 | AM39: 1 | AN39: =VLOOKUP(H39,'Base Art'!$A:$AJ,36,FALSE) -> FERRERO ARGENTINA S.A.
A40: (001) 01 SEP 2026 - 03 SEP 2026 | B40: 1 | C40: 01 SEP 2026 - 03 SEP 2026 | D40: Suc: 001 (000001) VERA ERNESTO | E40: 1 | F40: VERA ERNESTO | G40: (001919) CARAM SUGUS CONFITADO X 50 GR. | H40: 1919 | I40: CARAM SUGUS CONFITADO X 50 GR. | J40: 1421 | K40: SUGUS | L40: 1421 - SUGUS | Y40: 1374 | Z40: GOLOSINAS | AA40: 1374 - GOLOSINAS | AB40: 26417.69 | AC40: 32484.996 | AD40: 2.1333 | AE40: 0 | AF40: 2.1333 | AG40: 0 | AH40: 56357.74 | AI40: 69301.32 | AJ40: 0 | AK40: 0 | AL40: 0 | AM40: 1 | AN40: =VLOOKUP(H40,'Base Art'!$A:$AJ,36,FALSE) -> ARCOR S.A.I.C.
A41: (001) 01 SEP 2026 - 03 SEP 2026 | B41: 1 | C41: 01 SEP 2026 - 03 SEP 2026 | D41: Suc: 001 (000001) VERA ERNESTO | E41: 1 | F41: VERA ERNESTO | G41: (001941) FLYNN PAFF UVA 70U. X 8GR | H41: 1941 | I41: FLYNN PAFF UVA 70U. X 8GR | J41: 1425 | K41: FLYNN PAFFS | L41: 1425 - FLYNN PAFFS | P41: 1277 | Q41: FLYNN PAFF | R41: 1277 - FLYNN PAFF | Y41: 1374 | Z41: GOLOSINAS | AA41: 1374 - GOLOSINAS | AB41: 58685.742 | AC41: 71890.038 | AD41: 0.0833 | AE41: 0 | AF41: 0.0833 | AG41: 0 | AH41: 4890.48 | AI41: 5990.84 | AJ41: 0 | AK41: 0 | AL41: 0 | AM41: 1 | AN41: =VLOOKUP(H41,'Base Art'!$A:$AJ,36,FALSE) -> GEORGALOS HNOS. S.A.I.C.A.
A42: (001) 01 SEP 2026 - 03 SEP 2026 | B42: 1 | C42: 01 SEP 2026 - 03 SEP 2026 | D42: Suc: 001 (000001) VERA ERNESTO | E42: 1 | F42: VERA ERNESTO | G42: (001942) FLYNN PAFF TUTI FRUTI 70U. X 8GR | H42: 1942 | I42: FLYNN PAFF TUTI FRUTI 70U. X 8GR | J42: 1425 | K42: FLYNN PAFFS | L42: 1425 - FLYNN PAFFS | P42: 1277 | Q42: FLYNN PAFF | R42: 1277 - FLYNN PAFF | Y42: 1374 | Z42: GOLOSINAS | AA42: 1374 - GOLOSINAS | AB42: 58685.742 | AC42: 71890.038 | AD42: 0.25 | AE42: 0 | AF42: 0.25 | AG42: 0 | AH42: 14671.44 | AI42: 17972.51 | AJ42: 0 | AK42: 0 | AL42: 0 | AM42: 1 | AN42: =VLOOKUP(H42,'Base Art'!$A:$AJ,36,FALSE) -> GEORGALOS HNOS. S.A.I.C.A.
A43: (001) 01 SEP 2026 - 03 SEP 2026 | B43: 1 | C43: 01 SEP 2026 - 03 SEP 2026 | D43: Suc: 001 (000001) VERA ERNESTO | E43: 1 | F43: VERA ERNESTO | G43: (001971) KINDER CHOCOLATE MAXI X 210GR T.10 | H43: 1971 | I43: KINDER CHOCOLATE MAXI X 210GR T.10 | J43: 1204 | K43: KINDER SORP | L43: 1204 - KINDER SORP | Y43: 1372 | Z43: CHOCOLATE | AA43: 1372 - CHOCOLATE | AB43: 191259.18 | AC43: 234292.46 | AD43: 0.0357 | AE43: 0 | AF43: 0.0357 | AG43: 0 | AH43: 6830.68 | AI43: 8367.59 | AJ43: 0 | AK43: 0 | AL43: 0 | AM43: 1 | AN43: =VLOOKUP(H43,'Base Art'!$A:$AJ,36,FALSE) -> FERRERO ARGENTINA S.A.
A44: (001) 01 SEP 2026 - 03 SEP 2026 | B44: 1 | C44: 01 SEP 2026 - 03 SEP 2026 | D44: Suc: 001 (000001) VERA ERNESTO | E44: 1 | F44: VERA ERNESTO | G44: (002338) DON SATUR BIZCOCH DULCES X 200GR | H44: 2338 | I44: DON SATUR BIZCOCH DULCES X 200GR | P44: 1086 | Q44: BIZCOCHO DON SATUR | R44: 1086 - BIZCOCHO DON SATUR | Y44: 1373 | Z44: GALLETITAS | AA44: 1373 - GALLETITAS | AB44: 30012.091 | AC44: 36947.384 | AD44: 1.6333 | AE44: 0 | AF44: 1.6333 | AG44: 0 | AH44: 49019.75 | AI44: 60347.39 | AJ44: 0 | AK44: 0 | AL44: 0 | AM44: 1 | AN44: =VLOOKUP(H44,'Base Art'!$A:$AJ,36,FALSE) -> DON SATUR S.R.L.
A45: (001) 01 SEP 2026 - 03 SEP 2026 | B45: 1 | C45: 01 SEP 2026 - 03 SEP 2026 | D45: Suc: 001 (000001) VERA ERNESTO | E45: 1 | F45: VERA ERNESTO | G45: (002339) DON SATUR BIZCOCH SALADOS X 200GR | H45: 2339 | I45: DON SATUR BIZCOCH SALADOS X 200GR | P45: 1086 | Q45: BIZCOCHO DON SATUR | R45: 1086 - BIZCOCHO DON SATUR | Y45: 1373 | Z45: GALLETITAS | AA45: 1373 - GALLETITAS | AB45: 28487.296 | AC45: 35081.92 | AD45: 3.7 | AE45: 0.2667 | AF45: 3.9667 | AG45: 0 | AH45: 112999.61 | AI45: 139158.28 | AJ45: 1 | AK45: 3.97 | AL45: 0 | AM45: 1 | AN45: =VLOOKUP(H45,'Base Art'!$A:$AJ,36,FALSE) -> DON SATUR S.R.L.
A46: (001) 01 SEP 2026 - 03 SEP 2026 | B46: 1 | C46: 01 SEP 2026 - 03 SEP 2026 | D46: Suc: 001 (000001) VERA ERNESTO | E46: 1 | F46: VERA ERNESTO | G46: (003237) LAS COLONIAS ALF 3 PISOS BCO 24X65 GS | H46: 3237 | I46: LAS COLONIAS ALF 3 PISOS BCO 24X65 GS | J46: 1477 | K46: ALFAJORES LAS COLONIAS | L46: 1477 - ALFAJORES LAS COLONIAS | P46: 1093 | Q46: ALF LAS COLONIAS TRIPLE | R46: 1093 - ALF LAS COLONIAS TRIPLE | Y46: 1373 | Z46: GALLETITAS | AA46: 1373 - GALLETITAS | AB46: 107834.9 | AC46: 132986.78 | AD46: 0.5833 | AE46: 0 | AF46: 0.5833 | AG46: 0 | AH46: 62903.69 | AI46: 77575.62 | AJ46: 0 | AK46: 0 | AL46: 0 | AM46: 1 | AN46: =VLOOKUP(H46,'Base Art'!$A:$AJ,36,FALSE) -> ESTABLECIM. MODELO LAS COLONIAS S.A
A47: (001) 01 SEP 2026 - 03 SEP 2026 | B47: 1 | C47: 01 SEP 2026 - 03 SEP 2026 | D47: Suc: 001 (000001) VERA ERNESTO | E47: 1 | F47: VERA ERNESTO | G47: (003238) LAS COLONIAS ALF 3 PISOS NGRO 24X65 GS | H47: 3238 | I47: LAS COLONIAS ALF 3 PISOS NGRO 24X65 GS | J47: 1477 | K47: ALFAJORES LAS COLONIAS | L47: 1477 - ALFAJORES LAS COLONIAS | P47: 1093 | Q47: ALF LAS COLONIAS TRIPLE | R47: 1093 - ALF LAS COLONIAS TRIPLE | Y47: 1373 | Z47: GALLETITAS | AA47: 1373 - GALLETITAS | AB47: 103719.07 | AC47: 127833.75 | AD47: 0.6667 | AE47: 0 | AF47: 0.6667 | AG47: 0 | AH47: 69146.05 | AI47: 85222.5 | AJ47: 0 | AK47: 0 | AL47: 0 | AM47: 1 | AN47: =VLOOKUP(H47,'Base Art'!$A:$AJ,36,FALSE) -> ESTABLECIM. MODELO LAS COLONIAS S.A
A48: (001) 01 SEP 2026 - 03 SEP 2026 | B48: 1 | C48: 01 SEP 2026 - 03 SEP 2026 | D48: Suc: 001 (000001) VERA ERNESTO | E48: 1 | F48: VERA ERNESTO | G48: (003536) POLVORITAS FRUTILLA X 152 GR | H48: 3536 | I48: POLVORITAS FRUTILLA X 152 GR | J48: 1422 | K48: POLVORITAS | L48: 1422 - POLVORITAS | Y48: 1373 | Z48: GALLETITAS | AA48: 1373 - GALLETITAS | AB48: 28489.844 | AC48: 35469.86 | AD48: 0.1667 | AE48: 0 | AF48: 0.1667 | AG48: 0 | AH48: 4748.31 | AI48: 5911.64 | AJ48: 0 | AK48: 0 | AL48: 0 | AM48: 1 | AN48: =VLOOKUP(H48,'Base Art'!$A:$AJ,36,FALSE) -> ARCOR S.A.I.C.
A49: (001) 01 SEP 2026 - 03 SEP 2026 | B49: 1 | C49: 01 SEP 2026 - 03 SEP 2026 | D49: Suc: 001 (000001) VERA ERNESTO | E49: 1 | F49: VERA ERNESTO | G49: (003537) POLVORITAS VAINILLA X 152 GR | H49: 3537 | I49: POLVORITAS VAINILLA X 152 GR | J49: 1422 | K49: POLVORITAS | L49: 1422 - POLVORITAS | P49: 1167 | Q49: POLVORITA 147G | R49: 1167 - POLVORITA 147G | Y49: 1373 | Z49: GALLETITAS | AA49: 1373 - GALLETITAS | AB49: 28489.845 | AC49: 35754.75 | AD49: 0.1389 | AE49: 0 | AF49: 0.1389 | AG49: 0 | AH49: 3956.92 | AI49: 4965.94 | AJ49: 0 | AK49: 0 | AL49: 0 | AM49: 1 | AN49: =VLOOKUP(H49,'Base Art'!$A:$AJ,36,FALSE) -> ARCOR S.A.I.C.
A50: (001) 01 SEP 2026 - 03 SEP 2026 | B50: 1 | C50: 01 SEP 2026 - 03 SEP 2026 | D50: Suc: 001 (000001) VERA ERNESTO | E50: 1 | F50: VERA ERNESTO | G50: (003586) TE TARAGUI 25 SAQ X 2GR (S/ENS) FILTRO E | H50: 3586 | I50: TE TARAGUI 25 SAQ X 2GR (S/ENS) FILTRO E | J50: 1006 | K50: TARAGUI | L50: 1006 - TARAGUI | P50: 1004 | Q50: INFUSIONES | R50: 1004 - INFUSIONES | Y50: 1369 | Z50: ALMACEN | AA50: 1369 - ALMACEN | AB50: 6263.914 | AC50: 7755.463 | AD50: 1.1 | AE50: 0 | AF50: 1.1 | AG50: 0 | AH50: 6890.31 | AI50: 8531.01 | AJ50: 0 | AK50: 0 | AL50: 0 | AM50: 1 | AN50: =VLOOKUP(H50,'Base Art'!$A:$AJ,36,FALSE) -> EST. LAS MARIAS S.A.C.I.F.A.
A51: (001) 01 SEP 2026 - 03 SEP 2026 | B51: 1 | C51: 01 SEP 2026 - 03 SEP 2026 | D51: Suc: 001 (000001) VERA ERNESTO | E51: 1 | F51: VERA ERNESTO | G51: (004117) PILA E-91 AA X 20U ENERGIZER ALCALINA | H51: 4117 | I51: PILA E-91 AA X 20U ENERGIZER ALCALINA | J51: 1019 | K51: ENERGIZER | L51: 1019 - ENERGIZER | P51: 1020 | Q51: PILA | R51: 1020 - PILA | Y51: 1402 | Z51: PILAS | AA51: 1402 - PILAS | AB51: 184792.96 | AC51: 226371.39 | AD51: 0.5 | AE51: 0 | AF51: 0.5 | AG51: 0 | AH51: 92396.48 | AI51: 113185.69 | AJ51: 2 | AK51: 0.25 | AL51: 0 | AM51: 1 | AN51: =VLOOKUP(H51,'Base Art'!$A:$AJ,36,FALSE) -> ENERGIZER ARGENTINA S.A.
A52: (001) 01 SEP 2026 - 03 SEP 2026 | B52: 1 | C52: 01 SEP 2026 - 03 SEP 2026 | D52: Suc: 001 (000001) VERA ERNESTO | E52: 1 | F52: VERA ERNESTO | G52: (004386) PRINGLES CLASICAS X37GS | H52: 4386 | I52: PRINGLES CLASICAS X37GS | J52: 1015 | K52: PRINGLES | L52: 1015 - PRINGLES | P52: 1237 | Q52: PRINGLES CHICAS | R52: 1237 - PRINGLES CHICAS | Y52: 1374 | Z52: GOLOSINAS | AA52: 1374 - GOLOSINAS | AB52: 19291.084 | AC52: 24017.399 | AD52: 2 | AE52: 0 | AF52: 2 | AG52: 0 | AH52: 38582.17 | AI52: 48034.8 | AJ52: 1 | AK52: 2 | AL52: 0 | AM52: 1 | AN52: =VLOOKUP(H52,'Base Art'!$A:$AJ,36,FALSE) -> EST. LAS MARIAS S.A.C.I.F.A.
A53: (001) 01 SEP 2026 - 03 SEP 2026 | B53: 1 | C53: 01 SEP 2026 - 03 SEP 2026 | D53: Suc: 001 (000001) VERA ERNESTO | E53: 1 | F53: VERA ERNESTO | G53: (004438) CHOCOLATE C/LECHE MISKY 30X25 GR | H53: 4438 | I53: CHOCOLATE C/LECHE MISKY 30X25 GR | J53: 1414 | K53: MISKY | L53: 1414 - MISKY | Y53: 1372 | Z53: CHOCOLATE | AA53: 1372 - CHOCOLATE | AB53: 252706.78 | AC53: 309565.81 | AD53: 0.0833 | AE53: 0 | AF53: 0.0833 | AG53: 0 | AH53: 21058.9 | AI53: 25797.15 | AJ53: 1 | AK53: 0.08 | AL53: 0 | AM53: 1 | AN53: =VLOOKUP(H53,'Base Art'!$A:$AJ,36,FALSE) -> ARCOR S.A.I.C.
A54: (001) 01 SEP 2026 - 03 SEP 2026 | B54: 1 | C54: 01 SEP 2026 - 03 SEP 2026 | D54: Suc: 001 (000001) VERA ERNESTO | E54: 1 | F54: VERA ERNESTO | G54: (004446) MEDIA TARDE 3X107 GR SANDWICH | H54: 4446 | I54: MEDIA TARDE 3X107 GR SANDWICH | J54: 1420 | K54: MEDIATARDE | L54: 1420 - MEDIATARDE | Y54: 1373 | Z54: GALLETITAS | AA54: 1373 - GALLETITAS | AB54: 17750.427 | AC54: 22010.53 | AD54: -1 | AE54: 0 | AF54: -1 | AG54: 0 | AH54: -17750.43 | AI54: -22010.53 | AJ54: 0 | AK54: 0 | AL54: 0 | AM54: 1 | AN54: =VLOOKUP(H54,'Base Art'!$A:$AJ,36,FALSE) -> ARCOR S.A.I.C.
A55: (001) 01 SEP 2026 - 03 SEP 2026 | B55: 1 | C55: 01 SEP 2026 - 03 SEP 2026 | D55: Suc: 001 (000001) VERA ERNESTO | E55: 1 | F55: VERA ERNESTO | G55: (004522) YERBA LA MERCED DE MONTE O.C. X1/2 KG | H55: 4522 | I55: YERBA LA MERCED DE MONTE O.C. X1/2 KG | J55: 1013 | K55: LA MERCED | L55: 1013 - LA MERCED | P55: 1005 | Q55: YERBAS | R55: 1005 - YERBAS | Y55: 1369 | Z55: ALMACEN | AA55: 1369 - ALMACEN | AB55: 21927.758 | AC55: 26861.502 | AD55: 0.3333 | AE55: 0 | AF55: 0.3333 | AG55: 0 | AH55: 7309.25 | AI55: 8953.83 | AJ55: 1 | AK55: 0.33 | AL55: 0 | AM55: 1 | AN55: =VLOOKUP(H55,'Base Art'!$A:$AJ,36,FALSE) -> EST. LAS MARIAS S.A.C.I.F.A.
A56: (001) 01 SEP 2026 - 03 SEP 2026 | B56: 1 | C56: 01 SEP 2026 - 03 SEP 2026 | D56: Suc: 001 (000001) VERA ERNESTO | E56: 1 | F56: VERA ERNESTO | G56: (004781) YERBA MATE TARAGUI 4 FLEX X 1/4 KG | H56: 4781 | I56: YERBA MATE TARAGUI 4 FLEX X 1/4 KG | J56: 1006 | K56: TARAGUI | L56: 1006 - TARAGUI | P56: 1005 | Q56: YERBAS | R56: 1005 - YERBAS | Y56: 1369 | Z56: ALMACEN | AA56: 1369 - ALMACEN | AB56: 12083.501 | AC56: 14975.989 | AD56: 0.8 | AE56: 0 | AF56: 0.8 | AG56: 0 | AH56: 9666.8 | AI56: 11980.79 | AJ56: 0 | AK56: 0 | AL56: 0 | AM56: 1 | AN56: =VLOOKUP(H56,'Base Art'!$A:$AJ,36,FALSE) -> EST. LAS MARIAS S.A.C.I.F.A.
A57: (001) 01 SEP 2026 - 03 SEP 2026 | B57: 1 | C57: 01 SEP 2026 - 03 SEP 2026 | D57: Suc: 001 (000001) VERA ERNESTO | E57: 1 | F57: VERA ERNESTO | G57: (004783) YM UNION C/PALO 4 FLEX X 1/4 KG | H57: 4783 | I57: YM UNION C/PALO 4 FLEX X 1/4 KG | J57: 1008 | K57: UNION | L57: 1008 - UNION | P57: 1005 | Q57: YERBAS | R57: 1005 - YERBAS | Y57: 1369 | Z57: ALMACEN | AA57: 1369 - ALMACEN | AB57: 11803.79 | AC57: 14614.044 | AD57: 1.8 | AE57: 0 | AF57: 1.8 | AG57: 0 | AH57: 21246.82 | AI57: 26305.28 | AJ57: 0 | AK57: 0 | AL57: 0 | AM57: 1 | AN57: =VLOOKUP(H57,'Base Art'!$A:$AJ,36,FALSE) -> EST. LAS MARIAS S.A.C.I.F.A.
A58: (001) 01 SEP 2026 - 03 SEP 2026 | B58: 1 | C58: 01 SEP 2026 - 03 SEP 2026 | D58: Suc: 001 (000001) VERA ERNESTO | E58: 1 | F58: VERA ERNESTO | G58: (004828) ALKA CHERRY MENTOL X 800 GR | H58: 4828 | I58: ALKA CHERRY MENTOL X 800 GR | J58: 1413 | K58: ALKA | L58: 1413 - ALKA | P58: 1069 | Q58: CARAM Y CHUP ARCOR | R58: 1069 - CARAM Y CHUP ARCOR | Y58: 1374 | Z58: GOLOSINAS | AA58: 1374 - GOLOSINAS | AB58: 80232.279 | AC58: 98284.546 | AD58: 0.2 | AE58: 0 | AF58: 0.2 | AG58: 0 | AH58: 16046.46 | AI58: 19656.91 | AJ58: 0 | AK58: 0 | AL58: 0 | AM58: 1 | AN58: =VLOOKUP(H58,'Base Art'!$A:$AJ,36,FALSE) -> ARCOR S.A.I.C.
A59: (001) 01 SEP 2026 - 03 SEP 2026 | B59: 1 | C59: 01 SEP 2026 - 03 SEP 2026 | D59: Suc: 001 (000001) VERA ERNESTO | E59: 1 | F59: VERA ERNESTO | G59: (004940) MAGDALENAS C/D DE LECHE D SATUR 10X220G | H59: 4940 | I59: MAGDALENAS C/D DE LECHE D SATUR 10X220G | P59: 1085 | Q59: MAGD DON SATUR | R59: 1085 - MAGD DON SATUR | Y59: 1373 | Z59: GALLETITAS | AA59: 1373 - GALLETITAS | AB59: 17871.586 | AC59: 22145.189 | AD59: 1.8 | AE59: 0 | AF59: 1.8 | AG59: 0 | AH59: 32168.85 | AI59: 39861.34 | AJ59: 0 | AK59: 0 | AL59: 0 | AM59: 1 | AN59: =VLOOKUP(H59,'Base Art'!$A:$AJ,36,FALSE) -> DON SATUR S.R.L.
A60: (001) 01 SEP 2026 - 03 SEP 2026 | B60: 1 | C60: 01 SEP 2026 - 03 SEP 2026 | D60: Suc: 001 (000001) VERA ERNESTO | E60: 1 | F60: VERA ERNESTO | G60: (004941) MAGDALENAS DE VAINILLA D SATUR X 10U | H60: 4941 | I60: MAGDALENAS DE VAINILLA D SATUR X 10U | P60: 1085 | Q60: MAGD DON SATUR | R60: 1085 - MAGD DON SATUR | Y60: 1373 | Z60: GALLETITAS | AA60: 1373 - GALLETITAS | AB60: 18691.383 | AC60: 23317.498 | AD60: 0.4 | AE60: 0 | AF60: 0.4 | AG60: 0 | AH60: 7476.55 | AI60: 9327 | AJ60: 0 | AK60: 0 | AL60: 0 | AM60: 1 | AN60: =VLOOKUP(H60,'Base Art'!$A:$AJ,36,FALSE) -> DON SATUR S.R.L.
A61: (001) 01 SEP 2026 - 03 SEP 2026 | B61: 1 | C61: 01 SEP 2026 - 03 SEP 2026 | D61: Suc: 001 (000001) VERA ERNESTO | E61: 1 | F61: VERA ERNESTO | G61: (004981) MAGDALENAS MARMOLADAS D SATUR X 10U | H61: 4981 | I61: MAGDALENAS MARMOLADAS D SATUR X 10U | P61: 1085 | Q61: MAGD DON SATUR | R61: 1085 - MAGD DON SATUR | Y61: 1373 | Z61: GALLETITAS | AA61: 1373 - GALLETITAS | AB61: 17051.788 | AC61: 21019.611 | AD61: 0.9 | AE61: 0 | AF61: 0.9 | AG61: 0 | AH61: 15346.61 | AI61: 18917.65 | AJ61: 0 | AK61: 0 | AL61: 0 | AM61: 1 | AN61: =VLOOKUP(H61,'Base Art'!$A:$AJ,36,FALSE) -> DON SATUR S.R.L.
A62: (001) 01 SEP 2026 - 03 SEP 2026 | B62: 1 | C62: 01 SEP 2026 - 03 SEP 2026 | D62: Suc: 001 (000001) VERA ERNESTO | E62: 1 | F62: VERA ERNESTO | G62: (005002) MAGDALENAS CHOCOLATE C DDL SATUR X 8U | H62: 5002 | I62: MAGDALENAS CHOCOLATE C DDL SATUR X 8U | P62: 1085 | Q62: MAGD DON SATUR | R62: 1085 - MAGD DON SATUR | Y62: 1373 | Z62: GALLETITAS | AA62: 1373 - GALLETITAS | AB62: 18691.383 | AC62: 22896.948 | AD62: 0.3 | AE62: 0 | AF62: 0.3 | AG62: 0 | AH62: 5607.41 | AI62: 6869.08 | AJ62: 0 | AK62: 0 | AL62: 0 | AM62: 1 | AN62: =VLOOKUP(H62,'Base Art'!$A:$AJ,36,FALSE) -> DON SATUR S.R.L.
A63: (001) 01 SEP 2026 - 03 SEP 2026 | B63: 1 | C63: 01 SEP 2026 - 03 SEP 2026 | D63: Suc: 001 (000001) VERA ERNESTO | E63: 1 | F63: VERA ERNESTO | G63: (005032) BUDIN DON SATUR MARMOLADO X 190G | H63: 5032 | I63: BUDIN DON SATUR MARMOLADO X 190G | P63: 1273 | Q63: BUDIN DON SATUR | R63: 1273 - BUDIN DON SATUR | Y63: 1373 | Z63: GALLETITAS | AA63: 1373 - GALLETITAS | AB63: 25580.08 | AC63: 31335.603 | AD63: 0.1333 | AE63: 0 | AF63: 0.1333 | AG63: 0 | AH63: 3410.68 | AI63: 4178.08 | AJ63: 0 | AK63: 0 | AL63: 0 | AM63: 1 | AN63: =VLOOKUP(H63,'Base Art'!$A:$AJ,36,FALSE) -> DON SATUR S.R.L.
A64: (001) 01 SEP 2026 - 03 SEP 2026 | B64: 1 | C64: 01 SEP 2026 - 03 SEP 2026 | D64: Suc: 001 (000001) VERA ERNESTO | E64: 1 | F64: VERA ERNESTO | G64: (005107) PASEO MIX DE CEREALES X 300GR | H64: 5107 | I64: PASEO MIX DE CEREALES X 300GR | J64: 1065 | K64: PASEO | L64: 1065 - PASEO | Y64: 1373 | Z64: GALLETITAS | AA64: 1373 - GALLETITAS | AB64: 16876.109 | AC64: 20836.235 | AD64: 0.8571 | AE64: 0 | AF64: 0.8571 | AG64: 0 | AH64: 14465.24 | AI64: 17859.63 | AJ64: 0 | AK64: 0 | AL64: 0 | AM64: 1 | AN64: =VLOOKUP(H64,'Base Art'!$A:$AJ,36,FALSE) -> MOLINO CAÑUELAS S.A.C.I.F.I.A.
A65: (001) 01 SEP 2026 - 03 SEP 2026 | B65: 1 | C65: 01 SEP 2026 - 03 SEP 2026 | D65: Suc: 001 (000001) VERA ERNESTO | E65: 1 | F65: VERA ERNESTO | G65: (005108) PASEO 5 SEMILLAS X 300GR | H65: 5108 | I65: PASEO 5 SEMILLAS X 300GR | J65: 1065 | K65: PASEO | L65: 1065 - PASEO | Y65: 1373 | Z65: GALLETITAS | AA65: 1373 - GALLETITAS | AB65: 16736.412 | AC65: 20502.106 | AD65: 0.9286 | AE65: 0 | AF65: 0.9286 | AG65: 0 | AH65: 15540.95 | AI65: 19037.67 | AJ65: 0 | AK65: 0 | AL65: 0 | AM65: 1 | AN65: =VLOOKUP(H65,'Base Art'!$A:$AJ,36,FALSE) -> MOLINO CAÑUELAS S.A.C.I.F.I.A.
A66: (001) 01 SEP 2026 - 03 SEP 2026 | B66: 1 | C66: 01 SEP 2026 - 03 SEP 2026 | D66: Suc: 001 (000001) VERA ERNESTO | E66: 1 | F66: VERA ERNESTO | G66: (005110) PASEO SESAMO X 300GR | H66: 5110 | I66: PASEO SESAMO X 300GR | J66: 1065 | K66: PASEO | L66: 1065 - PASEO | Y66: 1373 | Z66: GALLETITAS | AA66: 1373 - GALLETITAS | AB66: 16566.049 | AC66: 20537.913 | AD66: 0.5714 | AE66: 0 | AF66: 0.5714 | AG66: 0 | AH66: 9466.31 | AI66: 11735.95 | AJ66: 0 | AK66: 0 | AL66: 0 | AM66: 1 | AN66: =VLOOKUP(H66,'Base Art'!$A:$AJ,36,FALSE) -> MOLINO CAÑUELAS S.A.C.I.F.I.A.
A67: (001) 01 SEP 2026 - 03 SEP 2026 | B67: 1 | C67: 01 SEP 2026 - 03 SEP 2026 | D67: Suc: 001 (000001) VERA ERNESTO | E67: 1 | F67: VERA ERNESTO | G67: (005111) PASEO MINI SALVADO X 300GR | H67: 5111 | I67: PASEO MINI SALVADO X 300GR | J67: 1065 | K67: PASEO | L67: 1065 - PASEO | Y67: 1373 | Z67: GALLETITAS | AA67: 1373 - GALLETITAS | AB67: 17717.7 | AC67: 21704.182 | AD67: 0.2143 | AE67: 0 | AF67: 0.2143 | AG67: 0 | AH67: 3796.65 | AI67: 4650.9 | AJ67: 0 | AK67: 0 | AL67: 0 | AM67: 1 | AN67: =VLOOKUP(H67,'Base Art'!$A:$AJ,36,FALSE) -> MOLINO CAÑUELAS S.A.C.I.F.I.A.
A68: (001) 01 SEP 2026 - 03 SEP 2026 | B68: 1 | C68: 01 SEP 2026 - 03 SEP 2026 | D68: Suc: 001 (000001) VERA ERNESTO | E68: 1 | F68: VERA ERNESTO | G68: (005630) PURE DE TOMATE LA HUERTA X530 GS | H68: 5630 | I68: PURE DE TOMATE LA HUERTA X530 GS | J68: 1449 | K68: DE LA HUERTA | L68: 1449 - DE LA HUERTA | Y68: 1370 | Z68: BEBIDAS | AA68: 1370 - BEBIDAS | AB68: 8263.528 | AC68: 10264.482 | AD68: 3.5 | AE68: 0 | AF68: 3.5 | AG68: 0 | AH68: 28922.35 | AI68: 35925.69 | AJ68: 0 | AK68: 0 | AL68: 0 | AM68: 1 | AN68: =VLOOKUP(H68,'Base Art'!$A:$AJ,36,FALSE) -> RPB SA
A69: (001) 01 SEP 2026 - 03 SEP 2026 | B69: 1 | C69: 01 SEP 2026 - 03 SEP 2026 | D69: Suc: 001 (000001) VERA ERNESTO | E69: 1 | F69: VERA ERNESTO | G69: (005631) PURE DE TOMATE LA HUERTA X210 GS | H69: 5631 | I69: PURE DE TOMATE LA HUERTA X210 GS | J69: 1449 | K69: DE LA HUERTA | L69: 1449 - DE LA HUERTA | Y69: 1370 | Z69: BEBIDAS | AA69: 1370 - BEBIDAS | AB69: 7847.912 | AC69: 9799.352 | AD69: 0.8889 | AE69: 0 | AF69: 0.8889 | AG69: 0 | AH69: 6975.92 | AI69: 8710.54 | AJ69: 1 | AK69: 0.89 | AL69: 0 | AM69: 1 | AN69: =VLOOKUP(H69,'Base Art'!$A:$AJ,36,FALSE) -> RPB SA
A70: (001) 01 SEP 2026 - 03 SEP 2026 | B70: 1 | C70: 01 SEP 2026 - 03 SEP 2026 | D70: Suc: 001 (000001) VERA ERNESTO | E70: 1 | F70: VERA ERNESTO | G70: (005634) EDULCORANTE SI DIET X250CC | H70: 5634 | I70: EDULCORANTE SI DIET X250CC | J70: 1076 | K70: SI DIET | L70: 1076 - SI DIET | Y70: 1369 | Z70: ALMACEN | AA70: 1369 - ALMACEN | AB70: 6561.213 | AC70: 8037.488 | AD70: 1.5 | AE70: 0 | AF70: 1.5 | AG70: 0 | AH70: 9841.82 | AI70: 12056.23 | AJ70: 0 | AK70: 0 | AL70: 0 | AM70: 1 | AN70: =VLOOKUP(H70,'Base Art'!$A:$AJ,36,FALSE) -> RPB SA
A71: (001) 01 SEP 2026 - 03 SEP 2026 | B71: 1 | C71: 01 SEP 2026 - 03 SEP 2026 | D71: Suc: 001 (000001) VERA ERNESTO | E71: 1 | F71: VERA ERNESTO | G71: (005723) BAGGIO FRESH X1,5L NARANJA DCE BOTEL | H71: 5723 | I71: BAGGIO FRESH X1,5L NARANJA DCE BOTEL | J71: 1450 | K71: FRESH | L71: 1450 - FRESH | P71: 1077 | Q71: FRESH 1.5L | R71: 1077 - FRESH 1.5L | Y71: 1370 | Z71: BEBIDAS | AA71: 1370 - BEBIDAS | AB71: 6040.1 | AC71: 7502.667 | AD71: 7 | AE71: 0 | AF71: 7 | AG71: 0 | AH71: 42280.7 | AI71: 52518.67 | AJ71: 0 | AK71: 0 | AL71: 0 | AM71: 1 | AN71: =VLOOKUP(H71,'Base Art'!$A:$AJ,36,FALSE) -> RPB SA
A72: (001) 01 SEP 2026 - 03 SEP 2026 | B72: 1 | C72: 01 SEP 2026 - 03 SEP 2026 | D72: Suc: 001 (000001) VERA ERNESTO | E72: 1 | F72: VERA ERNESTO | G72: (005761) BAGGIO FRESH X1,5L POMELO BOTELLA | H72: 5761 | I72: BAGGIO FRESH X1,5L POMELO BOTELLA | J72: 1450 | K72: FRESH | L72: 1450 - FRESH | P72: 1077 | Q72: FRESH 1.5L | R72: 1077 - FRESH 1.5L | Y72: 1370 | Z72: BEBIDAS | AA72: 1370 - BEBIDAS | AB72: 6040.1 | AC72: 7429.323 | AD72: 6 | AE72: 0 | AF72: 6 | AG72: 0 | AH72: 36240.6 | AI72: 44575.94 | AJ72: 0 | AK72: 0 | AL72: 0 | AM72: 1 | AN72: =VLOOKUP(H72,'Base Art'!$A:$AJ,36,FALSE) -> RPB SA
A73: (001) 01 SEP 2026 - 03 SEP 2026 | B73: 1 | C73: 01 SEP 2026 - 03 SEP 2026 | D73: Suc: 001 (000001) VERA ERNESTO | E73: 1 | F73: VERA ERNESTO | G73: (005765) ECCOLE ADHESIVO PARA ZAPATILLAS X9GS | H73: 5765 | I73: ECCOLE ADHESIVO PARA ZAPATILLAS X9GS | J73: 1446 | K73: ECCOLE | L73: 1446 - ECCOLE | Y73: 1376 | Z73: NO PERECEDEROS | AA73: 1376 - NO PERECEDEROS | AB73: 503918.47 | AC73: 617300.13 | AD73: 0.1 | AE73: 0 | AF73: 0.1 | AG73: 0 | AH73: 50391.85 | AI73: 61730.01 | AJ73: 0 | AK73: 0 | AL73: 0 | AM73: 1 | AN73: =VLOOKUP(H73,'Base Art'!$A:$AJ,36,FALSE) -> JORGE LUIS SUAREZ
A74: (001) 01 SEP 2026 - 03 SEP 2026 | B74: 1 | C74: 01 SEP 2026 - 03 SEP 2026 | D74: Suc: 001 (000001) VERA ERNESTO | E74: 1 | F74: VERA ERNESTO | G74: (005801) TIC TAC X12U MIX DE FRUTAS | H74: 5801 | I74: TIC TAC X12U MIX DE FRUTAS | J74: 1351 | K74: TICTACS | L74: 1351 - TICTACS | P74: 1141 | Q74: TIC TAC | R74: 1141 - TIC TAC | Y74: 1372 | Z74: CHOCOLATE | AA74: 1372 - CHOCOLATE | AB74: 264368.62 | AC74: 323851.56 | AD74: 0.0417 | AE74: 0 | AF74: 0.0417 | AG74: 0 | AH74: 11015.36 | AI74: 13493.82 | AJ74: 0 | AK74: 0 | AL74: 0 | AM74: 1 | AN74: =VLOOKUP(H74,'Base Art'!$A:$AJ,36,FALSE) -> FERRERO ARGENTINA S.A.
A75: (001) 01 SEP 2026 - 03 SEP 2026 | B75: 1 | C75: 01 SEP 2026 - 03 SEP 2026 | D75: Suc: 001 (000001) VERA ERNESTO | E75: 1 | F75: VERA ERNESTO | G75: (005816) BAGGIO FRESH X1,5L MANZA DCE BOTELLA | H75: 5816 | I75: BAGGIO FRESH X1,5L MANZA DCE BOTELLA | J75: 1450 | K75: FRESH | L75: 1450 - FRESH | P75: 1077 | Q75: FRESH 1.5L | R75: 1077 - FRESH 1.5L | Y75: 1370 | Z75: BEBIDAS | AA75: 1370 - BEBIDAS | AB75: 6040.1 | AC75: 7489.724 | AD75: 2 | AE75: 0 | AF75: 2 | AG75: 0 | AH75: 12080.2 | AI75: 14979.45 | AJ75: 0 | AK75: 0 | AL75: 0 | AM75: 1 | AN75: =VLOOKUP(H75,'Base Art'!$A:$AJ,36,FALSE) -> RPB SA
A76: (001) 01 SEP 2026 - 03 SEP 2026 | B76: 1 | C76: 01 SEP 2026 - 03 SEP 2026 | D76: Suc: 001 (000001) VERA ERNESTO | E76: 1 | F76: VERA ERNESTO | G76: (006007) PEDIGREE ADTO NC C&V ETAPA2 X1.5KG | H76: 6007 | I76: PEDIGREE ADTO NC C&V ETAPA2 X1.5KG | J76: 1194 | K76: PEDIGREE MARCA | L76: 1194 - PEDIGREE MARCA | P76: 1098 | Q76: PAQUETERIA WHISKAS Y PEDIG | R76: 1098 - PAQUETERIA WHISKAS Y PEDIG | Y76: 1375 | Z76: MASCOTAS | AA76: 1375 - MASCOTAS | AB76: 37205.401 | AC76: 45576.619 | AD76: 0.2222 | AE76: 0 | AF76: 0.2222 | AG76: 0 | AH76: 8267.87 | AI76: 10128.14 | AJ76: 0 | AK76: 0 | AL76: 0 | AM76: 1 | AN76: =VLOOKUP(H76,'Base Art'!$A:$AJ,36,FALSE) -> MASTERFOODS ARGENTINA LTD.
A77: (001) 01 SEP 2026 - 03 SEP 2026 | B77: 1 | C77: 01 SEP 2026 - 03 SEP 2026 | D77: Suc: 001 (000001) VERA ERNESTO | E77: 1 | F77: VERA ERNESTO | G77: (006009) PEDIGREE CACH SANO/CRE E1 X1.5KG | H77: 6009 | I77: PEDIGREE CACH SANO/CRE E1 X1.5KG | J77: 1194 | K77: PEDIGREE MARCA | L77: 1194 - PEDIGREE MARCA | P77: 1098 | Q77: PAQUETERIA WHISKAS Y PEDIG | R77: 1098 - PAQUETERIA WHISKAS Y PEDIG | Y77: 1375 | Z77: MASCOTAS | AA77: 1375 - MASCOTAS | AB77: 39065.634 | AC77: 47855.4 | AD77: 0.2222 | AE77: 0 | AF77: 0.2222 | AG77: 0 | AH77: 8681.25 | AI77: 10634.53 | AJ77: 0 | AK77: 0 | AL77: 0 | AM77: 1 | AN77: =VLOOKUP(H77,'Base Art'!$A:$AJ,36,FALSE) -> MASTERFOODS ARGENTINA LTD.
A78: (001) 01 SEP 2026 - 03 SEP 2026 | B78: 1 | C78: 01 SEP 2026 - 03 SEP 2026 | D78: Suc: 001 (000001) VERA ERNESTO | E78: 1 | F78: VERA ERNESTO | G78: (006030) PEDIGREE ADTO +7AÑOS ETAPA3 X1.5KG | H78: 6030 | I78: PEDIGREE ADTO +7AÑOS ETAPA3 X1.5KG | J78: 1194 | K78: PEDIGREE MARCA | L78: 1194 - PEDIGREE MARCA | P78: 1098 | Q78: PAQUETERIA WHISKAS Y PEDIG | R78: 1098 - PAQUETERIA WHISKAS Y PEDIG | Y78: 1375 | Z78: MASCOTAS | AA78: 1375 - MASCOTAS | AB78: 41121.72 | AC78: 50374.107 | AD78: 0.1111 | AE78: 0 | AF78: 0.1111 | AG78: 0 | AH78: 4569.08 | AI78: 5597.12 | AJ78: 0 | AK78: 0 | AL78: 0 | AM78: 1 | AN78: =VLOOKUP(H78,'Base Art'!$A:$AJ,36,FALSE) -> MASTERFOODS ARGENTINA LTD.
A79: (001) 01 SEP 2026 - 03 SEP 2026 | B79: 1 | C79: 01 SEP 2026 - 03 SEP 2026 | D79: Suc: 001 (000001) VERA ERNESTO | E79: 1 | F79: VERA ERNESTO | G79: (006179) BAGGIO PRONTO X1L NARANJA | H79: 6179 | I79: BAGGIO PRONTO X1L NARANJA | J79: 1454 | K79: BAGGIO PRONTO | L79: 1454 - BAGGIO PRONTO | P79: 1075 | Q79: BAGGIO 1 Y 1.5 LITRO | R79: 1075 - BAGGIO 1 Y 1.5 LITRO | Y79: 1370 | Z79: BEBIDAS | AA79: 1370 - BEBIDAS | AB79: 10990.778 | AC79: 13573.611 | AD79: 3 | AE79: 0 | AF79: 3 | AG79: 0 | AH79: 32972.33 | AI79: 40720.83 | AJ79: 0 | AK79: 0 | AL79: 0 | AM79: 1 | AN79: =VLOOKUP(H79,'Base Art'!$A:$AJ,36,FALSE) -> RPB SA
A80: (001) 01 SEP 2026 - 03 SEP 2026 | B80: 1 | C80: 01 SEP 2026 - 03 SEP 2026 | D80: Suc: 001 (000001) VERA ERNESTO | E80: 1 | F80: VERA ERNESTO | G80: (006180) BAGGIO PRONTO X1L MIX FRUTAL | H80: 6180 | I80: BAGGIO PRONTO X1L MIX FRUTAL | J80: 1454 | K80: BAGGIO PRONTO | L80: 1454 - BAGGIO PRONTO | P80: 1075 | Q80: BAGGIO 1 Y 1.5 LITRO | R80: 1075 - BAGGIO 1 Y 1.5 LITRO | Y80: 1370 | Z80: BEBIDAS | AA80: 1370 - BEBIDAS | AB80: 10990.778 | AC80: 13463.704 | AD80: 1 | AE80: 0 | AF80: 1 | AG80: 0 | AH80: 10990.78 | AI80: 13463.7 | AJ80: 0 | AK80: 0 | AL80: 0 | AM80: 1 | AN80: =VLOOKUP(H80,'Base Art'!$A:$AJ,36,FALSE) -> RPB SA
A81: (001) 01 SEP 2026 - 03 SEP 2026 | B81: 1 | C81: 01 SEP 2026 - 03 SEP 2026 | D81: Suc: 001 (000001) VERA ERNESTO | E81: 1 | F81: VERA ERNESTO | G81: (006182) BAGGIO PRONTO X1L PERA | H81: 6182 | I81: BAGGIO PRONTO X1L PERA | J81: 1454 | K81: BAGGIO PRONTO | L81: 1454 - BAGGIO PRONTO | P81: 1075 | Q81: BAGGIO 1 Y 1.5 LITRO | R81: 1075 - BAGGIO 1 Y 1.5 LITRO | Y81: 1370 | Z81: BEBIDAS | AA81: 1370 - BEBIDAS | AB81: 10990.778 | AC81: 13463.704 | AD81: 2 | AE81: 0 | AF81: 2 | AG81: 0 | AH81: 21981.56 | AI81: 26927.41 | AJ81: 0 | AK81: 0 | AL81: 0 | AM81: 1 | AN81: =VLOOKUP(H81,'Base Art'!$A:$AJ,36,FALSE) -> RPB SA
A82: (001) 01 SEP 2026 - 03 SEP 2026 | B82: 1 | C82: 01 SEP 2026 - 03 SEP 2026 | D82: Suc: 001 (000001) VERA ERNESTO | E82: 1 | F82: VERA ERNESTO | G82: (006183) BAGGIO PRONTO X1L DURAZNO | H82: 6183 | I82: BAGGIO PRONTO X1L DURAZNO | J82: 1454 | K82: BAGGIO PRONTO | L82: 1454 - BAGGIO PRONTO | P82: 1075 | Q82: BAGGIO 1 Y 1.5 LITRO | R82: 1075 - BAGGIO 1 Y 1.5 LITRO | Y82: 1370 | Z82: BEBIDAS | AA82: 1370 - BEBIDAS | AB82: 10990.778 | AC82: 13793.427 | AD82: 2 | AE82: 0 | AF82: 2 | AG82: 0 | AH82: 21981.56 | AI82: 27586.85 | AJ82: 0 | AK82: 0 | AL82: 0 | AM82: 1 | AN82: =VLOOKUP(H82,'Base Art'!$A:$AJ,36,FALSE) -> RPB SA
A83: (001) 01 SEP 2026 - 03 SEP 2026 | B83: 1 | C83: 01 SEP 2026 - 03 SEP 2026 | D83: Suc: 001 (000001) VERA ERNESTO | E83: 1 | F83: VERA ERNESTO | G83: (006185) BAGGIO PRONTO X200CC NARANJA | H83: 6185 | I83: BAGGIO PRONTO X200CC NARANJA | J83: 1454 | K83: BAGGIO PRONTO | L83: 1454 - BAGGIO PRONTO | P83: 1074 | Q83: BAGGIO 200CC | R83: 1074 - BAGGIO 200CC | Y83: 1370 | Z83: BEBIDAS | AA83: 1370 - BEBIDAS | AB83: 7302.603 | AC83: 9018.714 | AD83: 1.5 | AE83: 0 | AF83: 1.5 | AG83: 0 | AH83: 10953.9 | AI83: 13528.07 | AJ83: 0 | AK83: 0 | AL83: 0 | AM83: 1 | AN83: =VLOOKUP(H83,'Base Art'!$A:$AJ,36,FALSE) -> RPB SA
A84: (001) 01 SEP 2026 - 03 SEP 2026 | B84: 1 | C84: 01 SEP 2026 - 03 SEP 2026 | D84: Suc: 001 (000001) VERA ERNESTO | E84: 1 | F84: VERA ERNESTO | G84: (006186) BAGGIO PRONTO X200CC MIX FRUTAL | H84: 6186 | I84: BAGGIO PRONTO X200CC MIX FRUTAL | J84: 1454 | K84: BAGGIO PRONTO | L84: 1454 - BAGGIO PRONTO | P84: 1074 | Q84: BAGGIO 200CC | R84: 1074 - BAGGIO 200CC | Y84: 1370 | Z84: BEBIDAS | AA84: 1370 - BEBIDAS | AB84: 7187.298 | AC84: 8913.98 | AD84: 1 | AE84: 0 | AF84: 1 | AG84: 0 | AH84: 7187.3 | AI84: 8913.98 | AJ84: 0 | AK84: 0 | AL84: 0 | AM84: 1 | AN84: =VLOOKUP(H84,'Base Art'!$A:$AJ,36,FALSE) -> RPB SA
A85: (001) 01 SEP 2026 - 03 SEP 2026 | B85: 1 | C85: 01 SEP 2026 - 03 SEP 2026 | D85: Suc: 001 (000001) VERA ERNESTO | E85: 1 | F85: VERA ERNESTO | G85: (006188) BAGGIO PRONTO X200CC PERA | H85: 6188 | I85: BAGGIO PRONTO X200CC PERA | J85: 1454 | K85: BAGGIO PRONTO | L85: 1454 - BAGGIO PRONTO | P85: 1074 | Q85: BAGGIO 200CC | R85: 1074 - BAGGIO 200CC | Y85: 1370 | Z85: BEBIDAS | AA85: 1370 - BEBIDAS | AB85: 7302.603 | AC85: 8945.688 | AD85: 1 | AE85: 0 | AF85: 1 | AG85: 0 | AH85: 7302.6 | AI85: 8945.69 | AJ85: 0 | AK85: 0 | AL85: 0 | AM85: 1 | AN85: =VLOOKUP(H85,'Base Art'!$A:$AJ,36,FALSE) -> RPB SA
... A93: (001) 01 SEP 2026 - 03 SEP 2026 | B93: 1 | C93: 01 SEP 2026 - 03 SEP 2026 | D93: Suc: 001 (000001) VERA ERNESTO | E93: 1 | F93: VERA ERNESTO | G93: (006655) CARAM MED RELLENOS MIEL MISKY X675G | H93: 6655 | I93: CARAM MED RELLENOS MIEL MISKY X675G | J93: 1414 | K93: MISKY | L93: 1414 - MISKY | P93: 1072 | Q93: MISKY CARAM | R93: 1072 - MISKY CARAM | Y93: 1374 | Z93: GOLOSINAS | AA93: 1374 - GOLOSINAS | AB93: 34166.64 | AC93: 42366.634 | AD93: 0.1667 | AE93: 0 | AF93: 0.1667 | AG93: 0 | AH93: 5694.44 | AI93: 7061.11 | AJ93: 0 | AK93: 0 | AL93: 0 | AM93: 1 | AN93: =VLOOKUP(H93,'Base Art'!$A:$AJ,36,FALSE) -> ARCOR S.A.I.C.
A94: (001) 01 SEP 2026 - 03 SEP 2026 | B94: 1 | C94: 01 SEP 2026 - 03 SEP 2026 | D94: Suc: 001 (000001) VERA ERNESTO | E94: 1 | F94: VERA ERNESTO | G94: (006660) MAGD VAINI C/CHIP CHOC D SATUR X200G | H94: 6660 | I94: MAGD VAINI C/CHIP CHOC D SATUR X200G | P94: 1085 | Q94: MAGD DON SATUR | R94: 1085 - MAGD DON SATUR | Y94: 1373 | Z94: GALLETITAS | AA94: 1373 - GALLETITAS | AB94: 18691.383 | AC94: 23270.772 | AD94: 0.6 | AE94: 0 | AF94: 0.6 | AG94: 0 | AH94: 11214.83 | AI94: 13962.46 | AJ94: 0 | AK94: 0 | AL94: 0 | AM94: 1 | AN94: =VLOOKUP(H94,'Base Art'!$A:$AJ,36,FALSE) -> DON SATUR S.R.L.
A95: (001) 01 SEP 2026 - 03 SEP 2026 | B95: 1 | C95: 01 SEP 2026 - 03 SEP 2026 | D95: Suc: 001 (000001) VERA ERNESTO | E95: 1 | F95: VERA ERNESTO | G95: (006712) MERMELADA CONFIT CIRUELA NOEL X454G | H95: 6712 | I95: MERMELADA CONFIT CIRUELA NOEL X454G | J95: 1419 | K95: NOEL | L95: 1419 - NOEL | P95: 1333 | Q95: MERMELADA NOEL | R95: 1333 - MERMELADA NOEL | Y95: 1369 | Z95: ALMACEN | AA95: 1369 - ALMACEN | AB95: 22998.3 | AC95: 28517.892 | AD95: 0.1667 | AE95: 0 | AF95: 0.1667 | AG95: 0 | AH95: 3833.05 | AI95: 4752.98 | AJ95: 0 | AK95: 0 | AL95: 0 | AM95: 1 | AN95: =VLOOKUP(H95,'Base Art'!$A:$AJ,36,FALSE) -> ARCOR S.A.I.C.
A96: (001) 01 SEP 2026 - 03 SEP 2026 | B96: 1 | C96: 01 SEP 2026 - 03 SEP 2026 | D96: Suc: 001 (000001) VERA ERNESTO | E96: 1 | F96: VERA ERNESTO | G96: (007019) PEDIGREE DENTASTIX RZ PEQ 10X47,1GS | H96: 7019 | I96: PEDIGREE DENTASTIX RZ PEQ 10X47,1GS | J96: 1194 | K96: PEDIGREE MARCA | L96: 1194 - PEDIGREE MARCA | P96: 1132 | Q96: DENTASTIX/RODEO/BISCROK | R96: 1132 - DENTASTIX/RODEO/BISCROK | Y96: 1375 | Z96: MASCOTAS | AA96: 1375 - MASCOTAS | AB96: 19396.91 | AC96: 23761.217 | AD96: 0.5 | AE96: 0 | AF96: 0.5 | AG96: 0 | AH96: 9698.46 | AI96: 11880.61 | AJ96: 0 | AK96: 0 | AL96: 0 | AM96: 1 | AN96: =VLOOKUP(H96,'Base Art'!$A:$AJ,36,FALSE) -> MASTERFOODS ARGENTINA LTD.
A97: (001) 01 SEP 2026 - 03 SEP 2026 | B97: 1 | C97: 01 SEP 2026 - 03 SEP 2026 | D97: Suc: 001 (000001) VERA ERNESTO | E97: 1 | F97: VERA ERNESTO | G97: (007094) AC DE OLIVA V.E LA POSTA DE OLIVO X500ML | H97: 7094 | I97: AC DE OLIVA V.E LA POSTA DE OLIVO X500ML | J97: 1455 | K97: LA POSTA | L97: 1455 - LA POSTA | Y97: 1369 | Z97: ALMACEN | AA97: 1369 - ALMACEN | AB97: 61067.61 | AC97: 75723.844 | AD97: 0.1667 | AE97: 0 | AF97: 0.1667 | AG97: 0 | AH97: 10177.94 | AI97: 12620.64 | AJ97: 1 | AK97: 0.17 | AL97: 0 | AM97: 1 | AN97: =VLOOKUP(H97,'Base Art'!$A:$AJ,36,FALSE) -> RPB SA
A98: (001) 01 SEP 2026 - 03 SEP 2026 | B98: 1 | C98: 01 SEP 2026 - 03 SEP 2026 | D98: Suc: 001 (000001) VERA ERNESTO | E98: 1 | F98: VERA ERNESTO | G98: (007230) BAGGIO FRESH X1,5L PERA BOTELLA | H98: 7230 | I98: BAGGIO FRESH X1,5L PERA BOTELLA | J98: 1450 | K98: FRESH | L98: 1450 - FRESH | P98: 1077 | Q98: FRESH 1.5L | R98: 1077 - FRESH 1.5L | Y98: 1370 | Z98: BEBIDAS | AA98: 1370 - BEBIDAS | AB98: 6040.1 | AC98: 7580.326 | AD98: 1 | AE98: 0 | AF98: 1 | AG98: 0 | AH98: 6040.1 | AI98: 7580.33 | AJ98: 0 | AK98: 0 | AL98: 0 | AM98: 1 | AN98: =VLOOKUP(H98,'Base Art'!$A:$AJ,36,FALSE) -> RPB SA
A99: (001) 01 SEP 2026 - 03 SEP 2026 | B99: 1 | C99: 01 SEP 2026 - 03 SEP 2026 | D99: Suc: 001 (000001) VERA ERNESTO | E99: 1 | F99: VERA ERNESTO | G99: (007235) PEDIGREE SOBRESITO CACH CAR/SALS 12X85G | H99: 7235 | I99: PEDIGREE SOBRESITO CACH CAR/SALS 12X85G | J99: 1194 | K99: PEDIGREE MARCA | L99: 1194 - PEDIGREE MARCA | P99: 1094 | Q99: SOBRECITOS WHISKAS Y PEDIG | R99: 1094 - SOBRECITOS WHISKAS Y PEDIG | Y99: 1375 | Z99: MASCOTAS | AA99: 1375 - MASCOTAS | AB99: 9077.706 | AC99: 11120.191 | AD99: 1 | AE99: 0 | AF99: 1 | AG99: 0 | AH99: 9077.71 | AI99: 11120.19 | AJ99: 0 | AK99: 0 | AL99: 0 | AM99: 1 | AN99: =VLOOKUP(H99,'Base Art'!$A:$AJ,36,FALSE) -> MASTERFOODS ARGENTINA LTD.
A100: (001) 01 SEP 2026 - 03 SEP 2026 | B100: 1 | C100: 01 SEP 2026 - 03 SEP 2026 | D100: Suc: 001 (000001) VERA ERNESTO | E100: 1 | F100: VERA ERNESTO | G100: (007236) PEDIGREE SOBRESITO RP CAR/SALS 12X100G | H100: 7236 | I100: PEDIGREE SOBRESITO RP CAR/SALS 12X100G | J100: 1194 | K100: PEDIGREE MARCA | L100: 1194 - PEDIGREE MARCA | P100: 1094 | Q100: SOBRECITOS WHISKAS Y PEDIG | R100: 1094 - SOBRECITOS WHISKAS Y PEDIG | Y100: 1375 | Z100: MASCOTAS | AA100: 1375 - MASCOTAS | AB100: 9077.706 | AC100: 11120.191 | AD100: 2 | AE100: 0 | AF100: 2 | AG100: 0 | AH100: 18155.41 | AI100: 22240.38 | AJ100: 0 | AK100: 0 | AL100: 0 | AM100: 1 | AN100: =VLOOKUP(H100,'Base Art'!$A:$AJ,36,FALSE) -> MASTERFOODS ARGENTINA LTD.
A101: (001) 01 SEP 2026 - 03 SEP 2026 | B101: 1 | C101: 01 SEP 2026 - 03 SEP 2026 | D101: Suc: 001 (000001) VERA ERNESTO | E101: 1 | F101: VERA ERNESTO | G101: (007237) PEDIGREE SOBRESITO ADTO CAR/SALS 12X100G | H101: 7237 | I101: PEDIGREE SOBRESITO ADTO CAR/SALS 12X100G | J101: 1194 | K101: PEDIGREE MARCA | L101: 1194 - PEDIGREE MARCA | P101: 1094 | Q101: SOBRECITOS WHISKAS Y PEDIG | R101: 1094 - SOBRECITOS WHISKAS Y PEDIG | Y101: 1375 | Z101: MASCOTAS | AA101: 1375 - MASCOTAS | AB101: 9077.706 | AC101: 11120.191 | AD101: 2 | AE101: 0 | AF101: 2 | AG101: 0 | AH101: 18155.41 | AI101: 22240.38 | AJ101: 0 | AK101: 0 | AL101: 0 | AM101: 1 | AN101: =VLOOKUP(H101,'Base Art'!$A:$AJ,36,FALSE) -> MASTERFOODS ARGENTINA LTD.
A102: (001) 01 SEP 2026 - 03 SEP 2026 | B102: 1 | C102: 01 SEP 2026 - 03 SEP 2026 | D102: Suc: 001 (000001) VERA ERNESTO | E102: 1 | F102: VERA ERNESTO | G102: (007239) WHISKAS SOBRESITO ADTO CARNE 12X85GR | H102: 7239 | I102: WHISKAS SOBRESITO ADTO CARNE 12X85GR | J102: 1193 | K102: WHISKAS MARCA | L102: 1193 - WHISKAS MARCA | P102: 1094 | Q102: SOBRECITOS WHISKAS Y PEDIG | R102: 1094 - SOBRECITOS WHISKAS Y PEDIG | Y102: 1375 | Z102: MASCOTAS | AA102: 1375 - MASCOTAS | AB102: 9077.706 | AC102: 11120.191 | AD102: 1 | AE102: 0 | AF102: 1 | AG102: 0 | AH102: 9077.71 | AI102: 11120.19 | AJ102: 0 | AK102: 0 | AL102: 0 | AM102: 1 | AN102: =VLOOKUP(H102,'Base Art'!$A:$AJ,36,FALSE) -> MASTERFOODS ARGENTINA LTD.
A103: (001) 01 SEP 2026 - 03 SEP 2026 | B103: 1 | C103: 01 SEP 2026 - 03 SEP 2026 | D103: Suc: 001 (000001) VERA ERNESTO | E103: 1 | F103: VERA ERNESTO | G103: (007240) WHISKAS SOBRESITO ADTO SARDINA 12X85GR | H103: 7240 | I103: WHISKAS SOBRESITO ADTO SARDINA 12X85GR | J103: 1193 | K103: WHISKAS MARCA | L103: 1193 - WHISKAS MARCA | P103: 1094 | Q103: SOBRECITOS WHISKAS Y PEDIG | R103: 1094 - SOBRECITOS WHISKAS Y PEDIG | Y103: 1375 | Z103: MASCOTAS | AA103: 1375 - MASCOTAS | AB103: 9077.706 | AC103: 11120.191 | AD103: 2 | AE103: 0 | AF103: 2 | AG103: 0 | AH103: 18155.41 | AI103: 22240.38 | AJ103: 0 | AK103: 0 | AL103: 0 | AM103: 1 | AN103: =VLOOKUP(H103,'Base Art'!$A:$AJ,36,FALSE) -> MASTERFOODS ARGENTINA LTD.
A104: (001) 01 SEP 2026 - 03 SEP 2026 | B104: 1 | C104: 01 SEP 2026 - 03 SEP 2026 | D104: Suc: 001 (000001) VERA ERNESTO | E104: 1 | F104: VERA ERNESTO | G104: (007241) WHISKAS SOBRESITO ADTO POLLO 12X85GR | H104: 7241 | I104: WHISKAS SOBRESITO ADTO POLLO 12X85GR | J104: 1193 | K104: WHISKAS MARCA | L104: 1193 - WHISKAS MARCA | P104: 1094 | Q104: SOBRECITOS WHISKAS Y PEDIG | R104: 1094 - SOBRECITOS WHISKAS Y PEDIG | Y104: 1375 | Z104: MASCOTAS | AA104: 1375 - MASCOTAS | AB104: 9077.706 | AC104: 11120.191 | AD104: 2 | AE104: 0 | AF104: 2 | AG104: 0 | AH104: 18155.41 | AI104: 22240.38 | AJ104: 0 | AK104: 0 | AL104: 0 | AM104: 1 | AN104: =VLOOKUP(H104,'Base Art'!$A:$AJ,36,FALSE) -> MASTERFOODS ARGENTINA LTD.
A105: (001) 01 SEP 2026 - 03 SEP 2026 | B105: 1 | C105: 01 SEP 2026 - 03 SEP 2026 | D105: Suc: 001 (000001) VERA ERNESTO | E105: 1 | F105: VERA ERNESTO | G105: (007242) WHISKAS SOBRESITO ADTO SALMON 12X85GR | H105: 7242 | I105: WHISKAS SOBRESITO ADTO SALMON 12X85GR | J105: 1193 | K105: WHISKAS MARCA | L105: 1193 - WHISKAS MARCA | P105: 1094 | Q105: SOBRECITOS WHISKAS Y PEDIG | R105: 1094 - SOBRECITOS WHISKAS Y PEDIG | Y105: 1375 | Z105: MASCOTAS | AA105: 1375 - MASCOTAS | AB105: 9077.706 | AC105: 11120.191 | AD105: 1 | AE105: 0 | AF105: 1 | AG105: 0 | AH105: 9077.71 | AI105: 11120.19 | AJ105: 0 | AK105: 0 | AL105: 0 | AM105: 1 | AN105: =VLOOKUP(H105,'Base Art'!$A:$AJ,36,FALSE) -> MASTERFOODS ARGENTINA LTD.
A106: (001) 01 SEP 2026 - 03 SEP 2026 | B106: 1 | C106: 01 SEP 2026 - 03 SEP 2026 | D106: Suc: 001 (000001) VERA ERNESTO | E106: 1 | F106: VERA ERNESTO | G106: (007311) PEDIGREE SOBRESITO RP POLL/SALS 12X100G | H106: 7311 | I106: PEDIGREE SOBRESITO RP POLL/SALS 12X100G | J106: 1194 | K106: PEDIGREE MARCA | L106: 1194 - PEDIGREE MARCA | P106: 1094 | Q106: SOBRECITOS WHISKAS Y PEDIG | R106: 1094 - SOBRECITOS WHISKAS Y PEDIG | Y106: 1375 | Z106: MASCOTAS | AA106: 1375 - MASCOTAS | AB106: 8631.784 | AC106: 10573.935 | AD106: 3 | AE106: 0 | AF106: 3 | AG106: 0 | AH106: 25895.35 | AI106: 31721.8 | AJ106: 1 | AK106: 3 | AL106: 0 | AM106: 1 | AN106: =VLOOKUP(H106,'Base Art'!$A:$AJ,36,FALSE) -> MASTERFOODS ARGENTINA LTD.
A107: (001) 01 SEP 2026 - 03 SEP 2026 | B107: 1 | C107: 01 SEP 2026 - 03 SEP 2026 | D107: Suc: 001 (000001) VERA ERNESTO | E107: 1 | F107: VERA ERNESTO | G107: (007313) PEDIGREE SOBRESITO AD POLL/SALS 12X100G | H107: 7313 | I107: PEDIGREE SOBRESITO AD POLL/SALS 12X100G | J107: 1194 | K107: PEDIGREE MARCA | L107: 1194 - PEDIGREE MARCA | P107: 1094 | Q107: SOBRECITOS WHISKAS Y PEDIG | R107: 1094 - SOBRECITOS WHISKAS Y PEDIG | Y107: 1375 | Z107: MASCOTAS | AA107: 1375 - MASCOTAS | AB107: 9077.706 | AC107: 11120.191 | AD107: 1 | AE107: 0 | AF107: 1 | AG107: 0 | AH107: 9077.71 | AI107: 11120.19 | AJ107: 0 | AK107: 0 | AL107: 0 | AM107: 1 | AN107: =VLOOKUP(H107,'Base Art'!$A:$AJ,36,FALSE) -> MASTERFOODS ARGENTINA LTD.
...

Sheet Base Art
A1: CAMPOS OBLIGATORIOS Y FIJOS | D1: ATRIBUTOS COMPAÑÍA | F1: GENERAL | X1: GENERAL -> Datos Impositivo de Ventas | AI1: ABASTECIMIENTO -> Proveedor | AK1: INVENTARIO -> General | AP1: INVENTARIO -> Ordenes de Pedido | AR1: INVENTARIO -> Frescura | AT1: INVENTARIO -> Datos de Almacenamiento | AW1: INVENTARIO -> Activos Fijos | BB1: LOGISTICA -> Presentación | BL1: LOGISTICA -> Retornables
A2: Código | B2: Descripción | C2: Unidad x Bulto | D2: ID Compañía | E2: SKU Compañía | F2: Anulado | G2: Usado en Disp. Móvil | H2: Alcohólico | I2: Retornable | J2: Comodatable | K2: Activo Fijo | L2: Venta por Unidad y Peso | M2: Fecha Alta | N2: Descripción Corta | O2: Cód. Barra Bulto | P2: Cód. Barra Unidad | Q2: Cota inferior | R2: Cota superior | S2: Descripción Adicional | T2: Descripción de Voz | U2: Cód.Unidad de Medida | V2: Desc.Unidad de Medida | W2: Valor | X2: Mínimo de Facturación | Y2: Factor de Facturación | Z2: Exento de IVA | AA2: Exento de IVA (segun cond. Contribuyente) | AB2: IVA diferencial | AC2: Tasa de IVA diferencial | AD2: Porcentaje de imp. internos | AE2: Imp. Internos fijos | AF2: Porcentaje de Perc. II.BB. | AG2: Exento PER RG5329 | AH2: Codigo COT | AI2: Proveedor | AJ2: Razón Social | AK2: Cód.Artículo Proveedor | AL2: Cód.Artículo Proveedor Secundario | AM2: Cód.Depósito | AN2: Cód.Almacen | AO2: Ubicación | AP2: Orden | AQ2: Días Ventana | AR2: Días Política de Stock | AS2: Artículo con frescura | AT2: Bloquear antes del Vto. (días) | AU2: Bultos x Pallet | AV2: Pisos | AW2: Apilabilidad | AX2: Requiere Nro. Activo | AY2: Litros de Repago | AZ2: Años amortización | BA2: Cantidad de puertas | BB2: Unid. X frente | BC2: Prod.Estadístico | BD2: Cód.Pres Bulto Cerrado | BE2: Desc.Pres.Bulto.Cerrado | BF2: Cód. Pres. Individual | BG2: Desc.Pres.Individual | BH2: Peso | BI2: Unidad PKT | BJ2: Cód.Tipo Mercadería | BK2: Desc.Tipo Mercadería | BL2: Unid. Flete | BM2: Cód. Vacío | BN2: Cód. Esqueleto
A3: ENTERO | B3: CARACTER | C3: ENTERO | D3: ENTERO | E3: ENTERO | F3: LOGICO | G3: LOGICO | H3: LOGICO | I3: LOGICO | J3: LOGICO | K3: LOGICO | L3: LOGICO | M3: FECHA | N3: CARACTER | O3: CARACTER | P3: CARACTER | Q3: DECIMAL | R3: DECIMAL | S3: CARACTER | T3: CARACTER | U3: ENTERO | V3: CARACTER | W3: DECIMAL | X3: ENTERO | Y3: ENTERO | Z3: LOGICO | AA3: LOGICO | AB3: LOGICO | AC3: DECIMAL | AD3: DECIMAL | AE3: DECIMAL | AF3: DECIMAL | AG3: LOGICO | AH3: CARACTER | AI3: ENTERO | AJ3: CARACTER | AK3: CARACTER | AL3: CARACTER | AM3: ENTERO | AN3: ENTERO | AO3: CARACTER | AP3: ENTERO | AQ3: ENTERO | AR3: ENTERO | AS3: LOGICO | AT3: ENTERO | AU3: ENTERO | AV3: ENTERO | AW3: DECIMAL | AX3: LOGICO | AY3: DECIMAL | AZ3: ENTERO | BA3: ENTERO | BB3: ENTERO | BC3: ENTERO | BD3: CARACTER | BE3: CARACTER | BF3: CARACTER | BG3: CARACTER | BH3: DECIMAL | BI3: DECIMAL | BJ3: ENTERO | BK3: CARACTER | BL3: DECIMAL | BM3: ENTERO | BN3: ENTERO
A4: 1 | B4: PILA E 91AA X 4U ENERGIZER ALCALINA | C4: 40 | D4: 0 | E4: 0 | F4: NO | G4: SI | H4: NO | I4: NO | J4: NO | K4: NO | L4: NO | M4: 37377 | P4: 039800011329 | Q4: 0 | R4: 0 | U4: 1 | V4: UNIDADES | W4: 40 | X4: 0 | Y4: 0 | Z4: NO | AA4: NO | AB4: NO | AC4: 0 | AD4: 0 | AE4: 0 | AF4: 0 | AG4: SI | AI4: 27 | AJ4: ENERGIZER ARGENTINA S.A. | AQ4: 0 | AR4: 0 | AS4: SI | AT4: 0 | AU4: 0 | AV4: 0 | AW4: 0 | AX4: NO | AY4: 0 | AZ4: 0 | BA4: 0 | BB4: 0 | BC4: 0 | BH4: 8 | BI4: 0 | BJ4: 0 | BL4: 0 | BM4: 0 | BN4: 0
A5: 2 | B5: PILA E 92 AAA X 2U ENERGIZER ALCALINA | C5: 48 | D5: 0 | E5: 0 | F5: NO | G5: SI | H5: NO | I5: NO | J5: NO | K5: NO | L5: NO | M5: 37377 | P5: 039800014009 | Q5: 0 | R5: 0 | U5: 1 | V5: UNIDADES | W5: 48 | X5: 0 | Y5: 0 | Z5: NO | AA5: NO | AB5: NO | AC5: 0 | AD5: 0 | AE5: 0 | AF5: 0 | AG5: SI | AI5: 27 | AJ5: ENERGIZER ARGENTINA S.A. | AQ5: 10 | AR5: 40 | AS5: SI | AT5: 0 | AU5: 0 | AV5: 0 | AW5: 0 | AX5: NO | AY5: 0 | AZ5: 0 | BA5: 0 | BB5: 0 | BC5: 0 | BH5: 4.8 | BI5: 0 | BJ5: 0 | BL5: 0 | BM5: 0 | BN5: 0
A6: 3 | B6: PILA E 93 C X 2U ENERGIZER ALCALINA | C6: 12 | D6: 0 | E6: 0 | F6: NO | G6: SI | H6: NO | I6: NO | J6: NO | K6: NO | L6: NO | M6: 37377 | P6: 039800011367 | Q6: 0 | R6: 0 | U6: 1 | V6: UNIDADES | W6: 12 | X6: 0 | Y6: 0 | Z6: NO | AA6: NO | AB6: NO | AC6: 0 | AD6: 0 | AE6: 0 | AF6: 0 | AG6: SI | AI6: 27 | AJ6: ENERGIZER ARGENTINA S.A. | AQ6: 10 | AR6: 40 | AS6: SI | AT6: 0 | AU6: 0 | AV6: 0 | AW6: 0 | AX6: NO | AY6: 0 | AZ6: 0 | BA6: 0 | BB6: 0 | BC6: 0 | BH6: 2.4 | BI6: 0 | BJ6: 0 | BL6: 0 | BM6: 0 | BN6: 0
A7: 4 | B7: PILA E 95 D X 2U ENERGIZER ALCALINA | C7: 12 | D7: 0 | E7: 0 | F7: NO | G7: SI | H7: NO | I7: NO | J7: NO | K7: NO | L7: NO | M7: 37377 | P7: 039800011398 | Q7: 0 | R7: 0 | U7: 1 | V7: UNIDADES | W7: 12 | X7: 0 | Y7: 0 | Z7: NO | AA7: NO | AB7: NO | AC7: 0 | AD7: 0 | AE7: 0 | AF7: 0 | AG7: SI | AI7: 27 | AJ7: ENERGIZER ARGENTINA S.A. | AQ7: 10 | AR7: 40 | AS7: SI | AT7: 0 | AU7: 0 | AV7: 0 | AW7: 0 | AX7: NO | AY7: 0 | AZ7: 0 | BA7: 0 | BB7: 0 | BC7: 0 | BH7: 3.48 | BI7: 0 | BJ7: 0 | BL7: 0 | BM7: 0 | BN7: 0
A8: 5 | B8: BATERIA 9V X 1U -522BP ENERGIZER ALCALIN | C8: 48 | D8: 0 | E8: 0 | F8: NO | G8: SI | H8: NO | I8: NO | J8: NO | K8: NO | L8: NO | M8: 37377 | O8: 039800013613 | Q8: 0 | R8: 0 | U8: 1 | V8: UNIDADES | W8: 48 | X8: 0 | Y8: 0 | Z8: NO | AA8: NO | AB8: NO | AC8: 0 | AD8: 0 | AE8: 0 | AF8: 0 | AG8: SI | AI8: 27 | AJ8: ENERGIZER ARGENTINA S.A. | AQ8: 10 | AR8: 40 | AS8: SI | AT8: 0 | AU8: 0 | AV8: 0 | AW8: 0 | AX8: NO | AY8: 0 | AZ8: 0 | BA8: 0 | BB8: 0 | BC8: 0 | BH8: 9.6 | BI8: 0 | BJ8: 0 | BL8: 0 | BM8: 0 | BN8: 0
A9: 6 | B9: CIERRE ZETA CON INTERNO | C9: 1 | D9: 0 | E9: 0 | F9: NO | G9: SI | H9: NO | I9: NO | J9: NO | K9: NO | L9: NO | M9: 44779 | N9: ADMINISTRACION | Q9: 0 | R9: 0 | U9: 1 | V9: UNIDADES | W9: 1 | X9: 0 | Y9: 0 | Z9: NO | AA9: NO | AB9: NO | AC9: 0 | AD9: 10 | AE9: 0 | AF9: 0 | AG9: NO | AI9: 0 | AQ9: 10 | AR9: 40 | AS9: SI | AT9: 0 | AU9: 0 | AV9: 0 | AW9: 0 | AX9: NO | AY9: 0 | AZ9: 0 | BA9: 0 | BB9: 0 | BC9: 6 | BH9: 0 | BI9: 0 | BJ9: 0 | BL9: 0 | BM9: 0 | BN9: 0
A10: 27 | B10: PEDIGREE ADTO RAZ PEQ ETAPA2 X1,5KG | C10: 9 | D10: 0 | E10: 0 | F10: NO | G10: SI | H10: NO | I10: NO | J10: NO | K10: NO | L10: NO | M10: 44810 | O10: 10255295 | P10: 7797453001564 | Q10: 0 | R10: 0 | U10: 2 | V10: KILOS | W10: 13.5 | X10: 0 | Y10: 0 | Z10: NO | AA10: NO | AB10: NO | AC10: 0 | AD10: 0 | AE10: 0 | AF10: 0 | AG10: SI | AI10: 48 | AJ10: MASTERFOODS ARGENTINA LTD. | AQ10: 10 | AR10: 40 | AS10: SI | AT10: 0 | AU10: 36 | AV10: 8 | AW10: 0 | AX10: NO | AY10: 0 | AZ10: 0 | BA10: 0 | BB10: 0 | BC10: 27 | BH10: 13.5 | BI10: 0 | BJ10: 0 | BL10: 0 | BM10: 0 | BN10: 0
A11: 156 | B11: LA GOTITA X 2 ML CHICA | C11: 240 | D11: 0 | E11: 0 | F11: NO | G11: SI | H11: NO | I11: NO | J11: NO | K11: NO | L11: NO | M11: 37377 | P11: 77917188 | Q11: 0 | R11: 0 | U11: 1 | V11: UNIDADES | W11: 240 | X11: 3 | Y11: 3 | Z11: NO | AA11: NO | AB11: NO | AC11: 0 | AD11: 0 | AE11: 0 | AF11: 0 | AG11: SI | AI11: 26 | AJ11: JORGE LUIS SUAREZ | AQ11: 10 | AR11: 40 | AS11: SI | AT11: 0 | AU11: 0 | AV11: 0 | AW11: 0 | AX11: NO | AY11: 0 | AZ11: 0 | BA11: 0 | BB11: 0 | BC11: 0 | BH11: 11.7 | BI11: 0 | BJ11: 0 | BL11: 0 | BM11: 0 | BN11: 0
A12: 157 | B12: LA GOTITA X 10 ML GRANDE | C12: 120 | D12: 0 | E12: 0 | F12: NO | G12: SI | H12: NO | I12: NO | J12: NO | K12: NO | L12: NO | M12: 37377 | P12: 7794122006004 | Q12: 0 | R12: 0 | U12: 1 | V12: UNIDADES | W12: 120 | X12: 0 | Y12: 0 | Z12: NO | AA12: NO | AB12: NO | AC12: 0 | AD12: 0 | AE12: 0 | AF12: 0 | AG12: SI | AI12: 26 | AJ12: JORGE LUIS SUAREZ | AQ12: 10 | AR12: 40 | AS12: SI | AT12: 0 | AU12: 0 | AV12: 0 | AW12: 0 | AX12: NO | AY12: 0 | AZ12: 0 | BA12: 0 | BB12: 0 | BC12: 0 | BH12: 8.16 | BI12: 0 | BJ12: 0 | BL12: 0 | BM12: 0 | BN12: 0
A13: 158 | B13: LA GOTITA GEL X 3 GR CHICO | C13: 240 | D13: 0 | E13: 0 | F13: NO | G13: SI | H13: NO | I13: NO | J13: NO | K13: NO | L13: NO | M13: 37377 | O13: 77906731 | Q13: 0 | R13: 0 | U13: 1 | V13: UNIDADES | W13: 240 | X13: 3 | Y13: 3 | Z13: NO | AA13: NO | AB13: NO | AC13: 0 | AD13: 0 | AE13: 0 | AF13: 0 | AG13: SI | AI13: 26 | AJ13: JORGE LUIS SUAREZ | AQ13: 10 | AR13: 40 | AS13: SI | AT13: 0 | AU13: 0 | AV13: 0 | AW13: 0 | AX13: NO | AY13: 0 | AZ13: 0 | BA13: 0 | BB13: 0 | BC13: 0 | BH13: 8.16 | BI13: 0 | BJ13: 0 | BL13: 0 | BM13: 0 | BN13: 0
A14: 159 | B14: POXI-RAN X 25 ML CHICO (23GR) | C14: 120 | D14: 0 | E14: 0 | F14: NO | G14: SI | H14: NO | I14: NO | J14: NO | K14: NO | L14: NO | M14: 37377 | O14: 1286564 | P14: 7794122013071 | Q14: 0 | R14: 0 | U14: 1 | V14: UNIDADES | W14: 120 | X14: 3 | Y14: 3 | Z14: NO | AA14: NO | AB14: NO | AC14: 0 | AD14: 0 | AE14: 0 | AF14: 0 | AG14: SI | AI14: 26 | AJ14: JORGE LUIS SUAREZ | AQ14: 10 | AR14: 40 | AS14: SI | AT14: 0 | AU14: 0 | AV14: 0 | AW14: 0 | AX14: NO | AY14: 0 | AZ14: 0 | BA14: 0 | BB14: 0 | BC14: 0 | BH14: 8.16 | BI14: 0 | BJ14: 0 | BL14: 0 | BM14: 0 | BN14: 0
A15: 160 | B15: POXI-RAN X 50 ML MEDIANO (45GR) | C15: 120 | D15: 0 | E15: 0 | F15: NO | G15: SI | H15: NO | I15: NO | J15: NO | K15: NO | L15: NO | M15: 37377 | P15: 7794122013088 | Q15: 0 | R15: 0 | U15: 1 | V15: UNIDADES | W15: 120 | X15: 0 | Y15: 0 | Z15: NO | AA15: NO | AB15: NO | AC15: 0 | AD15: 0 | AE15: 0 | AF15: 0 | AG15: SI | AI15: 26 | AJ15: JORGE LUIS SUAREZ | AQ15: 10 | AR15: 40 | AS15: SI | AT15: 0 | AU15: 0 | AV15: 0 | AW15: 0 | AX15: NO | AY15: 0 | AZ15: 0 | BA15: 0 | BB15: 0 | BC15: 0 | BH15: 22 | BI15: 0 | BJ15: 0 | BL15: 0 | BM15: 0 | BN15: 0
A16: 161 | B16: POXI-RAN X 100 ML. GRANDE (90GR) | C16: 48 | D16: 0 | E16: 0 | F16: NO | G16: SI | H16: NO | I16: NO | J16: NO | K16: NO | L16: NO | M16: 37377 | O16: 1148237 | P16: 7794122013095 | Q16: 0 | R16: 0 | U16: 1 | V16: UNIDADES | W16: 48 | X16: 0 | Y16: 0 | Z16: NO | AA16: NO | AB16: NO | AC16: 0 | AD16: 0 | AE16: 0 | AF16: 0 | AG16: SI | AI16: 26 | AJ16: JORGE LUIS SUAREZ | AQ16: 10 | AR16: 40 | AS16: SI | AT16: 0 | AU16: 0 | AV16: 0 | AW16: 0 | AX16: NO | AY16: 0 | AZ16: 0 | BA16: 0 | BB16: 0 | BC16: 0 | BH16: 8 | BI16: 0 | BJ16: 0 | BL16: 0 | BM16: 0 | BN16: 0
A17: 163 | B17: POXIPOL 10' X 14 ML. GRIS CHICO | C17: 240 | D17: 0 | E17: 0 | F17: NO | G17: SI | H17: NO | I17: NO | J17: NO | K17: NO | L17: NO | M17: 37377 | P17: 7790400014525 | Q17: 0 | R17: 0 | U17: 1 | V17: UNIDADES | W17: 240 | X17: 3 | Y17: 3 | Z17: NO | AA17: NO | AB17: NO | AC17: 0 | AD17: 0 | AE17: 0 | AF17: 0 | AG17: SI | AI17: 26 | AJ17: JORGE LUIS SUAREZ | AQ17: 10 | AR17: 40 | AS17: SI | AT17: 0 | AU17: 0 | AV17: 0 | AW17: 0 | AX17: NO | AY17: 0 | AZ17: 0 | BA17: 0 | BB17: 0 | BC17: 0 | BH17: 18 | BI17: 0 | BJ17: 0 | BL17: 0 | BM17: 0 | BN17: 0
A18: 164 | B18: POXIPOL 10' X 14 ML. TPTE. CHICO | C18: 240 | D18: 0 | E18: 0 | F18: NO | G18: SI | H18: NO | I18: NO | J18: NO | K18: NO | L18: NO | M18: 37377 | P18: 7790400014532 | Q18: 0 | R18: 0 | U18: 1 | V18: UNIDADES | W18: 240 | X18: 3 | Y18: 3 | Z18: NO | AA18: NO | AB18: NO | AC18: 0 | AD18: 0 | AE18: 0 | AF18: 0 | AG18: SI | AI18: 26 | AJ18: JORGE LUIS SUAREZ | AQ18: 10 | AR18: 40 | AS18: SI | AT18: 0 | AU18: 0 | AV18: 0 | AW18: 0 | AX18: NO | AY18: 0 | AZ18: 0 | BA18: 0 | BB18: 0 | BC18: 0 | BH18: 7 | BI18: 0 | BJ18: 0 | BL18: 0 | BM18: 0 | BN18: 0
A19: 165 | B19: POXIPOL 10' X 70 ML. GRIS MEDIANO | C19: 96 | D19: 0 | E19: 0 | F19: NO | G19: SI | H19: NO | I19: NO | J19: NO | K19: NO | L19: NO | M19: 37377 | P19: 7794122001184 | Q19: 0 | R19: 0 | U19: 1 | V19: UNIDADES | W19: 96 | X19: 0 | Y19: 0 | Z19: NO | AA19: NO | AB19: NO | AC19: 0 | AD19: 0 | AE19: 0 | AF19: 0 | AG19: SI | AI19: 26 | AJ19: JORGE LUIS SUAREZ | AQ19: 10 | AR19: 40 | AS19: SI | AT19: 0 | AU19: 0 | AV19: 0 | AW19: 0 | AX19: NO | AY19: 0 | AZ19: 0 | BA19: 0 | BB19: 0 | BC19: 0 | BH19: 15 | BI19: 0 | BJ19: 0 | BL19: 0 | BM19: 0 | BN19: 0
A20: 166 | B20: POXIPOL 10' X 70 ML. TPTE. MEDIANO | C20: 96 | D20: 0 | E20: 0 | F20: NO | G20: SI | H20: NO | I20: NO | J20: NO | K20: NO | L20: NO | M20: 37377 | P20: 7794122001221 | Q20: 0 | R20: 0 | U20: 1 | V20: UNIDADES | W20: 96 | X20: 0 | Y20: 0 | Z20: NO | AA20: NO | AB20: NO | AC20: 0 | AD20: 0 | AE20: 0 | AF20: 0 | AG20: SI | AI20: 26 | AJ20: JORGE LUIS SUAREZ | AQ20: 10 | AR20: 40 | AS20: SI | AT20: 0 | AU20: 0 | AV20: 0 | AW20: 0 | AX20: NO | AY20: 0 | AZ20: 0 | BA20: 0 | BB20: 0 | BC20: 0 | BH20: 15 | BI20: 0 | BJ20: 0 | BL20: 0 | BM20: 0 | BN20: 0
A21: 170 | B21: FASTIX X 25 ML. ALT. TEMP. CHICO | C21: 120 | D21: 0 | E21: 0 | F21: NO | G21: SI | H21: NO | I21: NO | J21: NO | K21: NO | L21: NO | M21: 37377 | P21: 7790400017243 | Q21: 0 | R21: 0 | U21: 1 | V21: UNIDADES | W21: 120 | X21: 3 | Y21: 3 | Z21: NO | AA21: NO | AB21: NO | AC21: 0 | AD21: 0 | AE21: 0 | AF21: 0 | AG21: SI | AI21: 26 | AJ21: JORGE LUIS SUAREZ | AQ21: 10 | AR21: 40 | AS21: SI | AT21: 0 | AU21: 0 | AV21: 0 | AW21: 0 | AX21: NO | AY21: 0 | AZ21: 0 | BA21: 0 | BB21: 0 | BC21: 0 | BH21: 15 | BI21: 0 | BJ21: 0 | BL21: 0 | BM21: 0 | BN21: 0
A22: 174 | B22: POXILINA 10' X 70 GR CHICA | C22: 120 | D22: 0 | E22: 0 | F22: NO | G22: SI | H22: NO | I22: NO | J22: NO | K22: NO | L22: NO | M22: 37377 | O22: 1333765 | P22: 7794122001870 | Q22: 0 | R22: 0 | U22: 1 | V22: UNIDADES | W22: 120 | X22: 3 | Y22: 3 | Z22: NO | AA22: NO | AB22: NO | AC22: 0 | AD22: 0 | AE22: 0 | AF22: 0 | AG22: SI | AI22: 26 | AJ22: JORGE LUIS SUAREZ | AQ22: 10 | AR22: 40 | AS22: SI | AT22: 0 | AU22: 0 | AV22: 0 | AW22: 0 | AX22: NO | AY22: 0 | AZ22: 0 | BA22: 0 | BB22: 0 | BC22: 0 | BH22: 8.16 | BI22: 0 | BJ22: 0 | BL22: 0 | BM22: 0 | BN22: 0
A23: 175 | B23: POXILINA 10' X 250 GR. MEDIANA | C23: 120 | D23: 0 | E23: 0 | F23: NO | G23: SI | H23: NO | I23: NO | J23: NO | K23: NO | L23: NO | M23: 37377 | Q23: 0 | R23: 0 | U23: 1 | V23: UNIDADES | W23: 120 | X23: 0 | Y23: 0 | Z23: NO | AA23: NO | AB23: NO | AC23: 0 | AD23: 0 | AE23: 0 | AF23: 0 | AG23: SI | AI23: 26 | AJ23: JORGE LUIS SUAREZ | AQ23: 10 | AR23: 40 | AS23: SI | AT23: 0 | AU23: 0 | AV23: 0 | AW23: 0 | AX23: NO | AY23: 0 | AZ23: 0 | BA23: 0 | BB23: 0 | BC23: 0 | BH23: 8.16 | BI23: 0 | BJ23: 0 | BL23: 0 | BM23: 0 | BN23: 0
A24: 176 | B24: POXITAS X 12 U. | C24: 240 | D24: 0 | E24: 0 | F24: NO | G24: SI | H24: NO | I24: NO | J24: NO | K24: NO | L24: NO | M24: 37377 | P24: 7790400005721 | Q24: 0 | R24: 0 | U24: 1 | V24: UNIDADES | W24: 240 | X24: 3 | Y24: 3 | Z24: NO | AA24: NO | AB24: NO | AC24: 0 | AD24: 0 | AE24: 0 | AF24: 0 | AG24: SI | AI24: 26 | AJ24: JORGE LUIS SUAREZ | AK24: ST00572 | AQ24: 10 | AR24: 40 | AS24: SI | AT24: 0 | AU24: 0 | AV24: 0 | AW24: 0 | AX24: NO | AY24: 0 | AZ24: 0 | BA24: 0 | BB24: 0 | BC24: 0 | BH24: 8.16 | BI24: 0 | BJ24: 0 | BL24: 0 | BM24: 0 | BN24: 0
A25: 178 | B25: VOLIGOMA X 30 ML.X 12U CHICA | C25: 12 | D25: 0 | E25: 0 | F25: NO | G25: SI | H25: NO | I25: NO | J25: NO | K25: NO | L25: NO | M25: 37377 | O25: 156257 | P25: 7790400010503 | Q25: 0 | R25: 0 | U25: 1 | V25: UNIDADES | W25: 12 | X25: 0 | Y25: 0 | Z25: NO | AA25: NO | AB25: NO | AC25: 0 | AD25: 0 | AE25: 0 | AF25: 0 | AG25: SI | AI25: 26 | AJ25: JORGE LUIS SUAREZ | AQ25: 10 | AR25: 40 | AS25: SI | AT25: 0 | AU25: 0 | AV25: 0 | AW25: 0 | AX25: NO | AY25: 0 | AZ25: 0 | BA25: 0 | BB25: 0 | BC25: 0 | BH25: 8.16 | BI25: 0 | BJ25: 0 | BL25: 0 | BM25: 0 | BN25: 0
A26: 179 | B26: VOLIGOMA X 50 ML X12 U GRANDE | C26: 8 | D26: 0 | E26: 0 | F26: NO | G26: SI | H26: NO | I26: NO | J26: NO | K26: NO | L26: NO | M26: 37377 | O26: 1274213 | P26: 7790400010510 | Q26: 0 | R26: 0 | U26: 1 | V26: UNIDADES | W26: 8 | X26: 0 | Y26: 0 | Z26: NO | AA26: NO | AB26: NO | AC26: 0 | AD26: 0 | AE26: 0 | AF26: 0 | AG26: SI | AI26: 26 | AJ26: JORGE LUIS SUAREZ | AQ26: 10 | AR26: 40 | AS26: SI | AT26: 0 | AU26: 0 | AV26: 0 | AW26: 0 | AX26: NO | AY26: 0 | AZ26: 0 | BA26: 0 | BB26: 0 | BC26: 0 | BH26: 13.5 | BI26: 0 | BJ26: 0 | BL26: 0 | BM26: 0 | BN26: 0
A27: 236 | B27: MALTA EL POCILLO POTE X 170GR | C27: 6 | D27: 0 | E27: 0 | F27: NO | G27: SI | H27: NO | I27: NO | J27: NO | K27: NO | L27: NO | M27: 37377 | O27: 7791118000503 | P27: 7791118002224 | Q27: 0 | R27: 0 | U27: 1 | V27: UNIDADES | W27: 6 | X27: 0 | Y27: 0 | Z27: NO | AA27: NO | AB27: NO | AC27: 0 | AD27: 0 | AE27: 0 | AF27: 0 | AG27: NO | AI27: 46 | AJ27: LHERITIER ARGENTINA S.A. | AQ27: 10 | AR27: 40 | AS27: SI | AT27: 0 | AU27: 252 | AV27: 0 | AW27: 0 | AX27: NO | AY27: 0 | AZ27: 0 | BA27: 0 | BB27: 0 | BC27: 0 | BH27: 1.2 | BI27: 0 | BJ27: 0 | BL27: 0 | BM27: 0 | BN27: 0
A28: 273 | B28: ALKA CARAMELOS STRONG X 800 GR | C28: 10 | D28: 0 | E28: 0 | F28: NO | G28: SI | H28: NO | I28: NO | J28: NO | K28: NO | L28: NO | M28: 37377 | P28: 7794612002769 | Q28: 0 | R28: 0 | U28: 1 | V28: UNIDADES | W28: 10 | X28: 0 | Y28: 0 | Z28: NO | AA28: NO | AB28: NO | AC28: 0 | AD28: 0 | AE28: 0 | AF28: 0 | AG28: NO | AI28: 215 | AJ28: ARCOR S.A.I.C. | AQ28: 10 | AR28: 40 | AS28: SI | AT28: 0 | AU28: 96 | AV28: 0 | AW28: 0 | AX28: NO | AY28: 0 | AZ28: 0 | BA28: 0 | BB28: 0 | BC28: 0 | BH28: 8 | BI28: 0 | BJ28: 0 | BL28: 0 | BM28: 0 | BN28: 0
A29: 274 | B29: ALKA CARAMELOS MENTA X 800 GR | C29: 10 | D29: 0 | E29: 0 | F29: NO | G29: SI | H29: NO | I29: NO | J29: NO | K29: NO | L29: NO | M29: 37377 | P29: 7794612011105 | Q29: 0 | R29: 0 | U29: 1 | V29: UNIDADES | W29: 10 | X29: 0 | Y29: 0 | Z29: NO | AA29: NO | AB29: NO | AC29: 0 | AD29: 0 | AE29: 0 | AF29: 0 | AG29: NO | AI29: 215 | AJ29: ARCOR S.A.I.C. | AQ29: 10 | AR29: 40 | AS29: SI | AT29: 0 | AU29: 0 | AV29: 0 | AW29: 0 | AX29: NO | AY29: 0 | AZ29: 0 | BA29: 0 | BB29: 0 | BC29: 0 | BH29: 8 | BI29: 0 | BJ29: 0 | BL29: 0 | BM29: 0 | BN29: 0
A30: 279 | B30: PILA 1212 AAA X24U EVD EXTRA DURAC - CAJA | C30: 24 | D30: 0 | E30: 0 | F30: NO | G30: SI | H30: NO | I30: NO | J30: NO | K30: NO | L30: NO | M30: 37377 | O30: 7501037601718 | P30: 7807350000710 | Q30: 0 | R30: 0 | U30: 0 | W30: 0 | X30: 0 | Y30: 0 | Z30: NO | AA30: NO | AB30: NO | AC30: 0 | AD30: 0 | AE30: 0 | AF30: 0 | AG30: SI | AI30: 27 | AJ30: ENERGIZER ARGENTINA S.A. | AQ30: 10 | AR30: 40 | AS30: SI | AT30: 0 | AU30: 0 | AV30: 0 | AW30: 0 | AX30: NO | AY30: 0 | AZ30: 0 | BA30: 0 | BB30: 0 | BC30: 0 | BH30: 0 | BI30: 0 | BJ30: 0 | BL30: 0 | BM30: 0 | BN30: 0
A31: 307 | B31: SARDINA EN ACEITE X 125GR GDC | C31: 50 | D31: 0 | E31: 0 | F31: NO | G31: SI | H31: NO | I31: NO | J31: NO | K31: NO | L31: NO | M31: 37377 | P31: 7891167021013 | Q31: 0 | R31: 0 | U31: 0 | W31: 0 | X31: 0 | Y31: 0 | Z31: NO | AA31: NO | AB31: NO | AC31: 0 | AD31: 0 | AE31: 0 | AF31: 0 | AG31: NO | AI31: 108 | AJ31: GOMES DA COSTA ARGENTINA S.A. | AQ31: 10 | AR31: 40 | AS31: SI | AT31: 0 | AU31: 0 | AV31: 0 | AW31: 0 | AX31: NO | AY31: 0 | AZ31: 0 | BA31: 0 | BB31: 0 | BC31: 0 | BH31: 13.5 | BI31: 0 | BJ31: 0 | BL31: 0 | BM31: 0 | BN31: 0
A32: 308 | B32: SARDINA CON TOMATE X125GR GDC | C32: 50 | D32: 0 | E32: 0 | F32: NO | G32: SI | H32: NO | I32: NO | J32: NO | K32: NO | L32: NO | M32: 37377 | P32: 7891167831384 | Q32: 0 | R32: 0 | U32: 0 | W32: 0 | X32: 0 | Y32: 0 | Z32: NO | AA32: NO | AB32: NO | AC32: 0 | AD32: 0 | AE32: 0 | AF32: 0 | AG32: NO | AI32: 108 | AJ32: GOMES DA COSTA ARGENTINA S.A. | AQ32: 10 | AR32: 40 | AS32: SI | AT32: 0 | AU32: 0 | AV32: 0 | AW32: 0 | AX32: NO | AY32: 0 | AZ32: 0 | BA32: 0 | BB32: 0 | BC32: 0 | BH32: 13.5 | BI32: 0 | BJ32: 0 | BL32: 0 | BM32: 0 | BN32: 0
A33: 311 | B33: LOMO ATUN EN ACEITE X 170 GR | C33: 24 | D33: 0 | E33: 0 | F33: NO | G33: SI | H33: NO | I33: NO | J33: NO | K33: NO | L33: NO | M33: 37377 | P33: 7891167831117 | Q33: 0 | R33: 0 | U33: 0 | W33: 0 | X33: 0 | Y33: 0 | Z33: NO | AA33: NO | AB33: NO | AC33: 0 | AD33: 0 | AE33: 0 | AF33: 0 | AG33: NO | AI33: 108 | AJ33: GOMES DA COSTA ARGENTINA S.A. | AQ33: 10 | AR33: 40 | AS33: SI | AT33: 0 | AU33: 0 | AV33: 0 | AW33: 0 | AX33: NO | AY33: 0 | AZ33: 0 | BA33: 0 | BB33: 0 | BC33: 0 | BH33: 18 | BI33: 0 | BJ33: 0 | BL33: 0 | BM33: 0 | BN33: 0
A34: 312 | B34: ATUN DESMENUZADO EN ACEITE X 170 GR | C34: 24 | D34: 0 | E34: 0 | F34: NO | G34: SI | H34: NO | I34: NO | J34: NO | K34: NO | L34: NO | M34: 37377 | P34: 7891167831094 | Q34: 0 | R34: 0 | U34: 0 | W34: 0 | X34: 0 | Y34: 0 | Z34: NO | AA34: NO | AB34: NO | AC34: 0 | AD34: 0 | AE34: 0 | AF34: 0 | AG34: NO | AI34: 108 | AJ34: GOMES DA COSTA ARGENTINA S.A. | AQ34: 10 | AR34: 40 | AS34: SI | AT34: 0 | AU34: 0 | AV34: 0 | AW34: 0 | AX34: NO | AY34: 0 | AZ34: 0 | BA34: 0 | BB34: 0 | BC34: 0 | BH34: 18 | BI34: 0 | BJ34: 0 | BL34: 0 | BM34: 0 | BN34: 0
A35: 313 | B35: LOMO ATUN AL NATURAL X 170 GR | C35: 24 | D35: 0 | E35: 0 | F35: NO | G35: SI | H35: NO | I35: NO | J35: NO | K35: NO | L35: NO | M35: 37377 | P35: 7891167831100 | Q35: 0 | R35: 0 | U35: 0 | W35: 0 | X35: 0 | Y35: 0 | Z35: NO | AA35: NO | AB35: NO | AC35: 0 | AD35: 0 | AE35: 0 | AF35: 0 | AG35: NO | AI35: 108 | AJ35: GOMES DA COSTA ARGENTINA S.A. | AQ35: 10 | AR35: 40 | AS35: SI | AT35: 0 | AU35: 0 | AV35: 0 | AW35: 0 | AX35: NO | AY35: 0 | AZ35: 0 | BA35: 0 | BB35: 0 | BC35: 0 | BH35: 18 | BI35: 0 | BJ35: 0 | BL35: 0 | BM35: 0 | BN35: 0
A36: 314 | B36: ATUN DESMENUZADO EN NATURAL X 170 GR | C36: 24 | D36: 0 | E36: 0 | F36: NO | G36: SI | H36: NO | I36: NO | J36: NO | K36: NO | L36: NO | M36: 37377 | P36: 7891167831087 | Q36: 0 | R36: 0 | U36: 0 | W36: 0 | X36: 0 | Y36: 0 | Z36: NO | AA36: NO | AB36: NO | AC36: 0 | AD36: 0 | AE36: 0 | AF36: 0 | AG36: NO | AI36: 108 | AJ36: GOMES DA COSTA ARGENTINA S.A. | AQ36: 10 | AR36: 40 | AS36: SI | AT36: 0 | AU36: 0 | AV36: 0 | AW36: 0 | AX36: NO | AY36: 0 | AZ36: 0 | BA36: 0 | BB36: 0 | BC36: 0 | BH36: 4.08 | BI36: 0 | BJ36: 0 | BL36: 0 | BM36: 0 | BN36: 0
A37: 318 | B37: GOMITAS MISKY JELLY ROLL X 1 KG | C37: 6 | D37: 0 | E37: 0 | F37: NO | G37: SI | H37: NO | I37: NO | J37: NO | K37: NO | L37: NO | M37: 37377 | P37: 7790580640101 | Q37: 0 | R37: 0 | U37: 0 | W37: 0 | X37: 0 | Y37: 0 | Z37: NO | AA37: NO | AB37: NO | AC37: 0 | AD37: 0 | AE37: 0 | AF37: 0 | AG37: NO | AI37: 215 | AJ37: ARCOR S.A.I.C. | AQ37: 10 | AR37: 40 | AS37: SI | AT37: 0 | AU37: 150 | AV37: 0 | AW37: 0 | AX37: NO | AY37: 0 | AZ37: 0 | BA37: 0 | BB37: 0 | BC37: 0 | BH37: 6 | BI37: 0 | BJ37: 0 | BL37: 0 | BM37: 0 | BN37: 0
A38: 344 | B38: PILA E 91 AA X 2U ENERGIZER ALCALINA | C38: 48 | D38: 0 | E38: 0 | F38: NO | G38: SI | H38: NO | I38: NO | J38: NO | K38: NO | L38: NO | M38: 37377 | O38: 8888021305708 | P38: 039800015464 | Q38: 0 | R38: 0 | U38: 0 | W38: 0 | X38: 0 | Y38: 0 | Z38: NO | AA38: NO | AB38: NO | AC38: 0 | AD38: 0 | AE38: 0 | AF38: 0 | AG38: SI | AI38: 27 | AJ38: ENERGIZER ARGENTINA S.A. | AQ38: 10 | AR38: 40 | AS38: SI | AT38: 0 | AU38: 0 | AV38: 0 | AW38: 0 | AX38: NO | AY38: 0 | AZ38: 0 | BA38: 0 | BB38: 0 | BC38: 0 | BH38: 13.5 | BI38: 0 | BJ38: 0 | BL38: 0 | BM38: 0 | BN38: 0
A39: 345 | B39: PILA E 91AA X 8U ENERGIZER ALCALINA | C39: 72 | D39: 0 | E39: 0 | F39: NO | G39: SI | H39: NO | I39: NO | J39: NO | K39: NO | L39: NO | M39: 37377 | P39: 039800032874 | Q39: 0 | R39: 0 | U39: 0 | W39: 0 | X39: 0 | Y39: 0 | Z39: NO | AA39: NO | AB39: NO | AC39: 0 | AD39: 0 | AE39: 0 | AF39: 0 | AG39: SI | AI39: 27 | AJ39: ENERGIZER ARGENTINA S.A. | AQ39: 10 | AR39: 40 | AS39: SI | AT39: 0 | AU39: 0 | AV39: 0 | AW39: 0 | AX39: NO | AY39: 0 | AZ39: 0 | BA39: 0 | BB39: 0 | BC39: 0 | BH39: 18 | BI39: 0 | BJ39: 0 | BL39: 0 | BM39: 0 | BN39: 0
A40: 346 | B40: PILA E 92 AAA X 4U ENERGIZER ALCALINA | C40: 40 | D40: 0 | E40: 0 | F40: NO | G40: SI | H40: NO | I40: NO | J40: NO | K40: NO | L40: NO | M40: 37377 | P40: 039800099099 | Q40: 0 | R40: 0 | U40: 0 | W40: 0 | X40: 0 | Y40: 0 | Z40: NO | AA40: NO | AB40: NO | AC40: 0 | AD40: 0 | AE40: 0 | AF40: 0 | AG40: SI | AI40: 27 | AJ40: ENERGIZER ARGENTINA S.A. | AQ40: 10 | AR40: 40 | AS40: SI | AT40: 0 | AU40: 0 | AV40: 0 | AW40: 0 | AX40: NO | AY40: 0 | AZ40: 0 | BA40: 0 | BB40: 0 | BC40: 0 | BH40: 0 | BI40: 0 | BJ40: 0 | BL40: 0 | BM40: 0 | BN40: 0
A41: 362 | B41: BANANINA X30U. X 15G | C41: 12 | D41: 0 | E41: 0 | F41: NO | G41: SI | H41: NO | I41: NO | J41: NO | K41: NO | L41: NO | M41: 37377 | P41: 7790206008407 | Q41: 0 | R41: 0 | U41: 0 | W41: 0 | X41: 0 | Y41: 0 | Z41: NO | AA41: NO | AB41: NO | AC41: 0 | AD41: 0 | AE41: 0 | AF41: 0 | AG41: NO | AI41: 49 | AJ41: LA DELICIA FELIPE FORT S.A. | AK41: 840 | AQ41: 10 | AR41: 40 | AS41: SI | AT41: 0 | AU41: 60 | AV41: 6 | AW41: 0 | AX41: NO | AY41: 0 | AZ41: 0 | BA41: 0 | BB41: 0 | BC41: 0 | BH41: 0.63 | BI41: 0 | BJ41: 0 | BL41: 0 | BM41: 0 | BN41: 0
A42: 365 | B42: FLYNN PAFF FRUTILLA-VAINILLA X 70U X 8GR | C42: 12 | D42: 0 | E42: 0 | F42: NO | G42: SI | H42: NO | I42: NO | J42: NO | K42: NO | L42: NO | M42: 37377 | P42: 7790380011804 | Q42: 0 | R42: 0 | U42: 1 | V42: UNIDADES | W42: 12 | X42: 0 | Y42: 0 | Z42: NO | AA42: NO | AB42: NO | AC42: 0 | AD42: 0 | AE42: 0 | AF42: 0 | AG42: NO | AI42: 51 | AJ42: GEORGALOS HNOS. S.A.I.C.A. | AQ42: 10 | AR42: 40 | AS42: SI | AT42: 0 | AU42: 0 | AV42: 0 | AW42: 0 | AX42: NO | AY42: 0 | AZ42: 0 | BA42: 0 | BB42: 0 | BC42: 0 | BH42: 0 | BI42: 0 | BJ42: 0 | BL42: 0 | BM42: 0 | BN42: 0
A43: 395 | B43: PILA 357 / 303 X 5U ESP RELOJERIA PLATA | C43: 20 | D43: 0 | E43: 0 | F43: NO | G43: SI | H43: NO | I43: NO | J43: NO | K43: NO | L43: NO | M43: 37377 | P43: 039800111005 | Q43: 0 | R43: 0 | U43: 0 | W43: 0 | X43: 0 | Y43: 0 | Z43: NO | AA43: NO | AB43: NO | AC43: 0 | AD43: 0 | AE43: 0 | AF43: 0 | AG43: SI | AI43: 27 | AJ43: ENERGIZER ARGENTINA S.A. | AQ43: 10 | AR43: 40 | AS43: SI | AT43: 0 | AU43: 0 | AV43: 0 | AW43: 0 | AX43: NO | AY43: 0 | AZ43: 0 | BA43: 0 | BB43: 0 | BC43: 0 | BH43: 0.93 | BI43: 0 | BJ43: 0 | BL43: 0 | BM43: 0 | BN43: 0
A44: 397 | B44: PILA 364 / 363 X 5U ESP RELOJERIA PLATA | C44: 20 | D44: 0 | E44: 0 | F44: NO | G44: SI | H44: NO | I44: NO | J44: NO | K44: NO | L44: NO | M44: 37377 | P44: 039800109675 | Q44: 0 | R44: 0 | U44: 0 | W44: 0 | X44: 0 | Y44: 0 | Z44: NO | AA44: NO | AB44: NO | AC44: 0 | AD44: 0 | AE44: 0 | AF44: 0 | AG44: SI | AI44: 27 | AJ44: ENERGIZER ARGENTINA S.A. | AQ44: 10 | AR44: 40 | AS44: SI | AT44: 0 | AU44: 0 | AV44: 0 | AW44: 0 | AX44: NO | AY44: 0 | AZ44: 0 | BA44: 0 | BB44: 0 | BC44: 0 | BH44: 1.54 | BI44: 0 | BJ44: 0 | BL44: 0 | BM44: 0 | BN44: 0
A45: 400 | B45: PILA 377 / 376 X 5U ESP RELOJERIA PLATA | C45: 20 | D45: 0 | E45: 0 | F45: NO | G45: SI | H45: NO | I45: NO | J45: NO | K45: NO | L45: NO | M45: 37377 | P45: 039800111036 | Q45: 0 | R45: 0 | U45: 0 | W45: 0 | X45: 0 | Y45: 0 | Z45: NO | AA45: NO | AB45: NO | AC45: 0 | AD45: 0 | AE45: 0 | AF45: 0 | AG45: SI | AI45: 27 | AJ45: ENERGIZER ARGENTINA S.A. | AQ45: 10 | AR45: 40 | AS45: SI | AT45: 0 | AU45: 0 | AV45: 0 | AW45: 0 | AX45: NO | AY45: 0 | AZ45: 0 | BA45: 0 | BB45: 0 | BC45: 0 | BH45: 2.88 | BI45: 0 | BJ45: 0 | BL45: 0 | BM45: 0 | BN45: 0
A46: 407 | B46: BATERIA ENERGIZER ALCALINA X 2U -A23 | C46: 6 | D46: 0 | E46: 0 | F46: NO | G46: SI | H46: NO | I46: NO | J46: NO | K46: NO | L46: NO | M46: 37377 | P46: 039800110091 | Q46: 0 | R46: 0 | U46: 0 | W46: 0 | X46: 0 | Y46: 0 | Z46: NO | AA46: NO | AB46: NO | AC46: 0 | AD46: 0 | AE46: 0 | AF46: 0 | AG46: SI | AI46: 27 | AJ46: ENERGIZER ARGENTINA S.A. | AQ46: 10 | AR46: 40 | AS46: SI | AT46: 0 | AU46: 0 | AV46: 0 | AW46: 0 | AX46: NO | AY46: 0 | AZ46: 0 | BA46: 0 | BB46: 0 | BC46: 0 | BH46: 1.4 | BI46: 0 | BJ46: 0 | BL46: 0 | BM46: 0 | BN46: 0
A47: 408 | B47: PILA A544 6V X 1U ENERGIZER ALCALINA | C47: 6 | D47: 0 | E47: 0 | F47: NO | G47: SI | H47: NO | I47: NO | J47: NO | K47: NO | L47: NO | M47: 37377 | P47: 39800110114 | Q47: 0 | R47: 0 | U47: 0 | W47: 0 | X47: 0 | Y47: 0 | Z47: NO | AA47: NO | AB47: NO | AC47: 0 | AD47: 0 | AE47: 0 | AF47: 0 | AG47: SI | AI47: 27 | AJ47: ENERGIZER ARGENTINA S.A. | AQ47: 10 | AR47: 40 | AS47: SI | AT47: 0 | AU47: 0 | AV47: 0 | AW47: 0 | AX47: NO | AY47: 0 | AZ47: 0 | BA47: 0 | BB47: 0 | BC47: 0 | BH47: 14 | BI47: 0 | BJ47: 0 | BL47: 0 | BM47: 0 | BN47: 0
A48: 409 | B48: PILA A 76 X 1U ESPECIAL ENERGIZER | C48: 6 | D48: 0 | E48: 0 | F48: NO | G48: SI | H48: NO | I48: NO | J48: NO | K48: NO | L48: NO | M48: 37377 | P48: 39800110909 | Q48: 0 | R48: 0 | U48: 0 | W48: 0 | X48: 0 | Y48: 0 | Z48: NO | AA48: NO | AB48: NO | AC48: 0 | AD48: 0 | AE48: 0 | AF48: 0 | AG48: SI | AI48: 27 | AJ48: ENERGIZER ARGENTINA S.A. | AQ48: 10 | AR48: 40 | AS48: SI | AT48: 0 | AU48: 0 | AV48: 0 | AW48: 0 | AX48: NO | AY48: 0 | AZ48: 0 | BA48: 0 | BB48: 0 | BC48: 0 | BH48: 1.6 | BI48: 0 | BJ48: 0 | BL48: 0 | BM48: 0 | BN48: 0
A49: 410 | B49: BATERIA LITIO FOTOGRAFIA X 1U -EL1CR2BP | C49: 6 | D49: 0 | E49: 0 | F49: NO | G49: SI | H49: NO | I49: NO | J49: NO | K49: NO | L49: NO | M49: 37377 | P49: 39800075062 | Q49: 0 | R49: 0 | U49: 0 | W49: 0 | X49: 0 | Y49: 0 | Z49: NO | AA49: NO | AB49: NO | AC49: 0 | AD49: 0 | AE49: 0 | AF49: 0 | AG49: SI | AI49: 27 | AJ49: ENERGIZER ARGENTINA S.A. | AQ49: 10 | AR49: 40 | AS49: SI | AT49: 0 | AU49: 0 | AV49: 0 | AW49: 0 | AX49: NO | AY49: 0 | AZ49: 0 | BA49: 0 | BB49: 0 | BC49: 0 | BH49: 2 | BI49: 0 | BJ49: 0 | BL49: 0 | BM49: 0 | BN49: 0
A50: 411 | B50: PILA E 90 (N 2) X 2U ENERGIZER ALCALINA | C50: 6 | D50: 0 | E50: 0 | F50: NO | G50: SI | H50: NO | I50: NO | J50: NO | K50: NO | L50: NO | M50: 37377 | P50: 39800013200 | Q50: 0 | R50: 0 | U50: 0 | W50: 0 | X50: 0 | Y50: 0 | Z50: NO | AA50: NO | AB50: NO | AC50: 0 | AD50: 0 | AE50: 0 | AF50: 0 | AG50: SI | AI50: 27 | AJ50: ENERGIZER ARGENTINA S.A. | AQ50: 10 | AR50: 40 | AS50: SI | AT50: 0 | AU50: 0 | AV50: 0 | AW50: 0 | AX50: NO | AY50: 0 | AZ50: 0 | BA50: 0 | BB50: 0 | BC50: 0 | BH50: 0 | BI50: 0 | BJ50: 0 | BL50: 0 | BM50: 0 | BN50: 0
A51: 412 | B51: PILA E 96 AAAA X 2U ENERGIZER ALCALINA | C51: 12 | D51: 0 | E51: 0 | F51: NO | G51: SI | H51: NO | I51: NO | J51: NO | K51: NO | L51: NO | M51: 37377 | P51: 39800030771 | Q51: 0 | R51: 0 | U51: 0 | W51: 0 | X51: 0 | Y51: 0 | Z51: NO | AA51: NO | AB51: NO | AC51: 0 | AD51: 0 | AE51: 0 | AF51: 0 | AG51: SI | AI51: 27 | AJ51: ENERGIZER ARGENTINA S.A. | AQ51: 10 | AR51: 40 | AS51: SI | AT51: 0 | AU51: 0 | AV51: 0 | AW51: 0 | AX51: NO | AY51: 0 | AZ51: 0 | BA51: 0 | BB51: 0 | BC51: 0 | BH51: 0 | BI51: 0 | BJ51: 0 | BL51: 0 | BM51: 0 | BN51: 0
A52: 413 | B52: PILA EL123 X 1U LITIO FOTO ENERGIZER | C52: 24 | D52: 0 | E52: 0 | F52: NO | G52: SI | H52: NO | I52: NO | J52: NO | K52: NO | L52: NO | M52: 37377 | P52: 039800041098 | Q52: 0 | R52: 0 | U52: 0 | W52: 0 | X52: 0 | Y52: 0 | Z52: NO | AA52: NO | AB52: NO | AC52: 0 | AD52: 0 | AE52: 0 | AF52: 0 | AG52: SI | AI52: 27 | AJ52: ENERGIZER ARGENTINA S.A. | AQ52: 10 | AR52: 40 | AS52: SI | AT52: 0 | AU52: 0 | AV52: 0 | AW52: 0 | AX52: NO | AY52: 0 | AZ52: 0 | BA52: 0 | BB52: 0 | BC52: 0 | BH52: 1.02 | BI52: 0 | BJ52: 0 | BL52: 0 | BM52: 0 | BN52: 0
A53: 421 | B53: PILA L 91AA X 2U LITIO FOTO ENERGIZER | C53: 24 | D53: 0 | E53: 0 | F53: NO | G53: SI | H53: NO | I53: NO | J53: NO | K53: NO | L53: NO | M53: 37377 | P53: 39800034083 | Q53: 0 | R53: 0 | U53: 0 | W53: 0 | X53: 0 | Y53: 0 | Z53: NO | AA53: NO | AB53: NO | AC53: 0 | AD53: 0 | AE53: 0 | AF53: 0 | AG53: SI | AI53: 27 | AJ53: ENERGIZER ARGENTINA S.A. | AQ53: 10 | AR53: 40 | AS53: SI | AT53: 0 | AU53: 0 | AV53: 0 | AW53: 0 | AX53: NO | AY53: 0 | AZ53: 0 | BA53: 0 | BB53: 0 | BC53: 0 | BH53: 1.2 | BI53: 0 | BJ53: 0 | BL53: 0 | BM53: 0 | BN53: 0
A54: 438 | B54: POXI-RAN X 250 ML. LATA (225G) | C54: 48 | D54: 0 | E54: 0 | F54: NO | G54: SI | H54: NO | I54: NO | J54: NO | K54: NO | L54: NO | M54: 37377 | P54: 7794122013118 | Q54: 0 | R54: 0 | U54: 0 | W54: 0 | X54: 0 | Y54: 0 | Z54: NO | AA54: NO | AB54: NO | AC54: 0 | AD54: 0 | AE54: 0 | AF54: 0 | AG54: SI | AI54: 26 | AJ54: JORGE LUIS SUAREZ | AQ54: 10 | AR54: 40 | AS54: SI | AT54: 0 | AU54: 0 | AV54: 0 | AW54: 0 | AX54: NO | AY54: 0 | AZ54: 0 | BA54: 0 | BB54: 0 | BC54: 0 | BH54: 1.02 | BI54: 0 | BJ54: 0 | BL54: 0 | BM54: 0 | BN54: 0
A55: 454 | B55: CARAM MASTICABLE LHERITIER X450 GR X147U | C55: 10 | D55: 0 | E55: 0 | F55: NO | G55: SI | H55: NO | I55: NO | J55: NO | K55: NO | L55: NO | M55: 37377 | P55: 7792860000735 | Q55: 0 | R55: 0 | U55: 0 | W55: 0 | X55: 0 | Y55: 0 | Z55: NO | AA55: NO | AB55: NO | AC55: 0 | AD55: 0 | AE55: 0 | AF55: 0 | AG55: NO | AI55: 46 | AJ55: LHERITIER ARGENTINA S.A. | AQ55: 10 | AR55: 40 | AS55: SI | AT55: 0 | AU55: 78 | AV55: 6 | AW55: 0 | AX55: NO | AY55: 0 | AZ55: 0 | BA55: 0 | BB55: 0 | BC55: 0 | BH55: 1.02 | BI55: 0 | BJ55: 0 | BL55: 0 | BM55: 0 | BN55: 0
A56: 461 | B56: MATE LISTO TARAGUI X 35 GR | C56: 12 | D56: 0 | E56: 0 | F56: NO | G56: SI | H56: NO | I56: NO | J56: NO | K56: NO | L56: NO | M56: 37377 | P56: 7790387120363 | Q56: 0 | R56: 0 | U56: 0 | W56: 0 | X56: 0 | Y56: 0 | Z56: NO | AA56: NO | AB56: NO | AC56: 0 | AD56: 0 | AE56: 0 | AF56: 0 | AG56: NO | AI56: 116 | AJ56: EST. LAS MARIAS S.A.C.I.F.A. | AK56: 20 | AQ56: 10 | AR56: 40 | AS56: SI | AT56: 0 | AU56: 78 | AV56: 6 | AW56: 0 | AX56: NO | AY56: 0 | AZ56: 0 | BA56: 0 | BB56: 0 | BC56: 0 | BH56: 1.02 | BI56: 0 | BJ56: 0 | BL56: 0 | BM56: 0 | BN56: 0
A57: 462 | B57: BOTELLA TERMICA MATE LISTO | C57: 6 | D57: 0 | E57: 0 | F57: NO | G57: SI | H57: NO | I57: NO | J57: NO | K57: NO | L57: NO | M57: 37377 | P57: 7790387120370 | Q57: 0 | R57: 0 | U57: 0 | W57: 0 | X57: 0 | Y57: 0 | Z57: NO | AA57: NO | AB57: NO | AC57: 0 | AD57: 0 | AE57: 0 | AF57: 0 | AG57: NO | AI57: 116 | AJ57: EST. LAS MARIAS S.A.C.I.F.A. | AK57: 14 | AQ57: 10 | AR57: 40 | AS57: SI | AT57: 0 | AU57: 88 | AV57: 4 | AW57: 0 | AX57: NO | AY57: 0 | AZ57: 0 | BA57: 0 | BB57: 0 | BC57: 0 | BH57: 1.02 | BI57: 0 | BJ57: 0 | BL57: 0 | BM57: 0 | BN57: 0
A58: 484 | B58: TARAGUI SILVESTRE TILO 25 SAQ X 1GR | C58: 6 | D58: 0 | E58: 0 | F58: NO | G58: SI | H58: NO | I58: NO | J58: NO | K58: NO | L58: NO | M58: 37377 | P58: 7790387711844 | Q58: 0 | R58: 0 | U58: 0 | W58: 0 | X58: 0 | Y58: 0 | Z58: NO | AA58: NO | AB58: NO | AC58: 0 | AD58: 0 | AE58: 0 | AF58: 0 | AG58: NO | AI58: 116 | AJ58: EST. LAS MARIAS S.A.C.I.F.A. | AQ58: 10 | AR58: 40 | AS58: SI | AT58: 0 | AU58: 0 | AV58: 0 | AW58: 0 | AX58: NO | AY58: 0 | AZ58: 0 | BA58: 0 | BB58: 0 | BC58: 0 | BH58: 1.02 | BI58: 0 | BJ58: 0 | BL58: 0 | BM58: 0 | BN58: 0
A59: 488 | B59: TARAGUI SILVESTRE TILO SAQ 10 X 1GR | C59: 6 | D59: 0 | E59: 0 | F59: NO | G59: SI | H59: NO | I59: NO | J59: NO | K59: NO | L59: NO | M59: 37377 | Q59: 0 | R59: 0 | U59: 0 | W59: 0 | X59: 0 | Y59: 0 | Z59: NO | AA59: NO | AB59: NO | AC59: 0 | AD59: 0 | AE59: 0 | AF59: 0 | AG59: NO | AI59: 116 | AJ59: EST. LAS MARIAS S.A.C.I.F.A. | AQ59: 10 | AR59: 40 | AS59: NO | AT59: 0 | AU59: 0 | AV59: 0 | AW59: 0 | AX59: NO | AY59: 0 | AZ59: 0 | BA59: 0 | BB59: 0 | BC59: 0 | BH59: 1.2 | BI59: 0 | BJ59: 0 | BL59: 0 | BM59: 0 | BN59: 0
A60: 500 | B60: BOMBONERA LOVERS X 264 GR | C60: 12 | D60: 0 | E60: 0 | F60: NO | G60: SI | H60: NO | I60: NO | J60: NO | K60: NO | L60: NO | M60: 37377 | P60: 770206002658 | Q60: 0 | R60: 0 | U60: 0 | W60: 0 | X60: 0 | Y60: 0 | Z60: NO | AA60: NO | AB60: NO | AC60: 0 | AD60: 0 | AE60: 0 | AF60: 0 | AG60: NO | AI60: 49 | AJ60: LA DELICIA FELIPE FORT S.A. | AQ60: 10 | AR60: 40 | AS60: SI | AT60: 0 | AU60: 0 | AV60: 0 | AW60: 0 | AX60: NO | AY60: 0 | AZ60: 0 | BA60: 0 | BB60: 0 | BC60: 0 | BH60: 6 | BI60: 0 | BJ60: 0 | BL60: 0 | BM60: 0 | BN60: 0
A61: 506 | B61: TARAGUI SILVESTRE ENSUEÑOS 25 SAQ X 1GR | C61: 6 | D61: 0 | E61: 0 | F61: NO | G61: SI | H61: NO | I61: NO | J61: NO | K61: NO | L61: NO | M61: 37377 | P61: 7790387712445 | Q61: 0 | R61: 0 | U61: 0 | W61: 0 | X61: 0 | Y61: 0 | Z61: NO | AA61: NO | AB61: NO | AC61: 0 | AD61: 0 | AE61: 0 | AF61: 0 | AG61: NO | AI61: 116 | AJ61: EST. LAS MARIAS S.A.C.I.F.A. | AQ61: 10 | AR61: 40 | AS61: SI | AT61: 0 | AU61: 0 | AV61: 0 | AW61: 0 | AX61: NO | AY61: 0 | AZ61: 0 | BA61: 0 | BB61: 0 | BC61: 0 | BH61: 10 | BI61: 0 | BJ61: 0 | BL61: 0 | BM61: 0 | BN61: 0
A62: 534 | B62: EXHIBIDOR DE PIE ENERGIZER | C62: 1 | D62: 0 | E62: 0 | F62: NO | G62: NO | H62: NO | I62: NO | J62: NO | K62: NO | L62: NO | M62: 37377 | N62: POP | Q62: 0 | R62: 0 | U62: 0 | W62: 0 | X62: 0 | Y62: 0 | Z62: NO | AA62: NO | AB62: NO | AC62: 0 | AD62: 0 | AE62: 0 | AF62: 0 | AG62: SI | AI62: 27 | AJ62: ENERGIZER ARGENTINA S.A. | AQ62: 10 | AR62: 40 | AS62: SI | AT62: 0 | AU62: 0 | AV62: 0 | AW62: 0 | AX62: NO | AY62: 0 | AZ62: 0 | BA62: 0 | BB62: 0 | BC62: 0 | BH62: 10 | BI62: 0 | BJ62: 0 | BL62: 0 | BM62: 0 | BN62: 0
A63: 535 | B63: CHOC. CADBURY YOGHURT FTLLA X82 GR | C63: 28 | D63: 0 | E63: 0 | F63: NO | G63: SI | H63: NO | I63: NO | J63: NO | K63: NO | L63: NO | M63: 37377 | P63: 7622201818715 | Q63: 0 | R63: 0 | U63: 0 | W63: 0 | X63: 0 | Y63: 0 | Z63: NO | AA63: NO | AB63: NO | AC63: 0 | AD63: 0 | AE63: 0 | AF63: 0 | AG63: NO | AI63: 210 | AJ63: MONDELEZ ARGENTINA S.A. | AQ63: 10 | AR63: 40 | AS63: SI | AT63: 0 | AU63: 0 | AV63: 0 | AW63: 0 | AX63: NO | AY63: 0 | AZ63: 0 | BA63: 0 | BB63: 0 | BC63: 0 | BH63: 0 | BI63: 0 | BJ63: 0 | BL63: 0 | BM63: 0 | BN63: 0
A64: 536 | B64: PILA L 92 AAA X 2U LITIO FOTO ENERGIZER | C64: 24 | D64: 0 | E64: 0 | F64: NO | G64: SI | H64: NO | I64: NO | J64: NO | K64: NO | L64: NO | M64: 37377 | P64: 39800079305 | Q64: 0 | R64: 0 | U64: 0 | W64: 0 | X64: 0 | Y64: 0 | Z64: NO | AA64: NO | AB64: NO | AC64: 0 | AD64: 0 | AE64: 0 | AF64: 0 | AG64: SI | AI64: 27 | AJ64: ENERGIZER ARGENTINA S.A. | AQ64: 10 | AR64: 40 | AS64: SI | AT64: 0 | AU64: 0 | AV64: 0 | AW64: 0 | AX64: NO | AY64: 0 | AZ64: 0 | BA64: 0 | BB64: 0 | BC64: 0 | BH64: 10 | BI64: 0 | BJ64: 0 | BL64: 0 | BM64: 0 | BN64: 0
A65: 542 | B65: PILA ECR-2032 X 5U ESP CALCULADORA | C65: 20 | D65: 0 | E65: 0 | F65: NO | G65: SI | H65: NO | I65: NO | J65: NO | K65: NO | L65: NO | M65: 37377 | P65: 8888021300185 | Q65: 0 | R65: 0 | U65: 0 | W65: 0 | X65: 0 | Y65: 0 | Z65: NO | AA65: NO | AB65: NO | AC65: 0 | AD65: 0 | AE65: 0 | AF65: 0 | AG65: SI | AI65: 27 | AJ65: ENERGIZER ARGENTINA S.A. | AQ65: 10 | AR65: 40 | AS65: SI | AT65: 0 | AU65: 0 | AV65: 0 | AW65: 0 | AX65: NO | AY65: 0 | AZ65: 0 | BA65: 0 | BB65: 0 | BC65: 0 | BH65: 10 | BI65: 0 | BJ65: 0 | BL65: 0 | BM65: 0 | BN65: 0
A66: 543 | B66: EXHIBIDOR TIC TAC ARBOLITOS | C66: 25 | D66: 0 | E66: 0 | F66: NO | G66: SI | H66: NO | I66: NO | J66: NO | K66: NO | L66: NO | M66: 37377 | N66: POP | Q66: 0 | R66: 0 | U66: 0 | W66: 0 | X66: 0 | Y66: 0 | Z66: NO | AA66: NO | AB66: NO | AC66: 0 | AD66: 0 | AE66: 0 | AF66: 0 | AG66: NO | AI66: 47 | AJ66: FERRERO ARGENTINA S.A. | AQ66: 10 | AR66: 40 | AS66: SI | AT66: 0 | AU66: 0 | AV66: 0 | AW66: 0 | AX66: NO | AY66: 0 | AZ66: 0 | BA66: 0 | BB66: 0 | BC66: 0 | BH66: 10 | BI66: 0 | BJ66: 0 | BL66: 0 | BM66: 0 | BN66: 0
A67: 549 | B67: CARAM MASTICABLE DONGA X 218 U | C67: 10 | D67: 0 | E67: 0 | F67: NO | G67: SI | H67: NO | I67: NO | J67: NO | K67: NO | L67: NO | M67: 37377 | P67: 7792860005358 | Q67: 0 | R67: 0 | U67: 0 | W67: 0 | X67: 0 | Y67: 0 | Z67: NO | AA67: NO | AB67: NO | AC67: 0 | AD67: 0 | AE67: 0 | AF67: 0 | AG67: NO | AI67: 46 | AJ67: LHERITIER ARGENTINA S.A. | AQ67: 10 | AR67: 40 | AS67: SI | AT67: 0 | AU67: 60 | AV67: 6 | AW67: 0 | AX67: NO | AY67: 0 | AZ67: 0 | BA67: 0 | BB67: 0 | BC67: 0 | BH67: 10 | BI67: 0 | BJ67: 0 | BL67: 0 | BM67: 0 | BN67: 0
A68: 559 | B68: UNI-POX X 25 ML. CHICO | C68: 120 | D68: 0 | E68: 0 | F68: NO | G68: SI | H68: NO | I68: NO | J68: NO | K68: NO | L68: NO | M68: 37377 | P68: 7790400018585 | Q68: 0 | R68: 0 | U68: 0 | W68: 0 | X68: 3 | Y68: 3 | Z68: NO | AA68: NO | AB68: NO | AC68: 0 | AD68: 0 | AE68: 0 | AF68: 0 | AG68: SI | AI68: 26 | AJ68: JORGE LUIS SUAREZ | AQ68: 10 | AR68: 40 | AS68: SI | AT68: 0 | AU68: 0 | AV68: 0 | AW68: 0 | AX68: NO | AY68: 0 | AZ68: 0 | BA68: 0 | BB68: 0 | BC68: 0 | BH68: 18 | BI68: 0 | BJ68: 0 | BL68: 0 | BM68: 0 | BN68: 0
A69: 560 | B69: UNI-POX X 100 ML. GRANDE | C69: 48 | D69: 0 | E69: 0 | F69: NO | G69: SI | H69: NO | I69: NO | J69: NO | K69: NO | L69: NO | M69: 37377 | P69: 7790400018608 | Q69: 0 | R69: 0 | U69: 0 | W69: 0 | X69: 0 | Y69: 0 | Z69: NO | AA69: NO | AB69: NO | AC69: 0 | AD69: 0 | AE69: 0 | AF69: 0 | AG69: SI | AI69: 26 | AJ69: JORGE LUIS SUAREZ | AQ69: 10 | AR69: 40 | AS69: SI | AT69: 0 | AU69: 0 | AV69: 0 | AW69: 0 | AX69: NO | AY69: 0 | AZ69: 0 | BA69: 0 | BB69: 0 | BC69: 0 | BH69: 10 | BI69: 0 | BJ69: 0 | BL69: 0 | BM69: 0 | BN69: 0
A70: 565 | B70: BUBBALOO 60'S TUTTI FRUTTI | C70: 32 | D70: 0 | E70: 0 | F70: NO | G70: SI | H70: NO | I70: NO | J70: NO | K70: NO | L70: NO | M70: 37377 | P70: 7622210964458 | Q70: 0 | R70: 0 | U70: 0 | W70: 0 | X70: 0 | Y70: 0 | Z70: NO | AA70: NO | AB70: NO | AC70: 0 | AD70: 0 | AE70: 0 | AF70: 0 | AG70: NO | AI70: 210 | AJ70: MONDELEZ ARGENTINA S.A. | AQ70: 10 | AR70: 40 | AS70: SI | AT70: 0 | AU70: 56 | AV70: 7 | AW70: 0 | AX70: NO | AY70: 0 | AZ70: 0 | BA70: 0 | BB70: 0 | BC70: 0 | BH70: 1.02 | BI70: 0 | BJ70: 0 | BL70: 0 | BM70: 0 | BN70: 0
A71: 566 | B71: BUBBALOO 60'S FRUTILLA | C71: 32 | D71: 0 | E71: 0 | F71: NO | G71: SI | H71: NO | I71: NO | J71: NO | K71: NO | L71: NO | M71: 37377 | P71: 7622210965035 | Q71: 0 | R71: 0 | U71: 0 | W71: 0 | X71: 0 | Y71: 0 | Z71: NO | AA71: NO | AB71: NO | AC71: 0 | AD71: 0 | AE71: 0 | AF71: 0 | AG71: NO | AI71: 210 | AJ71: MONDELEZ ARGENTINA S.A. | AQ71: 10 | AR71: 40 | AS71: SI | AT71: 0 | AU71: 56 | AV71: 7 | AW71: 0 | AX71: NO | AY71: 0 | AZ71: 0 | BA71: 0 | BB71: 0 | BC71: 0 | BH71: 10 | BI71: 0 | BJ71: 0 | BL71: 0 | BM71: 0 | BN71: 0
A72: 567 | B72: BUBBALOO 60'S MENTA | C72: 32 | D72: 0 | E72: 0 | F72: NO | G72: SI | H72: NO | I72: NO | J72: NO | K72: NO | L72: NO | M72: 37377 | P72: 7622210964397 | Q72: 0 | R72: 0 | U72: 0 | W72: 0 | X72: 0 | Y72: 0 | Z72: NO | AA72: NO | AB72: NO | AC72: 0 | AD72: 0 | AE72: 0 | AF72: 0 | AG72: NO | AI72: 210 | AJ72: MONDELEZ ARGENTINA S.A. | AQ72: 10 | AR72: 40 | AS72: SI | AT72: 0 | AU72: 56 | AV72: 7 | AW72: 0 | AX72: NO | AY72: 0 | AZ72: 0 | BA72: 0 | BB72: 0 | BC72: 0 | BH72: 18 | BI72: 0 | BJ72: 0 | BL72: 0 | BM72: 0 | BN72: 0
A73: 568 | B73: BUBBALOO 60'S UVA | C73: 32 | D73: 0 | E73: 0 | F73: NO | G73: SI | H73: NO | I73: NO | J73: NO | K73: NO | L73: NO | M73: 37377 | P73: 7622210965134 | Q73: 0 | R73: 0 | U73: 0 | W73: 0 | X73: 0 | Y73: 0 | Z73: NO | AA73: NO | AB73: NO | AC73: 0 | AD73: 0 | AE73: 0 | AF73: 0 | AG73: NO | AI73: 210 | AJ73: MONDELEZ ARGENTINA S.A. | AQ73: 10 | AR73: 40 | AS73: SI | AT73: 0 | AU73: 56 | AV73: 7 | AW73: 0 | AX73: NO | AY73: 0 | AZ73: 0 | BA73: 0 | BB73: 0 | BC73: 0 | BH73: 10 | BI73: 0 | BJ73: 0 | BL73: 0 | BM73: 0 | BN73: 0
A74: 571 | B74: BUBBALOO 60'S BANANA | C74: 32 | D74: 0 | E74: 0 | F74: NO | G74: SI | H74: NO | I74: NO | J74: NO | K74: NO | L74: NO | M74: 37377 | Q74: 0 | R74: 0 | U74: 0 | W74: 0 | X74: 0 | Y74: 0 | Z74: NO | AA74: NO | AB74: NO | AC74: 0 | AD74: 0 | AE74: 0 | AF74: 0 | AG74: NO | AI74: 210 | AJ74: MONDELEZ ARGENTINA S.A. | AQ74: 10 | AR74: 40 | AS74: SI | AT74: 0 | AU74: 0 | AV74: 0 | AW74: 0 | AX74: NO | AY74: 0 | AZ74: 0 | BA74: 0 | BB74: 0 | BC74: 0 | BH74: 1.02 | BI74: 0 | BJ74: 0 | BL74: 0 | BM74: 0 | BN74: 0
A75: 581 | B75: HALLS VITA-C NARANJA X 12 U. | C75: 24 | D75: 0 | E75: 0 | F75: NO | G75: SI | H75: NO | I75: NO | J75: NO | K75: NO | L75: NO | M75: 37377 | O75: 7791249020029 | P75: 77917324 | Q75: 0 | R75: 0 | U75: 0 | W75: 0 | X75: 0 | Y75: 0 | Z75: NO | AA75: NO | AB75: NO | AC75: 0 | AD75: 0 | AE75: 0 | AF75: 0 | AG75: NO | AI75: 210 | AJ75: MONDELEZ ARGENTINA S.A. | AQ75: 10 | AR75: 40 | AS75: SI | AT75: 0 | AU75: 0 | AV75: 0 | AW75: 0 | AX75: NO | AY75: 0 | AZ75: 0 | BA75: 0 | BB75: 0 | BC75: 0 | BH75: 8 | BI75: 0 | BJ75: 0 | BL75: 0 | BM75: 0 | BN75: 0
A76: 587 | B76: HALLS MENTA-LYPTUS X 12 U. | C76: 24 | D76: 0 | E76: 0 | F76: NO | G76: SI | H76: NO | I76: NO | J76: NO | K76: NO | L76: NO | M76: 37377 | O76: 7791249450277 | P76: 77933928 | Q76: 0 | R76: 0 | U76: 0 | W76: 0 | X76: 0 | Y76: 0 | Z76: NO | AA76: NO | AB76: NO | AC76: 0 | AD76: 0 | AE76: 0 | AF76: 0 | AG76: NO | AI76: 210 | AJ76: MONDELEZ ARGENTINA S.A. | AQ76: 10 | AR76: 40 | AS76: SI | AT76: 0 | AU76: 0 | AV76: 0 | AW76: 0 | AX76: NO | AY76: 0 | AZ76: 0 | BA76: 0 | BB76: 0 | BC76: 0 | BH76: 8 | BI76: 0 | BJ76: 0 | BL76: 0 | BM76: 0 | BN76: 0
A77: 637 | B77: EXHIBIDOR PEGAMENTOS CONSIGNACION | C77: 1 | D77: 0 | E77: 0 | F77: NO | G77: NO | H77: NO | I77: NO | J77: NO | K77: NO | L77: NO | M77: 37377 | N77: POP | Q77: 0 | R77: 0 | U77: 0 | W77: 0 | X77: 0 | Y77: 0 | Z77: NO | AA77: NO | AB77: NO | AC77: 0 | AD77: 0 | AE77: 0 | AF77: 0 | AG77: SI | AI77: 26 | AJ77: JORGE LUIS SUAREZ | AQ77: 10 | AR77: 40 | AS77: SI | AT77: 0 | AU77: 0 | AV77: 0 | AW77: 0 | AX77: NO | AY77: 0 | AZ77: 0 | BA77: 0 | BB77: 0 | BC77: 0 | BH77: 8 | BI77: 0 | BJ77: 0 | BL77: 0 | BM77: 0 | BN77: 0
A78: 639 | B78: BATERIA A23 -12V X 5U -ENERGIZER ALCALINA | C78: 20 | D78: 0 | E78: 0 | F78: NO | G78: SI | H78: NO | I78: NO | J78: NO | K78: NO | L78: NO | M78: 37377 | P78: 8888021300376 | Q78: 0 | R78: 0 | U78: 0 | W78: 0 | X78: 0 | Y78: 0 | Z78: NO | AA78: NO | AB78: NO | AC78: 0 | AD78: 0 | AE78: 0 | AF78: 0 | AG78: SI | AI78: 27 | AJ78: ENERGIZER ARGENTINA S.A. | AQ78: 10 | AR78: 40 | AS78: SI | AT78: 0 | AU78: 0 | AV78: 0 | AW78: 0 | AX78: NO | AY78: 0 | AZ78: 0 | BA78: 0 | BB78: 0 | BC78: 0 | BH78: 8 | BI78: 0 | BJ78: 0 | BL78: 0 | BM78: 0 | BN78: 0
A79: 653 | B79: CARAM MAST SURT MISKY X800 GR | C79: 10 | D79: 0 | E79: 0 | F79: NO | G79: SI | H79: NO | I79: NO | J79: NO | K79: NO | L79: NO | M79: 37377 | P79: 7790580178109 | Q79: 0 | R79: 0 | U79: 0 | W79: 0 | X79: 0 | Y79: 0 | Z79: NO | AA79: NO | AB79: NO | AC79: 0 | AD79: 0 | AE79: 0 | AF79: 0 | AG79: NO | AI79: 215 | AJ79: ARCOR S.A.I.C. | AQ79: 10 | AR79: 40 | AS79: SI | AT79: 0 | AU79: 96 | AV79: 0 | AW79: 0 | AX79: NO | AY79: 0 | AZ79: 0 | BA79: 0 | BB79: 0 | BC79: 0 | BH79: 8 | BI79: 0 | BJ79: 0 | BL79: 0 | BM79: 0 | BN79: 0
A80: 676 | B80: DIABFORT CHOCOLATE DIET X 50 GR | C80: 20 | D80: 0 | E80: 0 | F80: NO | G80: SI | H80: NO | I80: NO | J80: NO | K80: NO | L80: NO | M80: 37377 | Q80: 0 | R80: 0 | U80: 0 | W80: 0 | X80: 0 | Y80: 0 | Z80: NO | AA80: NO | AB80: NO | AC80: 0 | AD80: 0 | AE80: 0 | AF80: 0 | AG80: NO | AI80: 49 | AJ80: LA DELICIA FELIPE FORT S.A. | AQ80: 10 | AR80: 40 | AS80: SI | AT80: 0 | AU80: 0 | AV80: 0 | AW80: 0 | AX80: NO | AY80: 0 | AZ80: 0 | BA80: 0 | BB80: 0 | BC80: 0 | BH80: 12 | BI80: 0 | BJ80: 0 | BL80: 0 | BM80: 0 | BN80: 0
A81: 692 | B81: ACEITE LUBRICANTE WD-40 X 155 G | C81: 12 | D81: 0 | E81: 0 | F81: NO | G81: SI | H81: NO | I81: NO | J81: NO | K81: NO | L81: NO | M81: 37377 | P81: 7790400021806 | Q81: 0 | R81: 0 | U81: 0 | W81: 0 | X81: 0 | Y81: 0 | Z81: NO | AA81: NO | AB81: NO | AC81: 0 | AD81: 0 | AE81: 0 | AF81: 0 | AG81: SI | AI81: 26 | AJ81: JORGE LUIS SUAREZ | AQ81: 10 | AR81: 40 | AS81: SI | AT81: 0 | AU81: 0 | AV81: 0 | AW81: 0 | AX81: NO | AY81: 0 | AZ81: 0 | BA81: 0 | BB81: 0 | BC81: 0 | BH81: 15 | BI81: 0 | BJ81: 0 | BL81: 0 | BM81: 0 | BN81: 0
A82: 699 | B82: PILA 1215 AA X 60U EVEREADY EXTRA DURAC | C82: 15 | D82: 0 | E82: 0 | F82: NO | G82: SI | H82: NO | I82: NO | J82: NO | K82: NO | L82: NO | M82: 37377 | P82: 7501037601145 | Q82: 0 | R82: 0 | U82: 0 | W82: 0 | X82: 0 | Y82: 0 | Z82: NO | AA82: NO | AB82: NO | AC82: 0 | AD82: 0 | AE82: 0 | AF82: 0 | AG82: SI | AI82: 27 | AJ82: ENERGIZER ARGENTINA S.A. | AQ82: 10 | AR82: 40 | AS82: SI | AT82: 0 | AU82: 0 | AV82: 0 | AW82: 0 | AX82: NO | AY82: 0 | AZ82: 0 | BA82: 0 | BB82: 0 | BC82: 0 | BH82: 15 | BI82: 0 | BJ82: 0 | BL82: 0 | BM82: 0 | BN82: 0
A83: 710 | B83: PILA ECR-2025 X 5U ESP CALCULADORA | C83: 20 | D83: 0 | E83: 0 | F83: NO | G83: SI | H83: NO | I83: NO | J83: NO | K83: NO | L83: NO | M83: 37377 | P83: 8888021300161 | Q83: 0 | R83: 0 | U83: 0 | W83: 0 | X83: 0 | Y83: 0 | Z83: NO | AA83: NO | AB83: NO | AC83: 0 | AD83: 0 | AE83: 0 | AF83: 0 | AG83: SI | AI83: 27 | AJ83: ENERGIZER ARGENTINA S.A. | AQ83: 10 | AR83: 40 | AS83: SI | AT83: 0 | AU83: 0 | AV83: 0 | AW83: 0 | AX83: NO | AY83: 0 | AZ83: 0 | BA83: 0 | BB83: 0 | BC83: 0 | BH83: 1.02 | BI83: 0 | BJ83: 0 | BL83: 0 | BM83: 0 | BN83: 0
A84: 711 | B84: PILA ECR-2016 X 5U ESP CALCULADORA | C84: 20 | D84: 0 | E84: 0 | F84: NO | G84: SI | H84: NO | I84: NO | J84: NO | K84: NO | L84: NO | M84: 37377 | O84: 8888021700213 | P84: 8888021300192 | Q84: 0 | R84: 0 | U84: 0 | W84: 0 | X84: 0 | Y84: 0 | Z84: NO | AA84: NO | AB84: NO | AC84: 0 | AD84: 0 | AE84: 0 | AF84: 0 | AG84: SI | AI84: 27 | AJ84: ENERGIZER ARGENTINA S.A. | AQ84: 10 | AR84: 40 | AS84: SI | AT84: 0 | AU84: 0 | AV84: 0 | AW84: 0 | AX84: NO | AY84: 0 | AZ84: 0 | BA84: 0 | BB84: 0 | BC84: 0 | BH84: 1.02 | BI84: 0 | BJ84: 0 | BL84: 0 | BM84: 0 | BN84: 0
A85: 712 | B85: PILA A 76 X 10U ESPECIAL BLISTER | C85: 20 | D85: 0 | E85: 0 | F85: NO | G85: SI | H85: NO | I85: NO | J85: NO | K85: NO | L85: NO | M85: 37377 | P85: 8888021300178 | Q85: 0 | R85: 0 | U85: 0 | W85: 0 | X85: 0 | Y85: 0 | Z85: NO | AA85: NO | AB85: NO | AC85: 0 | AD85: 0 | AE85: 0 | AF85: 0 | AG85: SI | AI85: 27 | AJ85: ENERGIZER ARGENTINA S.A. | AQ85: 10 | AR85: 40 | AS85: SI | AT85: 0 | AU85: 0 | AV85: 0 | AW85: 0 | AX85: NO | AY85: 0 | AZ85: 0 | BA85: 0 | BB85: 0 | BC85: 0 | BH85: 4 | BI85: 0 | BJ85: 0 | BL85: 0 | BM85: 0 | BN85: 0
A86: 726 | B86: BICICLETA CONCURSO RAP | C86: 1 | D86: 0 | E86: 0 | F86: NO | G86: SI | H86: NO | I86: NO | J86: NO | K86: NO | L86: NO | M86: 37377 | N86: JUGUETES | Q86: 0 | R86: 0 | U86: 0 | W86: 0 | X86: 0 | Y86: 0 | Z86: NO | AA86: NO | AB86: NO | AC86: 0 | AD86: 0 | AE86: 0 | AF86: 0 | AG86: NO | AI86: 213 | AJ86: FEDESUR S.A | AQ86: 10 | AR86: 40 | AS86: SI | AT86: 0 | AU86: 0 | AV86: 0 | AW86: 0 | AX86: NO | AY86: 0 | AZ86: 0 | BA86: 0 | BB86: 0 | BC86: 0 | BH86: 4 | BI86: 0 | BJ86: 0 | BL86: 0 | BM86: 0 | BN86: 0
A87: 731 | B87: POLVORITAS VAINILLA X 81 GR | C87: 40 | D87: 0 | E87: 0 | F87: NO | G87: SI | H87: NO | I87: NO | J87: NO | K87: NO | L87: NO | M87: 37377 | P87: 7790040139169 | Q87: 0 | R87: 0 | U87: 0 | W87: 0 | X87: 0 | Y87: 0 | Z87: NO | AA87: NO | AB87: NO | AC87: 0 | AD87: 0 | AE87: 0 | AF87: 0 | AG87: NO | AI87: 215 | AJ87: ARCOR S.A.I.C. | AQ87: 10 | AR87: 40 | AS87: SI | AT87: 0 | AU87: 208 | AV87: 0 | AW87: 0 | AX87: NO | AY87: 0 | AZ87: 0 | BA87: 0 | BB87: 0 | BC87: 0 | BH87: 324 | BI87: 0 | BJ87: 0 | BL87: 0 | BM87: 0 | BN87: 0
A88: 737 | B88: LINT ENGZ LUZ DE LECTURA -BOOK LIGHTN2 | C88: 4 | D88: 0 | E88: 0 | F88: NO | G88: SI | H88: NO | I88: NO | J88: NO | K88: NO | L88: NO | M88: 37377 | P88: 4891138929853 | Q88: 0 | R88: 0 | U88: 0 | W88: 0 | X88: 0 | Y88: 0 | Z88: NO | AA88: NO | AB88: NO | AC88: 0 | AD88: 0 | AE88: 0 | AF88: 0 | AG88: SI | AI88: 27 | AJ88: ENERGIZER ARGENTINA S.A. | AQ88: 10 | AR88: 40 | AS88: SI | AT88: 0 | AU88: 0 | AV88: 0 | AW88: 0 | AX88: NO | AY88: 0 | AZ88: 0 | BA88: 0 | BB88: 0 | BC88: 0 | BH88: 10 | BI88: 0 | BJ88: 0 | BL88: 0 | BM88: 0 | BN88: 0
A89: 742 | B89: PRESERV PRIME CON ESPERMICIDA X 3U | C89: 24 | D89: 0 | E89: 0 | F89: NO | G89: SI | H89: NO | I89: NO | J89: NO | K89: NO | L89: NO | M89: 37377 | P89: 7791519200076 | Q89: 0 | R89: 0 | U89: 0 | W89: 0 | X89: 0 | Y89: 0 | Z89: NO | AA89: NO | AB89: NO | AC89: 0 | AD89: 0 | AE89: 0 | AF89: 0 | AG89: NO | AI89: 37 | AJ89: BUHL S.A. | AQ89: 10 | AR89: 40 | AS89: SI | AT89: 0 | AU89: 0 | AV89: 0 | AW89: 0 | AX89: NO | AY89: 0 | AZ89: 0 | BA89: 0 | BB89: 0 | BC89: 0 | BH89: 4 | BI89: 0 | BJ89: 0 | BL89: 0 | BM89: 0 | BN89: 0
A90: 743 | B90: PRESERV PRIME EXTRALUBRICADO X 3U. | C90: 24 | D90: 0 | E90: 0 | F90: NO | G90: SI | H90: NO | I90: NO | J90: NO | K90: NO | L90: NO | M90: 37377 | P90: 7791519000676 | Q90: 0 | R90: 0 | U90: 0 | W90: 0 | X90: 0 | Y90: 0 | Z90: NO | AA90: NO | AB90: NO | AC90: 0 | AD90: 0 | AE90: 0 | AF90: 0 | AG90: NO | AI90: 37 | AJ90: BUHL S.A. | AQ90: 10 | AR90: 40 | AS90: SI | AT90: 0 | AU90: 0 | AV90: 0 | AW90: 0 | AX90: NO | AY90: 0 | AZ90: 0 | BA90: 0 | BB90: 0 | BC90: 0 | BH90: 12 | BI90: 0 | BJ90: 0 | BL90: 0 | BM90: 0 | BN90: 0
A91: 744 | B91: PRESERV PRIME SUPER FINOS X 3U. | C91: 24 | D91: 0 | E91: 0 | F91: NO | G91: SI | H91: NO | I91: NO | J91: NO | K91: NO | L91: NO | M91: 37377 | P91: 7791519200045 | Q91: 0 | R91: 0 | U91: 0 | W91: 0 | X91: 0 | Y91: 0 | Z91: NO | AA91: NO | AB91: NO | AC91: 0 | AD91: 0 | AE91: 0 | AF91: 0 | AG91: NO | AI91: 37 | AJ91: BUHL S.A. | AQ91: 10 | AR91: 40 | AS91: SI | AT91: 0 | AU91: 0 | AV91: 0 | AW91: 0 | AX91: NO | AY91: 0 | AZ91: 0 | BA91: 0 | BB91: 0 | BC91: 0 | BH91: 1 | BI91: 0 | BJ91: 0 | BL91: 0 | BM91: 0 | BN91: 0
A92: 745 | B92: PRESERV PRIME ANATOMICOS X 3U. | C92: 24 | D92: 0 | E92: 0 | F92: NO | G92: SI | H92: NO | I92: NO | J92: NO | K92: NO | L92: NO | M92: 37377 | P92: 7791519200021 | Q92: 0 | R92: 0 | U92: 0 | W92: 0 | X92: 0 | Y92: 0 | Z92: NO | AA92: NO | AB92: NO | AC92: 0 | AD92: 0 | AE92: 0 | AF92: 0 | AG92: NO | AI92: 37 | AJ92: BUHL S.A. | AQ92: 10 | AR92: 40 | AS92: SI | AT92: 0 | AU92: 0 | AV92: 0 | AW92: 0 | AX92: NO | AY92: 0 | AZ92: 0 | BA92: 0 | BB92: 0 | BC92: 0 | BH92: 1 | BI92: 0 | BJ92: 0 | BL92: 0 | BM92: 0 | BN92: 0
A93: 746 | B93: PRESERV PRIME TEXTURADOS X 3U. | C93: 24 | D93: 0 | E93: 0 | F93: NO | G93: SI | H93: NO | I93: NO | J93: NO | K93: NO | L93: NO | M93: 37377 | P93: 7791519200069 | Q93: 0 | R93: 0 | U93: 0 | W93: 0 | X93: 0 | Y93: 0 | Z93: NO | AA93: NO | AB93: NO | AC93: 0 | AD93: 0 | AE93: 0 | AF93: 0 | AG93: NO | AI93: 37 | AJ93: BUHL S.A. | AQ93: 10 | AR93: 40 | AS93: SI | AT93: 0 | AU93: 0 | AV93: 0 | AW93: 0 | AX93: NO | AY93: 0 | AZ93: 0 | BA93: 0 | BB93: 0 | BC93: 0 | BH93: 1 | BI93: 0 | BJ93: 0 | BL93: 0 | BM93: 0 | BN93: 0
A94: 747 | B94: PRESERV PRIME CAJA MIXTA X 24 X 3U | C94: 20 | D94: 0 | E94: 0 | F94: NO | G94: SI | H94: NO | I94: NO | J94: NO | K94: NO | L94: NO | M94: 37377 | O94: 17791519000321 | Q94: 0 | R94: 0 | U94: 0 | W94: 0 | X94: 0 | Y94: 0 | Z94: NO | AA94: NO | AB94: NO | AC94: 0 | AD94: 0 | AE94: 0 | AF94: 0 | AG94: NO | AI94: 37 | AJ94: BUHL S.A. | AQ94: 10 | AR94: 40 | AS94: SI | AT94: 0 | AU94: 0 | AV94: 0 | AW94: 0 | AX94: NO | AY94: 0 | AZ94: 0 | BA94: 0 | BB94: 0 | BC94: 0 | BH94: 1 | BI94: 0 | BJ94: 0 | BL94: 0 | BM94: 0 | BN94: 0
A95: 752 | B95: PRESERV PRIME MIXTA 12X3 | C95: 30 | D95: 0 | E95: 0 | F95: NO | G95: NO | H95: NO | I95: NO | J95: NO | K95: NO | L95: NO | M95: 37377 | P95: 7791519000314 | Q95: 0 | R95: 0 | U95: 0 | W95: 0 | X95: 0 | Y95: 0 | Z95: NO | AA95: NO | AB95: NO | AC95: 0 | AD95: 0 | AE95: 0 | AF95: 0 | AG95: NO | AI95: 37 | AJ95: BUHL S.A. | AQ95: 10 | AR95: 40 | AS95: SI | AT95: 0 | AU95: 0 | AV95: 0 | AW95: 0 | AX95: NO | AY95: 0 | AZ95: 0 | BA95: 0 | BB95: 0 | BC95: 0 | BH95: 1 | BI95: 0 | BJ95: 0 | BL95: 0 | BM95: 0 | BN95: 0
A96: 799 | B96: BATERIA ENERGIZER 12V X 1U -A27 | C96: 12 | D96: 0 | E96: 0 | F96: NO | G96: SI | H96: NO | I96: NO | J96: NO | K96: NO | L96: NO | M96: 37377 | P96: 8888021300369 | Q96: 0 | R96: 0 | U96: 0 | W96: 0 | X96: 0 | Y96: 0 | Z96: NO | AA96: NO | AB96: NO | AC96: 0 | AD96: 0 | AE96: 0 | AF96: 0 | AG96: SI | AI96: 27 | AJ96: ENERGIZER ARGENTINA S.A. | AQ96: 10 | AR96: 40 | AS96: SI | AT96: 0 | AU96: 0 | AV96: 0 | AW96: 0 | AX96: NO | AY96: 0 | AZ96: 0 | BA96: 0 | BB96: 0 | BC96: 0 | BH96: 11 | BI96: 0 | BJ96: 0 | BL96: 0 | BM96: 0 | BN96: 0
A97: 819 | B97: PILA 1215 AA X 4U EVEREADY EXTRA DURAC | C97: 48 | D97: 0 | E97: 0 | F97: NO | G97: SI | H97: NO | I97: NO | J97: NO | K97: NO | L97: NO | M97: 37377 | P97: 7501037600056 | Q97: 0 | R97: 0 | U97: 0 | W97: 0 | X97: 0 | Y97: 0 | Z97: NO | AA97: NO | AB97: NO | AC97: 0 | AD97: 0 | AE97: 0 | AF97: 0 | AG97: SI | AI97: 27 | AJ97: ENERGIZER ARGENTINA S.A. | AQ97: 10 | AR97: 40 | AS97: SI | AT97: 0 | AU97: 0 | AV97: 0 | AW97: 0 | AX97: NO | AY97: 0 | AZ97: 0 | BA97: 0 | BB97: 0 | BC97: 0 | BH97: 24 | BI97: 0 | BJ97: 0 | BL97: 0 | BM97: 0 | BN97: 0
A98: 821 | B98: PILA 1250 D X 2U EVEREADY EXTRA DURAC | C98: 24 | D98: 0 | E98: 0 | F98: NO | G98: SI | H98: NO | I98: NO | J98: NO | K98: NO | L98: NO | M98: 37377 | P98: 7501037600018 | Q98: 0 | R98: 0 | U98: 0 | W98: 0 | X98: 0 | Y98: 0 | Z98: NO | AA98: NO | AB98: NO | AC98: 0 | AD98: 0 | AE98: 0 | AF98: 0 | AG98: SI | AI98: 27 | AJ98: ENERGIZER ARGENTINA S.A. | AQ98: 10 | AR98: 40 | AS98: SI | AT98: 0 | AU98: 0 | AV98: 0 | AW98: 0 | AX98: NO | AY98: 0 | AZ98: 0 | BA98: 0 | BB98: 0 | BC98: 0 | BH98: 24 | BI98: 0 | BJ98: 0 | BL98: 0 | BM98: 0 | BN98: 0
A99: 822 | B99: PILA 1212 AAA X 2U EVEREADY EXTRA DURAC | C99: 72 | D99: 0 | E99: 0 | F99: NO | G99: SI | H99: NO | I99: NO | J99: NO | K99: NO | L99: NO | M99: 37377 | P99: 039800052636 | Q99: 0 | R99: 0 | U99: 0 | W99: 0 | X99: 0 | Y99: 0 | Z99: NO | AA99: NO | AB99: NO | AC99: 0 | AD99: 0 | AE99: 0 | AF99: 0 | AG99: SI | AI99: 27 | AJ99: ENERGIZER ARGENTINA S.A. | AQ99: 10 | AR99: 40 | AS99: SI | AT99: 0 | AU99: 0 | AV99: 0 | AW99: 0 | AX99: NO | AY99: 0 | AZ99: 0 | BA99: 0 | BB99: 0 | BC99: 0 | BH99: 11 | BI99: 0 | BJ99: 0 | BL99: 0 | BM99: 0 | BN99: 0
A100: 824 | B100: BATERIA EVEREADY EXTRA DURAC 9V -1222 | C100: 24 | D100: 0 | E100: 0 | F100: NO | G100: SI | H100: NO | I100: NO | J100: NO | K100: NO | L100: NO | M100: 37377 | P100: 039800011626 | Q100: 0 | R100: 0 | U100: 0 | W100: 0 | X100: 0 | Y100: 0 | Z100: NO | AA100: NO | AB100: NO | AC100: 0 | AD100: 0 | AE100: 0 | AF100: 0 | AG100: SI | AI100: 27 | AJ100: ENERGIZER ARGENTINA S.A. | AQ100: 10 | AR100: 40 | AS100: SI | AT100: 0 | AU100: 0 | AV100: 0 | AW100: 0 | AX100: NO | AY100: 0 | AZ100: 0 | BA100: 0 | BB100: 0 | BC100: 0 | BH100: 18 | BI100: 0 | BJ100: 0 | BL100: 0 | BM100: 0 | BN100: 0
...

Sheet Promedio Horas
A1: Cod | B1: Vendedor | D1: Promedio Mensual
A2: V2 | B2: =+AVANCE!B16 -> 2 - OJEDA NORBERTO | D2: 0.19616319
A3: V3 | B3: =+AVANCE!B17 -> 3 - VIDAL NAHUEL | D3: 0.29096065
A4: V18 | B4: =+AVANCE!B18 -> 18 - HERRERA PABLO | D4: 0.24764468
A5: V21 | B5: =+AVANCE!B19 -> 21 - CATAN MATIAS | D5: 0.26050347
A6: V23 | B6: =+AVANCE!B20 -> 23 - DELGADO JOSÉ | D6: 0.25247106
A7: V31 | B7: =+AVANCE!B21 -> 31 - RENZO RAMOS | D7: 0.25171875
A8: V44 | B8: =+AVANCE!B22 -> 44 - MONGES CESAR LUIS | D8: 0.24983796
A9: V54 | B9: =+AVANCE!B23 -> 54 - BARTSCHAT EMILIANO NAHUEL | D9: 0.24949653
A10: V56 | B10: =+AVANCE!B42 -> 56 - JUAN ANDRES SANCHEZ | D10: 0.091938657
A11: V4 | B11: =+AVANCE!B9 -> 4 - TUR SPRINGER FERNANDO | D11: 0.25181713
A12: V5 | B12: =+AVANCE!B8 -> 5 - SCHELOVER RAUL | D12: 0.29418403
A13: V8 | B13: =+AVANCE!B7 -> 8 - PARRA MAXIMILIANO | D13: 0.25631944
A14: V11 | B14: =+AVANCE!B6 -> 11 - SANCHEZ RICARDO | D14: 0.28696181
A15: V12 | B15: =+AVANCE!B5 -> 12 - GUTIERREZ MARCOS DAVID | D15: 0.22791088
A16: V16 | B16: =+AVANCE!B4 -> 16 - GOMEZ MATÍAS | D16: 0.25814815
A17: V19 | B17: =+AVANCE!B3 -> 19 - GONZALEZ MARCELO | D17: 0.25258681
A18: V20 | B18: =+AVANCE!B2 -> 20 - FLORES JAVIER | D18: 0.24541088
A19: V49 | B19: =+AVANCE!B41 -> 49 - ESCOBAR RAÚL | D19: 0.24541088
A20: V1 | B20: =+AVANCE!B37 -> 1 - VERA ERNESTO | D20: 0.28325231
A21: V9 | B21: =+AVANCE!B27 -> 9 - ESTIGARRIBIA DAVID | D21: 0.24265625
A22: V10 | B22: =+AVANCE!B30 -> 10 - BRITEZ EMMANUEL | D22: 0.2428588
A23: V24 | B23: =+AVANCE!B34 -> 24 - AZULA NICOLAS | D23: 0.25132523
A24: V27 | B24: =+AVANCE!B29 -> 27 - GOMEZ ADRIÁN | D24: 0.23364005
A25: V28 | B25: =+AVANCE!B31 -> 28 - GOMEZ PABLO | D25: 0.20928819
A26: V33 | B26: =+AVANCE!B32 -> 33 - ESQUIVEL NICOLAS | D26: 0.24005208
A27: V36 | B27: =+AVANCE!B26 -> 36 - IBARROLA JORGE | D27: 0.24850694
A28: V37 | B28: =+AVANCE!B33 -> 37 - SALAJ EMILIO | D28: 0.25096065
A29: V40 | B29: =+AVANCE!B28 -> 40 - SOLIS EMMANUEL | D29: 0.15519676
A30: V52 | B30: =+AVANCE!B13 -> 52 - RAVAROTTO EMANUEL | D30: 0.22253472
A31: V53 | B31: =+AVANCE!B14 -> 53 - SANDOVAL RODRIGO | D31: 0.17992477
A32: V15 | B32: =+AVANCE!B12 -> 15 - GALARZA GERARDO | D32: 0.20059606
A33: V22 | B33: =+AVANCE!B11 -> 22 - ALMIRON NICOLAS | D33: 0.23152199
A34: V7 | B34: =+AVANCE!B35 -> 7 - VALLEJOS EDUARDO | D34: 0.11230903
A35: V32 | B35: =+AVANCE!B25 -> 32 - CABRAL GONZALO | D35: 0.13935185
A36: V57 | B36: =+AVANCE!B36 -> 57 - FEDERRATH MARTIN | D36: 0.14675926

Sheet Base Cobertura
A1: COBERTURAMESENCURSO | F1: COBERTURAUNIDADDENEGOCIO
A2: Nro Vendedor | B2: CCC x Bultos | C2: Cartera Clientes | F2: Nro Vendedor | G2: Agrupacion | H2: CCC x Bultos | I2: Cartera Clientes
B3: 1 | C3: 3707 | G3: 135 - ALMACEN | H3: 1 | I3: 3707
A4: 1 | B4: 34 | C4: 115 | G4: 135 - Articulos Sin Asociar Agrupacion | H4: 1 | I4: 3707
A5: 10 | B5: 31 | C5: 165 | G5: 135 - BEBIDAS | H5: 1 | I5: 3707
A6: 100 | B6: 20 | C6: 2039 | G6: 135 - CHOCOLATE | I6: 3707
A7: 11 | B7: 42 | C7: 168 | G7: 135 - GALLETITAS | H7: 1 | I7: 3707
A8: 12 | B8: 46 | C8: 213 | G8: 135 - GOLOSINAS | I8: 3707
A9: 123 | B9: 20 | C9: 492 | G9: 135 - MASCOTAS | H9: 1 | I9: 3707
A10: 15 | B10: 8 | C10: 65 | G10: 135 - NO PERECEDEROS | I10: 3707
A11: 16 | B11: 36 | C11: 201 | G11: 135 - PILAS | I11: 3707
A12: 18 | B12: 52 | C12: 182 | E12: =+F12 -> 1 | F12: 1 | G12: 135 - ALMACEN | H12: 16 | I12: 115
A13: 19 | B13: 55 | C13: 209 | E13: =+$E$12 -> 1 | G13: 135 - Articulos Sin Asociar Agrupacion | H13: 9 | I13: 115
A14: 2 | B14: 29 | C14: 124 | E14: =+$E$12 -> 1 | G14: 135 - BEBIDAS | H14: 16 | I14: 115
A15: 20 | B15: 64 | C15: 230 | E15: =+$E$12 -> 1 | G15: 135 - CHOCOLATE | H15: 8 | I15: 115
A16: 21 | B16: 57 | C16: 166 | E16: =+$E$12 -> 1 | G16: 135 - GALLETITAS | H16: 24 | I16: 115
A17: 22 | B17: 19 | C17: 79 | E17: =+$E$12 -> 1 | G17: 135 - GOLOSINAS | H17: 19 | I17: 115
A18: 23 | B18: 59 | C18: 158 | E18: =+$E$12 -> 1 | G18: 135 - MASCOTAS | H18: 7 | I18: 115
A19: 24 | B19: 22 | C19: 173 | E19: =+$E$12 -> 1 | G19: 135 - NO PERECEDEROS | H19: 8 | I19: 115
A20: 25 | C20: 174 | E20: =+$E$12 -> 1 | G20: 135 - PILAS | H20: 4 | I20: 115
A21: 26 | B21: 40 | C21: 174 | E21: =+$F$21 -> 10 | F21: 10 | G21: 135 - ALMACEN | H21: 6 | I21: 165
A22: 27 | B22: 40 | C22: 131 | E22: =+$F$21 -> 10 | G22: 135 - Articulos Sin Asociar Agrupacion | H22: 6 | I22: 165
A23: 28 | B23: 46 | C23: 157 | E23: =+$F$21 -> 10 | G23: 135 - BEBIDAS | H23: 9 | I23: 165
A24: 3 | B24: 58 | C24: 173 | E24: =+$F$21 -> 10 | G24: 135 - CHOCOLATE | H24: 7 | I24: 165
A25: 30 | B25: 1 | C25: 123 | E25: =+$F$21 -> 10 | G25: 135 - GALLETITAS | H25: 13 | I25: 165
A26: 31 | B26: 40 | C26: 173 | E26: =+$F$21 -> 10 | G26: 135 - GOLOSINAS | H26: 9 | I26: 165
A27: 32 | B27: 6 | C27: 58 | E27: =+$F$21 -> 10 | G27: 135 - MASCOTAS | H27: 8 | I27: 165
A28: 33 | B28: 26 | C28: 171 | E28: =+$F$21 -> 10 | G28: 135 - NO PERECEDEROS | H28: 1 | I28: 165
A29: 36 | B29: 26 | C29: 161 | E29: =+$F$21 -> 10 | G29: 135 - PILAS | H29: 2 | I29: 165
A30: 37 | B30: 22 | C30: 148 | E30: =+$F$30 -> 100 | F30: 100 | G30: 135 - ALMACEN | H30: 7 | I30: 2039
A31: 4 | B31: 42 | C31: 183 | E31: =+$F$30 -> 100 | G31: 135 - Articulos Sin Asociar Agrupacion | H31: 2 | I31: 2039
A32: 40 | B32: 24 | C32: 227 | E32: =+$F$30 -> 100 | G32: 135 - BEBIDAS | H32: 4 | I32: 2039
A33: 42 | C33: 52 | E33: =+$F$30 -> 100 | G33: 135 - CHOCOLATE | H33: 2 | I33: 2039
A34: 43 | C34: 93 | E34: =+$F$30 -> 100 | G34: 135 - GALLETITAS | H34: 16 | I34: 2039
A35: 44 | B35: 37 | C35: 174 | E35: =+$F$30 -> 100 | G35: 135 - GOLOSINAS | H35: 3 | I35: 2039
A36: 49 | C36: 247 | E36: =+$F$30 -> 100 | G36: 135 - MASCOTAS | H36: 5 | I36: 2039
A37: 5 | B37: 80 | C37: 266 | E37: =+$F$30 -> 100 | G37: 135 - NO PERECEDEROS | H37: 1 | I37: 2039
A38: 52 | B38: 12 | C38: 107 | E38: =+$F$30 -> 100 | G38: 135 - PILAS | H38: 1 | I38: 2039
A39: 53 | B39: 11 | C39: 105 | E39: =+$F$39 -> 11 | F39: 11 | G39: 135 - ALMACEN | H39: 11 | I39: 168
A40: 54 | B40: 44 | C40: 205 | E40: =+$F$39 -> 11 | G40: 135 - Articulos Sin Asociar Agrupacion | H40: 3 | I40: 168
A41: 56 | B41: 32 | C41: 202 | E41: =+$F$39 -> 11 | G41: 135 - BEBIDAS | H41: 20 | I41: 168
A42: 57 | B42: 13 | C42: 107 | E42: =+$F$39 -> 11 | G42: 135 - CHOCOLATE | H42: 12 | I42: 168
A43: 58 | C43: 83 | E43: =+$F$39 -> 11 | G43: 135 - GALLETITAS | H43: 19 | I43: 168
A44: 59 | C44: 128 | E44: =+$F$39 -> 11 | G44: 135 - GOLOSINAS | H44: 12 | I44: 168
A45: 60 | B45: 13 | C45: 89 | E45: =+$F$39 -> 11 | G45: 135 - MASCOTAS | H45: 1 | I45: 168
A46: 7 | B46: 1 | C46: 116 | E46: =+$F$39 -> 11 | G46: 135 - NO PERECEDEROS | H46: 5 | I46: 168
A47: 8 | B47: 44 | C47: 203 | E47: =+$F$39 -> 11 | G47: 135 - PILAS | I47: 168
A48: 9 | B48: 38 | C48: 149 | E48: =+$F$48 -> 12 | F48: 12 | G48: 135 - ALMACEN | H48: 12 | I48: 213
E49: =+$F$48 -> 12 | G49: 135 - Articulos Sin Asociar Agrupacion | H49: 1 | I49: 213
E50: =+$F$48 -> 12 | G50: 135 - BEBIDAS | H50: 12 | I50: 213
E51: =+$F$48 -> 12 | G51: 135 - CHOCOLATE | H51: 9 | I51: 213
E52: =+$F$48 -> 12 | G52: 135 - GALLETITAS | H52: 21 | I52: 213
E53: =+$F$48 -> 12 | G53: 135 - GOLOSINAS | H53: 14 | I53: 213
E54: =+$F$48 -> 12 | G54: 135 - MASCOTAS | H54: 6 | I54: 213
E55: =+$F$48 -> 12 | G55: 135 - NO PERECEDEROS | H55: 5 | I55: 213
E56: =+$F$48 -> 12 | G56: 135 - PILAS | H56: 6 | I56: 213
E57: =+$F$57 -> 123 | F57: 123 | G57: 135 - ALMACEN | H57: 10 | I57: 492
E58: =+$F$57 -> 123 | G58: 135 - Articulos Sin Asociar Agrupacion | H58: 7 | I58: 492
E59: =+$F$57 -> 123 | G59: 135 - BEBIDAS | H59: 7 | I59: 492
E60: =+$F$57 -> 123 | G60: 135 - CHOCOLATE | H60: 3 | I60: 492
E61: =+$F$57 -> 123 | G61: 135 - GALLETITAS | H61: 14 | I61: 492
E62: =+$F$57 -> 123 | G62: 135 - GOLOSINAS | H62: 6 | I62: 492
E63: =+$F$57 -> 123 | G63: 135 - MASCOTAS | H63: 5 | I63: 492
E64: =+$F$57 -> 123 | G64: 135 - NO PERECEDEROS | H64: 3 | I64: 492
E65: =+$F$57 -> 123 | G65: 135 - PILAS | I65: 492
E66: =+$F$66 -> 15 | F66: 15 | G66: 135 - ALMACEN | H66: 5 | I66: 65
E67: =+$F$66 -> 15 | G67: 135 - Articulos Sin Asociar Agrupacion | I67: 65
E68: =+$F$66 -> 15 | G68: 135 - BEBIDAS | H68: 5 | I68: 65
E69: =+$F$66 -> 15 | G69: 135 - CHOCOLATE | H69: 2 | I69: 65
E70: =+$F$66 -> 15 | G70: 135 - GALLETITAS | H70: 6 | I70: 65
E71: =+$F$66 -> 15 | G71: 135 - GOLOSINAS | H71: 2 | I71: 65
E72: =+$F$66 -> 15 | G72: 135 - MASCOTAS | H72: 2 | I72: 65
E73: =+$F$66 -> 15 | G73: 135 - NO PERECEDEROS | I73: 65
E74: =+$F$66 -> 15 | G74: 135 - PILAS | H74: 1 | I74: 65
E75: =+$F$75 -> 16 | F75: 16 | G75: 135 - ALMACEN | H75: 10 | I75: 201
E76: =+$F$75 -> 16 | G76: 135 - Articulos Sin Asociar Agrupacion | H76: 1 | I76: 201
E77: =+$F$75 -> 16 | G77: 135 - BEBIDAS | H77: 14 | I77: 201
E78: =+$F$75 -> 16 | G78: 135 - CHOCOLATE | H78: 4 | I78: 201
E79: =+$F$75 -> 16 | G79: 135 - GALLETITAS | H79: 16 | I79: 201
E80: =+$F$75 -> 16 | G80: 135 - GOLOSINAS | H80: 14 | I80: 201
E81: =+$F$75 -> 16 | G81: 135 - MASCOTAS | I81: 201
E82: =+$F$75 -> 16 | G82: 135 - NO PERECEDEROS | H82: 4 | I82: 201
E83: =+$F$75 -> 16 | G83: 135 - PILAS | H83: 10 | I83: 201
E84: =+$F$84 -> 18 | F84: 18 | G84: 135 - ALMACEN | H84: 16 | I84: 182
E85: =+$F$84 -> 18 | G85: 135 - Articulos Sin Asociar Agrupacion | H85: 3 | I85: 182
E86: =+$F$84 -> 18 | G86: 135 - BEBIDAS | H86: 12 | I86: 182
E87: =+$F$84 -> 18 | G87: 135 - CHOCOLATE | H87: 7 | I87: 182
E88: =+$F$84 -> 18 | G88: 135 - GALLETITAS | H88: 30 | I88: 182
E89: =+$F$84 -> 18 | G89: 135 - GOLOSINAS | H89: 19 | I89: 182
E90: =+$F$84 -> 18 | G90: 135 - MASCOTAS | H90: 3 | I90: 182
E91: =+$F$84 -> 18 | G91: 135 - NO PERECEDEROS | H91: 5 | I91: 182
E92: =+$F$84 -> 18 | G92: 135 - PILAS | H92: 4 | I92: 182
E93: =+$F$93 -> 19 | F93: 19 | G93: 135 - ALMACEN | H93: 11 | I93: 209
E94: =+$F$93 -> 19 | G94: 135 - Articulos Sin Asociar Agrupacion | H94: 4 | I94: 209
E95: =+$F$93 -> 19 | G95: 135 - BEBIDAS | H95: 20 | I95: 209
E96: =+$F$93 -> 19 | G96: 135 - CHOCOLATE | H96: 13 | I96: 209
E97: =+$F$93 -> 19 | G97: 135 - GALLETITAS | H97: 37 | I97: 209
E98: =+$F$93 -> 19 | G98: 135 - GOLOSINAS | H98: 30 | I98: 209
E99: =+$F$93 -> 19 | G99: 135 - MASCOTAS | H99: 4 | I99: 209
E100: =+$F$93 -> 19 | G100: 135 - NO PERECEDEROS | H100: 7 | I100: 209
...

Sheet Venta C
B1: VENDEDOR/ SUPERVISOR | C1: Venta NETA ARTICULOS C
A2: 20 | B2: 20 - FLORES JAVIER | C2: =IFERROR(VLOOKUP(A2,'Base venta C'!$E:$P,12,FALSE),"0")*1 -> 343887.46
A3: 19 | B3: 19 - GONZALEZ MARCELO | C3: =IFERROR(VLOOKUP(A3,'Base venta C'!$E:$P,12,FALSE),"0")*1 -> 365262.82
A4: 16 | B4: 16 - GOMEZ MATÍAS | C4: =IFERROR(VLOOKUP(A4,'Base venta C'!$E:$P,12,FALSE),"0")*1 -> 271002.4
A5: 12 | B5: 12 - GUTIERREZ MARCOS DAVID | C5: =IFERROR(VLOOKUP(A5,'Base venta C'!$E:$P,12,FALSE),"0")*1 -> 284624.48
A6: 11 | B6: 11 - ZACARIAS DAVID | C6: =IFERROR(VLOOKUP(A6,'Base venta C'!$E:$P,12,FALSE),"0")*1 -> 166886.05
A7: 8 | B7: 8 - RAVAROTTO EMANUEL | C7: =IFERROR(VLOOKUP(A7,'Base venta C'!$E:$P,12,FALSE),"0")*1 -> 284846.64
A8: 5 | B8: 5 - SCHELOVER RAUL | C8: =IFERROR(VLOOKUP(A8,'Base venta C'!$E:$P,12,FALSE),"0")*1 -> 322216.7
A9: 4 | B9: 4 - TUR SPRINGER FERNANDO | C9: =IFERROR(VLOOKUP(A9,'Base venta C'!$E:$P,12,FALSE),"0")*1 -> 875228.78
B10: MARTIN (SUPERVISOR) PREVENTA
A11: 22 | B11: 22 - ALMIRON NICOLAS | C11: =IFERROR(VLOOKUP(A11,'Base venta C'!$E:$P,12,FALSE),"0")*1 -> 270784.37
A12: 49 | B12: 49 - ESCOBAR RAÚL | C12: =IFERROR(VLOOKUP(A12,'Base venta C'!$E:$P,12,FALSE),"0")*1 -> 76349.44
A13: 15 | B13: 15 - GALARZA GERARDO | C13: =IFERROR(VLOOKUP(A13,'Base venta C'!$E:$P,12,FALSE),"0")*1 -> 1329007.3
A14: 52 | B14: 52 - MARSALL NICOLAS | C14: =IFERROR(VLOOKUP(A14,'Base venta C'!$E:$P,12,FALSE),"0")*1 -> 155315.73
A15: 53 | B15: 53 - SANDOVAL RODRIGO | C15: =IFERROR(VLOOKUP(A15,'Base venta C'!$E:$P,12,FALSE),"0")*1 -> 833691.44
B16: MARTIN (SUPERVISOR)
A17: 2 | B17: 2 - OJEDA NORBERTO | C17: =IFERROR(VLOOKUP(A17,'Base venta C'!$E:$P,12,FALSE),"0")*1 -> 355809.05
A18: 3 | B18: 3 - VIDAL NAHUEL | C18: =IFERROR(VLOOKUP(A18,'Base venta C'!$E:$P,12,FALSE),"0")*1 -> 461503.95
A19: 18 | B19: 18 - HERRERA PABLO | C19: =IFERROR(VLOOKUP(A19,'Base venta C'!$E:$P,12,FALSE),"0")*1 -> 465462.81
A20: 21 | B20: 21 - CATAN MATIAS | C20: =IFERROR(VLOOKUP(A20,'Base venta C'!$E:$P,12,FALSE),"0")*1 -> 300786.17
A21: 23 | B21: 23 - DELGADO JOSÉ | C21: =IFERROR(VLOOKUP(A21,'Base venta C'!$E:$P,12,FALSE),"0")*1 -> 517438.51
A22: 31 | B22: 31 - BARTSCHAT EMILIANO NAHUEL | C22: =IFERROR(VLOOKUP(A22,'Base venta C'!$E:$P,12,FALSE),"0")*1 -> 346898.23
A23: 44 | B23: 44 - MONGE CÉSAR LUIS | C23: =IFERROR(VLOOKUP(A23,'Base venta C'!$E:$P,12,FALSE),"0")*1 -> 475747.4
A24: 54 | B24: 54 - CAÑETE DIEGO | C24: =IFERROR(VLOOKUP(A24,'Base venta C'!$E:$P,12,FALSE),"0")*1 -> 394891.73
A25: 56 | B25: 56 - JUAN ANDRES SANCHEZ | C25: =IFERROR(VLOOKUP(A25,'Base venta C'!$E:$P,12,FALSE),"0")*1 -> 254599.35
B26: CRISTIAN (SUPERVISOR)
A27: 32 | B27: 32 - BLANCO FERNANDO | C27: =IFERROR(VLOOKUP(A27,'Base venta C'!$E:$P,12,FALSE),"0")*1 -> 357064.39
A28: 36 | B28: 36 - STELLA MARIS CANO | C28: =IFERROR(VLOOKUP(A28,'Base venta C'!$E:$P,12,FALSE),"0")*1 -> 228911.14
A29: 9 | B29: 9 - ESTIGARRIBIA DAVID | C29: =IFERROR(VLOOKUP(A29,'Base venta C'!$E:$P,12,FALSE),"0")*1 -> 449396.93
A30: 40 | B30: 40 - GARCIA BOGARIN SANTIAGO | C30: =IFERROR(VLOOKUP(A30,'Base venta C'!$E:$P,12,FALSE),"0")*1 -> 259074.86
A31: 27 | B31: 27 - GOMEZ ADRIÁN | C31: =IFERROR(VLOOKUP(A31,'Base venta C'!$E:$P,12,FALSE),"0")*1 -> 315929.47
A32: 10 | B32: 10 - SEGOVIA JUAN CRUZ | C32: =IFERROR(VLOOKUP(A32,'Base venta C'!$E:$P,12,FALSE),"0")*1 -> 385757.33
A33: 28 | B33: 28 - GOMEZ PABLO | C33: =IFERROR(VLOOKUP(A33,'Base venta C'!$E:$P,12,FALSE),"0")*1 -> 216785.26
A34: 33 | B34: 33 - NICOLAS AZULA | C34: =IFERROR(VLOOKUP(A34,'Base venta C'!$E:$P,12,FALSE),"0")*1 -> 218111.24
A35: 37 | B35: 37 - PEREZ ESQUIVEL BRUNO NICOLAS | C35: =IFERROR(VLOOKUP(A35,'Base venta C'!$E:$P,12,FALSE),"0")*1 -> 160532.76
A36: 24 | B36: 24 - DELGADO HERNAN GABRIEL | C36: =IFERROR(VLOOKUP(A36,'Base venta C'!$E:$P,12,FALSE),"0")*1 -> 294217.66
A37: 7 | B37: 7 - VALLEJOS EDUARDO | C37: =IFERROR(VLOOKUP(A37,'Base venta C'!$E:$P,12,FALSE),"0")*1 -> 264122.85
A38: 57 | B38: 57 - ZARATE NICOLAS | C38: =IFERROR(VLOOKUP(A38,'Base venta C'!$E:$P,12,FALSE),"0")*1 -> 62179.29
A39: 1 | B39: 1 - VERA ERNESTO | C39: =IFERROR(VLOOKUP(A39,'Base venta C'!$E:$P,12,FALSE),"0")*1 -> 1671221.4
B40: GONZALO (SUPERVISOR)
B41: LOPEZ ENZO

Sheet Base venta C
A1: Periodos | B1: Cod. Período | C1: Descripción Período | D1: Vendedor según comprobante | E1: Código | F1: Descripción | G1: Rotacion a-b-c | H1: Código | I1: Descripción | J1: P.P.P. Neto | K1: P.P.P. Final | L1: Cantidades CON Cargo | M1: Cantidades SIN Cargo | N1: Cantidades Totales | O1: Pesos Totales | P1: Importes Netos | Q1: Importes Finales | R1: Cantidad de Facturas | S1: Bultos Promedio | T1: Cantidades en Combos
A2: (001) MAR 2026 | B2: 1 | C2: 46082 | D2: Suc: 001 (000001) VERA ERNESTO | E2: 1 | F2: VERA ERNESTO | G2: (1382) ROTACION C INCENTIVO | H2: 1382 | I2: ROTACION C INCENTIVO | J2: 98746.145 | K2: 122432.8 | L2: 14.2607 | M2: 2.6637 | N2: 16.9244 | O2: 0 | P2: 1671221.4 | Q2: 2072104.4 | R2: 128 | S2: 0.13 | T2: 0
A3: (001) MAR 2026 | B3: 1 | C3: 46082 | D3: Suc: 001 (000002) OJEDA NORBERTO | E3: 2 | F3: OJEDA NORBERTO | G3: (1382) ROTACION C INCENTIVO | H3: 1382 | I3: ROTACION C INCENTIVO | J3: 11815.421 | K3: 14554.453 | L3: 25.5498 | M3: 4.5642 | N3: 30.114 | O3: 0 | P3: 355809.05 | Q3: 438292.15 | R3: 73 | S3: 0.41 | T3: 0
A4: (001) MAR 2026 | B4: 1 | C4: 46082 | D4: Suc: 001 (000003) VIDAL NAHUEL | E4: 3 | F4: VIDAL NAHUEL | G4: (1382) ROTACION C INCENTIVO | H4: 1382 | I4: ROTACION C INCENTIVO | J4: 12029.634 | K4: 14825.838 | L4: 27.3731 | M4: 10.9908 | N4: 38.3639 | O4: 0 | P4: 461503.95 | Q4: 568777.28 | R4: 79 | S4: 0.49 | T4: 0
A5: (001) MAR 2026 | B5: 1 | C5: 46082 | D5: Suc: 001 (000004) TUR SPRINGER FERNANDO | E5: 4 | F5: TUR SPRINGER FERNANDO | G5: (1382) ROTACION C INCENTIVO | H5: 1382 | I5: ROTACION C INCENTIVO | J5: 17624.902 | K5: 21774.702 | L5: 44.3529 | M5: 5.3058 | N5: 49.6586 | O5: 0 | P5: 875228.78 | Q5: 1081302.2 | R5: 100 | S5: 0.5 | T5: 0
A6: (001) MAR 2026 | B6: 1 | C6: 46082 | D6: Suc: 001 (000005) SCHELOVER RAUL | E6: 5 | F6: SCHELOVER RAUL | G6: (1382) ROTACION C INCENTIVO | H6: 1382 | I6: ROTACION C INCENTIVO | J6: 26707.909 | K6: 32656.222 | L6: 7.0172 | M6: 5.0472 | N6: 12.0645 | O6: 0 | P6: 322216.7 | Q6: 393979.93 | R6: 70 | S6: 0.17 | T6: 0
A7: (001) MAR 2026 | B7: 1 | C7: 46082 | D7: Suc: 001 (000007) VALLEJOS EDUARDO | E7: 7 | F7: VALLEJOS EDUARDO | G7: (1382) ROTACION C INCENTIVO | H7: 1382 | I7: ROTACION C INCENTIVO | J7: 6772.381 | K7: 8382.717 | L7: 39 | M7: 0 | N7: 39 | O7: 0 | P7: 264122.85 | Q7: 326925.97 | R7: 1 | S7: 39 | T7: 0
A8: (001) MAR 2026 | B8: 1 | C8: 46082 | D8: Suc: 001 (000008) RAVAROTTO EMANUEL | E8: 8 | F8: RAVAROTTO EMANUEL | G8: (1382) ROTACION C INCENTIVO | H8: 1382 | I8: ROTACION C INCENTIVO | J8: 18047.967 | K8: 22290.443 | L8: 8.0508 | M8: 7.7319 | N8: 15.7828 | O8: 0 | P8: 284846.64 | Q8: 351804.59 | R8: 61 | S8: 0.26 | T8: 0
A9: (001) MAR 2026 | B9: 1 | C9: 46082 | D9: Suc: 001 (000009) ESTIGARRIBIA DAVID | E9: 9 | F9: ESTIGARRIBIA DAVID | G9: (1382) ROTACION C INCENTIVO | H9: 1382 | I9: ROTACION C INCENTIVO | J9: 9288.078 | K9: 11426.613 | L9: 40.549 | M9: 7.8353 | N9: 48.3843 | O9: 0 | P9: 449396.93 | Q9: 552868.39 | R9: 85 | S9: 0.57 | T9: 0
A10: (001) MAR 2026 | B10: 1 | C10: 46082 | D10: Suc: 001 (000010) SEGOVIA JUAN CRUZ | E10: 10 | F10: SEGOVIA JUAN CRUZ | G10: (1382) ROTACION C INCENTIVO | H10: 1382 | I10: ROTACION C INCENTIVO | J10: 19423.102 | K10: 23755.08 | L10: 16.26 | M10: 3.6008 | N10: 19.8607 | O10: 0 | P10: 385757.33 | Q10: 471793.64 | R10: 61 | S10: 0.33 | T10: 0
A11: (001) MAR 2026 | B11: 1 | C11: 46082 | D11: Suc: 001 (000011) ZACARIAS DAVID | E11: 11 | F11: ZACARIAS DAVID | G11: (1382) ROTACION C INCENTIVO | H11: 1382 | I11: ROTACION C INCENTIVO | J11: 19880.77 | K11: 24580.662 | L11: 6.225 | M11: 2.1693 | N11: 8.3943 | O11: 0 | P11: 166886.05 | Q11: 206338.57 | R11: 53 | S11: 0.16 | T11: 0
A12: (001) MAR 2026 | B12: 1 | C12: 46082 | D12: Suc: 001 (000012) GUTIERREZ MARCOS DAVID | E12: 12 | F12: GUTIERREZ MARCOS DAVID | G12: (1382) ROTACION C INCENTIVO | H12: 1382 | I12: ROTACION C INCENTIVO | J12: 21003.651 | K12: 25910.202 | L12: 6.2833 | M12: 7.2679 | N12: 13.5512 | O12: 0 | P12: 284624.48 | Q12: 351114.08 | R12: 65 | S12: 0.21 | T12: 0
A13: (001) MAR 2026 | B13: 1 | C13: 46082 | D13: Suc: 001 (000015) GALARZA GERARDO | E13: 15 | F13: GALARZA GERARDO | G13: (1382) ROTACION C INCENTIVO | H13: 1382 | I13: ROTACION C INCENTIVO | J13: 39203.754 | K13: 49427.271 | L13: 33.6667 | M13: 0.2333 | N13: 33.9 | O13: 0 | P13: 1329007.3 | Q13: 1675584.5 | R13: 10 | S13: 3.39 | T13: 0
... A45: (001) MAR 2026 | B45: 1 | C45: 46082 | D45: Suc: 001 (000123) TORRES ROLANDO | E45: 123 | F45: TORRES ROLANDO | G45: (1382) ROTACION C INCENTIVO | H45: 1382 | I45: ROTACION C INCENTIVO | J45: 52587.592 | K45: 64949.011 | L45: 26.325 | M45: 0.1667 | N45: 26.4917 | O45: 0 | P45: 1393132.9 | Q45: 1720607.6 | R45: 13 | S45: 2.04 | T45: 0

Sheet Historico Enero
A1: VENDEDOR/ SUPERVISOR | B1: OBJETIVO | C1: FACTURACION ACUMULADA | D1: FACTURACION N-1 | E1: FACTURACION DEL DIA | F1: AVANCE VS OBJETIVO | G1: PROYECCION | H1: CUMPLIMIENTO PROYECTADO | I1: MEDIA REAL | J1: MEDIA NECESARIA | K1: COBRO | N1: VENDEDOR/ SUPERVISOR | O1: COBERTURA TOTAL | P1: DIA ANTERIOR | Q1: INCREMENTO DIARIO | R1: CARTERA TOTAL | S1: CCC | T1: CCC FALTANTE 85% | W1: Cantidad skus
A2: 20 - FLORES JAVIER | B2: 28001295 | C2: 32969064 | D2: 0 | E2: 32969064 | F2: 1.1774121 | G2: 32969064 | H2: 1.1774121 | I2: 1268040.9 | J2: #DIV/0! | K2: 659381.28 | M2: 22 | N2: 22 - ALMIRON NICOLAS | O2: 0.79411765 | P2: 33 | Q2: 21 | R2: 68 | S2: 54 | T2: 3.8 | V2: Supervisor Cristian | Z2: Vendedores Mayoristas | AB2: Cantidad skus
A3: 19 - GONZALEZ MARCELO | B3: 26876745 | C3: 29130365 | D3: 0 | E3: 29130365 | F3: 1.0838502 | G3: 29130365 | H3: 1.0838502 | I3: 1120398.6 | J3: #DIV/0! | K3: 364129.56 | M3: 49 | N3: 49 - ESCOBAR RAÚL | O3: 0.45493562 | P3: 1 | Q3: 105 | R3: 233 | S3: 106 | T3: 92.05 | V3: Cod vdor | X3: Cantidad skus | Z3: 15 | AA3: GALARZA GERARDO | AB3: 261
A4: 16 - GOMEZ MATÍAS | B4: 24627645 | C4: 20258834 | D4: 0 | E4: 20258834 | F4: 0.82260539 | G4: 20258834 | H4: 0.82260539 | I4: 779185.91 | J4: #DIV/0! | K4: 0 | M4: 20 | N4: 20 - FLORES JAVIER | O4: 0.91891892 | P4: 126 | Q4: 78 | R4: 222 | S4: 204 | T4: -15.3 | V4: 2 | W4: OJEDA NORBERTO | X4: 302 | Z4: 7 | AA4: VALLEJOS EDUARDO | AB4: 154
A5: 12 - GUTIERREZ MARCOS DAVID | B5: 24627645 | C5: 26537938 | D5: 0 | E5: 26537938 | F5: 1.077567 | G5: 26537938 | H5: 1.077567 | I5: 1020689.9 | J5: #DIV/0! | K5: 331724.23 | M5: 15 | N5: 15 - GALARZA GERARDO | O5: 0.78461538 | P5: 21 | Q5: 30 | R5: 65 | S5: 51 | T5: 4.25 | V5: 3 | W5: VIDAL NAHUEL | X5: 321
A6: 11 - ZACARIAS DAVID | B6: 20410582 | C6: 17576103 | D6: 0 | E6: 17576103 | F6: 0.86112695 | G6: 17576103 | H6: 0.86112695 | I6: 676003.95 | J6: #DIV/0! | K6: 0 | M6: 19 | N6: 19 - GONZALEZ MARCELO | O6: 0.85784314 | P6: 100 | Q6: 75 | R6: 204 | S6: 175 | T6: -1.6 | V6: 18 | W6: HERRERA PABLO | X6: 331
A7: 8 - RAVAROTTO EMANUEL | B7: 24065370 | C7: 24383409 | D7: 0 | E7: 24383409 | F7: 1.0132156 | G7: 24383409 | H7: 1.0132156 | I7: 937823.42 | J7: #DIV/0! | K7: 243834.09 | M7: 16 | N7: 16 - GOMEZ MATÍAS | O7: 0.87309645 | P7: 81 | Q7: 91 | R7: 197 | S7: 172 | T7: -4.55 | V7: 21 | W7: CATAN MATIAS | X7: 317
A8: 5 - SCHELOVER RAUL | B8: 31082562 | C8: 32899445 | D8: 0 | E8: 32899445 | F8: 1.0584534 | G8: 32899445 | H8: 1.0584534 | I8: 1265363.3 | J8: #DIV/0! | K8: 411243.06 | M8: 12 | N8: 12 - GUTIERREZ MARCOS DAVID | O8: 0.89952153 | P8: 89 | Q8: 99 | R8: 209 | S8: 188 | T8: -10.35 | V8: 23 | W8: DELGADO JOSÉ | X8: 370 | Z8: Vendedores Supermercados | AB8: Cantidad skus
A9: 4 - TUR SPRINGER FERNANDO | B9: 31082562 | C9: 30879202 | D9: 0 | E9: 30879202 | F9: 0.99345741 | G9: 30879202 | H9: 0.99345741 | I9: 1187661.6 | J9: #DIV/0! | K9: 308792.02 | M9: 11 | N9: 11 - ZACARIAS DAVID | O9: 0.90797546 | P9: 92 | Q9: 56 | R9: 163 | S9: 148 | T9: -9.45 | V9: 31 | W9: RENZO RAMOS | X9: 322 | Z9: 22 | AA9: ALMIRON NICOLAS | AB9: 339
A10: MARTIN (SUPERVISOR) PREVENTA | B10: 2.1077441e+08 | C10: 2.1463436e+08 | D10: 0 | E10: 2.1463436e+08 | F10: 1.0183132 | G10: 2.1463436e+08 | H10: 1.0183132 | I10: 8255167.6 | J10: #DIV/0! | M10: 8 | N10: 8 - RAVAROTTO EMANUEL | O10: 0.83243243 | P10: 64 | Q10: 90 | R10: 185 | S10: 154 | T10: 3.25 | V10: 44 | W10: MONGES CESAR LUIS | X10: 311 | Z10: 32 | AA10: CABRAL GONZALO | AB10: 424
A11: 22 - ALMIRON NICOLAS | B11: 84120750 | C11: 64387272 | D11: 0 | E11: 64387272 | F11: 0.76541486 | G11: 64387272 | H11: 0.76541486 | I11: 2476433.5 | J11: #DIV/0! | K11: 0 | M11: 52 | N11: 52 - MARSALL NICOLAS | O11: 0.52884615 | P11: 19 | Q11: 36 | R11: 104 | S11: 55 | T11: 33.4 | V11: 54 | W11: BARTSCHAT EMILIANO NAHUEL | X11: 375
A12: 49 - ESCOBAR RAÚL | B12: 27439020 | C12: 21503764 | D12: 0 | E12: 21503764 | F12: 0.78369285 | G12: 21503764 | H12: 0.78369285 | I12: 827067.84 | J12: #DIV/0! | K12: 0 | M12: 53 | N12: 53 - SANDOVAL RODRIGO | O12: 0.62727273 | P12: 24 | Q12: 45 | R12: 110 | S12: 69 | T12: 24.5 | V12: Totales | Z12: Supervisior Maxi | AB12: Cantidad skus
A13: 15 - GALARZA GERARDO | B13: 111352500 | C13: 81948671 | D13: 0 | E13: 81948671 | F13: 0.73593921 | G13: 81948671 | H13: 0.73593921 | I13: 3151872 | J13: #DIV/0! | K13: 0 | M13: 5 | N13: 5 - SCHELOVER RAUL | O13: 0.96484375 | P13: 144 | Q13: 103 | R13: 256 | S13: 247 | T13: -29.4 | V13: Supervisor Martin | X13: Cantidad skus | Z13: 58 | AA13: #N/A | AB13: #N/A
A14: 52 - MARSALL NICOLAS | B14: 36823500 | C14: 27773182 | D14: 0 | E14: 27773182 | F14: 0.75422438 | G14: 27773182 | H14: 0.75422438 | I14: 1068199.3 | J14: #DIV/0! | K14: 0 | M14: 4 | N14: 4 - TUR SPRINGER FERNANDO | O14: 0.88571429 | P14: 85 | Q14: 70 | R14: 175 | S14: 155 | T14: -6.25 | V14: 4 | W14: TUR SPRINGER FERNANDO | X14: 382 | Z14: 59 | AA14: #N/A | AB14: #N/A
A15: 53 - SANDOVAL RODRIGO | B15: 36823500 | C15: 40412111 | D15: 0 | E15: 40412111 | F15: 1.0974544 | G15: 40412111 | H15: 1.0974544 | I15: 1554312 | J15: #DIV/0! | K15: 606181.66 | N15: MARTIN (SUPERVISOR) | Q15: 899 | R15: 2191 | S15: 1778 | V15: 5 | W15: SCHELOVER RAUL | X15: 421 | Z15: 60 | AA15: #N/A | AB15: #N/A
A16: MARTIN (SUPERVISOR) | B16: 296559270 | C16: 2.36025e+08 | D16: 0 | E16: 2.36025e+08 | F16: 0.795878 | G16: 2.36025e+08 | H16: 0.795878 | I16: 9077884.6 | J16: #DIV/0! | M16: 31 | N16: 31 - BARTSCHAT EMILIANO NAHUEL | O16: 0.91082803 | P16: 90 | Q16: 53 | R16: 157 | S16: 143 | T16: -9.55 | V16: 8 | W16: PARRA MAXIMILIANO | X16: 290 | Z16: 56 | AA16: JUAN ANDRES SANCHEZ | AB16: 235
A17: 2 - OJEDA NORBERTO | B17: 25450000 | C17: 16519194 | D17: 0 | E17: 16519194 | F17: 0.64908425 | G17: 16519194 | H17: 0.64908425 | I17: 635353.63 | J17: #DIV/0! | K17: 0 | M17: 54 | N17: 54 - CAÑETE DIEGO | O17: 0.66494845 | P17: 92 | Q17: 37 | R17: 194 | S17: 129 | T17: 35.9 | V17: 11 | W17: SANCHEZ RICARDO | X17: 255 | Z17: 26 | AA17: PUJOL ERNESTO | AB17: 260
A18: 3 - VIDAL NAHUEL | B18: 22430000 | C18: 14871119 | D18: 0 | E18: 14871119 | F18: 0.66300128 | G18: 14871119 | H18: 0.66300128 | I18: 571966.1 | J18: #DIV/0! | K18: 0 | M18: 21 | N18: 21 - CATAN MATIAS | O18: 0.81097561 | P18: 88 | Q18: 45 | R18: 164 | S18: 133 | T18: 6.4 | V18: 12 | W18: GUTIERREZ MARCOS DAVID | X18: 383 | Z18: 25 | AA18: KALATAKI GUSTAVO | AB18: 455
A19: 18 - HERRERA PABLO | B19: 22430000 | C19: 17383068 | D19: 0 | E19: 17383068 | F19: 0.77499188 | G19: 17383068 | H19: 0.77499188 | I19: 668579.53 | J19: #DIV/0! | K19: 0 | M19: 23 | N19: 23 - DELGADO JOSÉ | O19: 0.91333333 | P19: 95 | Q19: 42 | R19: 150 | S19: 137 | T19: -9.5 | V19: 16 | W19: GOMEZ MATÍAS | X19: 282 | Z19: 43 | AA19: COLHER DIEGO | AB19: 218
A20: 21 - CATAN MATIAS | B20: 29000000 | C20: 24462625 | D20: 0 | E20: 24462625 | F20: 0.84353878 | G20: 24462625 | H20: 0.84353878 | I20: 940870.18 | J20: #DIV/0! | K20: 0 | M20: 18 | N20: 18 - HERRERA PABLO | O20: 0.86046512 | P20: 83 | Q20: 65 | R20: 172 | S20: 148 | T20: -1.8 | V20: 19 | W20: GONZALEZ MARCELO | X20: 377
A21: 23 - DELGADO JOSÉ | B21: 22000000 | C21: 19224921 | D21: 0 | E21: 19224921 | F21: 0.87386003 | G21: 19224921 | H21: 0.87386003 | I21: 739420.02 | J21: #DIV/0! | K21: 0 | M21: 44 | N21: 44 - MONGE CÉSAR LUIS | O21: 0.88505747 | P21: 64 | Q21: 90 | R21: 174 | S21: 154 | T21: -6.1 | V21: 20 | W21: FLORES JAVIER | X21: 373 | Z21: Vendedores PETS | AB21: Cantidad skus
A22: 31 - BARTSCHAT EMILIANO NAHUEL | B22: 27500000 | C22: 22580286 | D22: 0 | E22: 22580286 | F22: 0.82110133 | G22: 22580286 | H22: 0.82110133 | I22: 868472.56 | J22: #DIV/0! | K22: 0 | M22: 56 | N22: 56 - JUAN ANDRES SANCHEZ | O22: 0.46268657 | P22: 66 | Q22: 27 | R22: 201 | S22: 93 | T22: 77.85 | V22: Totales | Z22: 52 | AA22: RAVAROTTO EMANUEL | AB22: 136
A23: 44 - MONGE CÉSAR LUIS | B23: 23800000 | C23: 18758064 | D23: 0 | E23: 18758064 | F23: 0.78815396 | G23: 18758064 | H23: 0.78815396 | I23: 721464.01 | J23: #DIV/0! | K23: 0 | M23: 2 | N23: 2 - OJEDA NORBERTO | O23: 0.83783784 | P23: 70 | Q23: 54 | R23: 148 | S23: 124 | T23: 1.8 | V23: Supervision Corrientes | X23: Cantidad skus | Z23: 53 | AA23: SANDOVAL RODRIGO | AB23: 132
A24: 54 - CAÑETE DIEGO | B24: 28500000 | C24: 25700325 | D24: 0 | E24: 25700325 | F24: 0.9017658 | G24: 25700325 | H24: 0.9017658 | I24: 988474.05 | J24: #DIV/0! | K24: 0 | M24: 3 | N24: 3 - VIDAL NAHUEL | O24: 0.90967742 | P24: 79 | Q24: 62 | R24: 155 | S24: 141 | T24: -9.25 | V24: 1 | W24: VERA ERNESTO | X24: 328 | Z24: 57 | AA24: FEDERRATH MARTIN | AB24: 105
A25: 56 - JUAN ANDRES SANCHEZ | B25: 46900000 | C25: 26132281 | D25: 0 | E25: 26132281 | F25: 0.55719149 | G25: 26132281 | H25: 0.55719149 | I25: 1005087.7 | J25: #DIV/0! | K25: 0 | N25: CRISTIAN (SUPERVISOR) | Q25: 475 | R25: 1515 | S25: 1202 | V25: 9 | W25: ESTIGARRIBIA DAVID | X25: 300
A26: CRISTIAN (SUPERVISOR) | B26: 248010000 | C26: 1.8563188e+08 | D26: 0 | E26: 1.8563188e+08 | F26: 0.74848548 | G26: 1.8563188e+08 | H26: 0.74848548 | I26: 7139687.8 | J26: #DIV/0! | M26: 32 | N26: 32 - BLANCO FERNANDO | O26: 0.83636364 | P26: 20 | Q26: 26 | R26: 55 | S26: 46 | T26: 0.75 | V26: 10 | W26: BRITEZ EMMANUEL | X26: 293
A27: 32 - BLANCO FERNANDO | B27: 72908794 | C27: 59705699 | D27: 0 | E27: 59705699 | F27: 0.81890944 | G27: 59705699 | H27: 0.81890944 | I27: 2296373.1 | J27: #DIV/0! | K27: 0 | M27: 36 | N27: 36 - STELLA MARIS CANO | O27: 0.64705882 | P27: 68 | Q27: 31 | R27: 153 | S27: 99 | T27: 31.05 | V27: 24 | W27: SOLIS EMMANUEL | X27: 338
A28: 36 - STELLA MARIS CANO | B28: 20300095 | C28: 7088486.6 | D28: 0 | E28: 7088486.6 | F28: 0.34918489 | G28: 7088486.6 | H28: 0.34918489 | I28: 272634.1 | J28: #DIV/0! | K28: 0 | M28: 9 | N28: 9 - ESTIGARRIBIA DAVID | O28: 0.7114094 | P28: 80 | Q28: 26 | R28: 149 | S28: 106 | T28: 20.65 | V28: 27 | W28: GOMEZ ADRIÁN | X28: 364
A29: 9 - ESTIGARRIBIA DAVID | B29: 21701088 | C29: 11524508 | D29: 0 | E29: 11524508 | F29: 0.53105671 | G29: 11524508 | H29: 0.53105671 | I29: 443250.32 | J29: #DIV/0! | K29: 0 | M29: 40 | N29: 40 - GARCIA BOGARIN SANTIAGO | O29: 0.86666667 | P29: 68 | Q29: 140 | R29: 240 | S29: 208 | T29: -4 | V29: 28 | W29: GOMEZ PABLO | X29: 315
A30: 40 - GARCIA BOGARIN SANTIAGO | B30: 33166353 | C30: 32454209 | D30: 0 | E30: 32454209 | F30: 0.97852812 | G30: 32454209 | H30: 0.97852812 | I30: 1248238.8 | J30: #DIV/0! | K30: 0 | M30: 27 | N30: 27 - GOMEZ ADRIÁN | O30: 0.87769784 | P30: 73 | Q30: 49 | R30: 139 | S30: 122 | T30: -3.85 | V30: 33 | W30: NICOLAS AZULA | X30: 207
A31: 27 - GOMEZ ADRIÁN | B31: 21701088 | C31: 18178589 | D31: 0 | E31: 18178589 | F31: 0.83768098 | G31: 18178589 | H31: 0.83768098 | I31: 699176.48 | J31: #DIV/0! | K31: 0 | M31: 10 | N31: 10 - SEGOVIA JUAN CRUZ | O31: 0.79558011 | P31: 40 | Q31: 104 | R31: 181 | S31: 144 | T31: 9.85 | V31: 36 | W31: COSARINSKI DIEGO | X31: 197
A32: 10 - SEGOVIA JUAN CRUZ | B32: 21701088 | C32: 22255931 | D32: 0 | E32: 22255931 | F32: 1.0255675 | G32: 22255931 | H32: 1.0255675 | I32: 855997.34 | J32: #DIV/0! | K32: 222559.31 | M32: 28 | N32: 28 - GOMEZ PABLO | O32: 0.87150838 | P32: 67 | Q32: 89 | R32: 179 | S32: 156 | T32: -3.85 | V32: 37 | W32: SALAJ EMILIO | X32: 246
A33: 28 - GOMEZ PABLO | B33: 20586012 | C33: 21491454 | D33: 0 | E33: 21491454 | F33: 1.0439834 | G33: 21491454 | H33: 1.0439834 | I33: 826594.39 | J33: #DIV/0! | K33: 268643.18 | M33: 33 | N33: 33 - NICOLAS AZULA | O33: 0.57926829 | P33: 66 | Q33: 29 | R33: 164 | S33: 95 | T33: 44.4 | V33: 40 | W33: IBARROLA JORGE | X33: 428
A34: 33 - NICOLAS AZULA | B34: 21701088 | C34: 6604694.9 | D34: 0 | E34: 6604694.9 | F34: 0.30434856 | G34: 6604694.9 | H34: 0.30434856 | I34: 254026.73 | J34: #DIV/0! | K34: 0 | M34: 37 | N34: 37 - PEREZ ESQUIVEL BRUNO NICOLAS | O34: 0.69736842 | P34: 82 | Q34: 24 | R34: 152 | S34: 106 | T34: 23.2 | V34: Totales
A35: 37 - PEREZ ESQUIVEL BRUNO NICOLAS | B35: 20586012 | C35: 10300686 | D35: 0 | E35: 10300686 | F35: 0.50037307 | G35: 10300686 | H35: 0.50037307 | I35: 396180.23 | J35: #DIV/0! | K35: 0 | M35: 24 | N35: 24 - DELGADO HERNAN GABRIEL | O35: 0.82954545 | P35: 81 | Q35: 65 | R35: 176 | S35: 146 | T35: 3.6
A36: 24 - DELGADO HERNAN GABRIEL | B36: 21729680 | C36: 17015925 | D36: 0 | E36: 17015925 | F36: 0.78307297 | G36: 17015925 | H36: 0.78307297 | I36: 654458.65 | J36: #DIV/0! | K36: 0 | M36: 7 | N36: 7 - VALLEJOS EDUARDO | O36: 0.14414414 | P36: 0 | Q36: 16 | R36: 111 | S36: 16 | T36: 78.35
A37: 7 - VALLEJOS EDUARDO | B37: 1.0293006e+08 | C37: 71043541 | D37: 0 | E37: 71043541 | F37: 0.69021178 | G37: 71043541 | H37: 0.69021178 | I37: 2732443.9 | J37: #DIV/0! | K37: 0 | M37: 57 | N37: 57 - ZARATE NICOLAS | O37: 0.5 | P37: 17 | Q37: 35 | R37: 104 | S37: 52 | T37: 36.4
A38: 57 - ZARATE NICOLAS | B38: 29964085 | C38: 34108717 | D38: 0 | E38: 34108717 | F38: 1.13832 | G38: 34108717 | H38: 1.13832 | I38: 1311873.7 | J38: #DIV/0! | K38: 511630.76 | M38: 1 | N38: 1 - VERA ERNESTO | O38: 0.87903226 | P38: 60 | Q38: 49 | R38: 124 | S38: 109 | T38: -3.6
A39: 1 - VERA ERNESTO | B39: 32594519 | C39: 24484653 | D39: 0 | E39: 24484653 | F39: 0.75118927 | G39: 24484653 | H39: 0.75118927 | I39: 941717.43 | J39: #DIV/0! | K39: 0 | N39: NELSON (SUPERVISOR) | Q39: 683 | R39: 1927 | S39: 1405
A40: NELSON (SUPERVISOR) | B40: 4.4156996e+08 | C40: 3.3625709e+08 | D40: 0 | E40: 3.3625709e+08 | F40: 0.76150355 | G40: 3.3625709e+08 | H40: 0.76150355 | I40: 12932965 | J40: #DIV/0! | N40: LOPEZ ENZO | Q40: 2057 | R40: 5633 | S40: 4385
A41: LOPEZ ENZO | B41: 1.1969136e+09 | C41: 9.7254833e+08 | D41: 0 | E41: 9.7254833e+08 | F41: 0.81254679 | G41: 9.7254833e+08 | H41: 0.81254679 | I41: 37405705 | J41: #DIV/0!

Sheet Historico Febrero
A1: VENDEDOR/ SUPERVISOR | B1: OBJETIVO | C1: FACTURACION ACUMULADA | D1: FACTURACION N-1 | E1: FACTURACION DEL DIA | F1: AVANCE VS OBJETIVO | G1: PROYECCION | H1: CUMPLIMIENTO PROYECTADO | I1: MEDIA REAL | J1: MEDIA NECESARIA | K1: COBRO | N1: VENDEDOR/ SUPERVISOR | O1: COBERTURA TOTAL | P1: DIA ANTERIOR | Q1: INCREMENTO DIARIO | R1: CARTERA TOTAL | S1: CCC | T1: CCC FALTANTE 85% | W1: Cantidad skus
A2: 20 - FLORES JAVIER | B2: 28561321 | C2: 39721296 | D2: 39088386 | E2: 632909.85 | F2: 1.3907374 | G2: 39721296 | H2: 1.3907374 | I2: 1727012.9 | J2: #DIV/0! | K2: 794425.92 | M2: 22 | N2: 22 - ALMIRON NICOLAS | O2: 0.87142857 | P2: 33 | Q2: 28 | R2: 70 | S2: 61 | T2: -1.5 | V2: Supervisor Cristian | Z2: Vendedores Mayoristas | AB2: Cantidad skus
A3: 19 - GONZALEZ MARCELO | B3: 27414280 | C3: 29249180 | D3: 28088898 | E3: 1160282.6 | F3: 1.0669323 | G3: 29249180 | H3: 1.0669323 | I3: 1271703.5 | J3: #DIV/0! | K3: 365614.75 | M3: 49 | N3: 49 - ESCOBAR RAÚL | O3: 0.45064378 | P3: 1 | Q3: 104 | R3: 233 | S3: 105 | T3: 93.05 | V3: Cod vdor | X3: Cantidad skus | Z3: 15 | AA3: GALARZA GERARDO | AB3: 317
A4: 16 - GOMEZ MATÍAS | B4: 25120198 | C4: 23167100 | D4: 21799244 | E4: 1367856.5 | F4: 0.92224991 | G4: 23167100 | H4: 0.92224991 | I4: 1007265.2 | J4: #DIV/0! | K4: 0 | M4: 20 | N4: 20 - FLORES JAVIER | O4: 0.94222222 | P4: 126 | Q4: 86 | R4: 225 | S4: 212 | T4: -20.75 | V4: 2 | W4: OJEDA NORBERTO | X4: 313 | Z4: 7 | AA4: VALLEJOS EDUARDO | AB4: 114
A5: 12 - GUTIERREZ MARCOS DAVID | B5: 25120198 | C5: 31630959 | D5: 30307629 | E5: 1323329.4 | F5: 1.2591843 | G5: 31630959 | H5: 1.2591843 | I5: 1375259.1 | J5: #DIV/0! | K5: 632619.18 | M5: 15 | N5: 15 - GALARZA GERARDO | O5: 0.83076923 | P5: 21 | Q5: 33 | R5: 65 | S5: 54 | T5: 1.25 | V5: 3 | W5: VIDAL NAHUEL | X5: 332
A6: 11 - ZACARIAS DAVID | B6: 20818794 | C6: 15488446 | D6: 15012989 | E6: 475456.5 | F6: 0.74396461 | G6: 15488446 | H6: 0.74396461 | I6: 673410.69 | J6: #DIV/0! | K6: 0 | M6: 19 | N6: 19 - GONZALEZ MARCELO | O6: 0.89756098 | P6: 100 | Q6: 84 | R6: 205 | S6: 184 | T6: -9.75 | V6: 18 | W6: HERRERA PABLO | X6: 294
A7: 8 - RAVAROTTO EMANUEL | B7: 24546677 | C7: 18088953 | D7: 17362470 | E7: 726482.81 | F7: 0.73692064 | G7: 18088953 | H7: 0.73692064 | I7: 786476.22 | J7: #DIV/0! | K7: 0 | M7: 16 | N7: 16 - GOMEZ MATÍAS | O7: 0.9035533 | P7: 81 | Q7: 97 | R7: 197 | S7: 178 | T7: -10.55 | V7: 21 | W7: CATAN MATIAS | X7: 354
A8: 5 - SCHELOVER RAUL | B8: 31704213 | C8: 25692635 | D8: 25203128 | E8: 489506.21 | F8: 0.8103855 | G8: 25692635 | H8: 0.8103855 | I8: 1117071.1 | J8: #DIV/0! | K8: 0 | M8: 12 | N8: 12 - GUTIERREZ MARCOS DAVID | O8: 0.9 | P8: 89 | Q8: 100 | R8: 210 | S8: 189 | T8: -10.5 | V8: 23 | W8: DELGADO JOSÉ | X8: 317 | Z8: Vendedores Supermercados | AB8: Cantidad skus
A9: 4 - TUR SPRINGER FERNANDO | B9: 31704213 | C9: 32620850 | D9: 30865959 | E9: 1754891.8 | F9: 1.0289122 | G9: 32620850 | H9: 1.0289122 | I9: 1418297.8 | J9: #DIV/0! | K9: 326208.5 | M9: 11 | N9: 11 - ZACARIAS DAVID | O9: 0.84146341 | P9: 92 | Q9: 46 | R9: 164 | S9: 138 | T9: 1.4 | V9: 31 | W9: RENZO RAMOS | X9: 393 | Z9: 22 | AA9: ALMIRON NICOLAS | AB9: 348
A10: MARTIN (SUPERVISOR) PREVENTA | B10: 2.1498989e+08 | C10: 2.1565942e+08 | D10: 2.077287e+08 | E10: 7930715.6 | F10: 1.0031142 | G10: 2.1565942e+08 | H10: 1.0031142 | I10: 9376496.5 | J10: #DIV/0! | M10: 8 | N10: 8 - RAVAROTTO EMANUEL | O10: 0.8655914 | P10: 64 | Q10: 97 | R10: 186 | S10: 161 | T10: -2.9 | V10: 44 | W10: MONGES CESAR LUIS | X10: 281 | Z10: 32 | AA10: CABRAL GONZALO | AB10: 349
A11: 22 - ALMIRON NICOLAS | B11: 85803165 | C11: 74801914 | D11: 72706629 | E11: 2095285.3 | F11: 0.87178503 | G11: 74801914 | H11: 0.87178503 | I11: 3252257.1 | J11: #DIV/0! | K11: 0 | M11: 52 | N11: 52 - MARSALL NICOLAS | O11: 0.60576923 | P11: 19 | Q11: 44 | R11: 104 | S11: 63 | T11: 25.4 | V11: 54 | W11: BARTSCHAT EMILIANO NAHUEL | X11: 433
A12: 49 - ESCOBAR RAÚL | B12: 27987800 | C12: 21624276 | D12: 21624276 | E12: 0 | F12: 0.77263221 | G12: 21624276 | H12: 0.77263221 | I12: 940185.91 | J12: #DIV/0! | K12: 0 | M12: 53 | N12: 53 - SANDOVAL RODRIGO | O12: 0.54867257 | P12: 24 | Q12: 38 | R12: 113 | S12: 62 | T12: 34.05 | V12: Totales | Z12: Supervisior Maxi | AB12: Cantidad skus
A13: 15 - GALARZA GERARDO | B13: 113579550 | C13: 1.105629e+08 | D13: 1.0102614e+08 | E13: 9536757.5 | F13: 0.9734402 | G13: 1.105629e+08 | H13: 0.9734402 | I13: 4807082.6 | J13: #DIV/0! | K13: 0 | M13: 5 | N13: 5 - SCHELOVER RAUL | O13: 0.875 | P13: 144 | Q13: 80 | R13: 256 | S13: 224 | T13: -6.4 | V13: Supervisor Martin | X13: Cantidad skus | Z13: 58 | AA13: BLADIMIR LEZCANO | AB13: 248
A14: 52 - MARSALL NICOLAS | B14: 37559970 | C14: 25974210 | D14: 25893547 | E14: 80662.059 | F14: 0.69153968 | G14: 25974210 | H14: 0.69153968 | I14: 1129313.5 | J14: #DIV/0! | K14: 0 | M14: 4 | N14: 4 - TUR SPRINGER FERNANDO | O14: 0.9039548 | P14: 85 | Q14: 75 | R14: 177 | S14: 160 | T14: -9.55 | V14: 4 | W14: TUR SPRINGER FERNANDO | X14: 383 | Z14: 59 | AA14: LEIVA SILVIO | AB14: 178
A15: 53 - SANDOVAL RODRIGO | B15: 37559970 | C15: 32322953 | D15: 32261497 | E15: 61455.881 | F15: 0.8605692 | G15: 32322953 | H15: 0.8605692 | I15: 1405345.8 | J15: #DIV/0! | K15: 0 | N15: MARTIN (SUPERVISOR) | Q15: 912 | R15: 2205 | S15: 1791 | V15: 5 | W15: SCHELOVER RAUL | X15: 387 | Z15: 60 | AA15: #N/A | AB15: #N/A
A16: MARTIN (SUPERVISOR) | B16: 3.0249046e+08 | C16: 2.6528625e+08 | D16: 2.5351209e+08 | E16: 11774161 | F16: 0.87700702 | G16: 2.6528625e+08 | H16: 0.87700702 | I16: 11534185 | J16: #DIV/0! | M16: 31 | N16: 31 - BARTSCHAT EMILIANO NAHUEL | O16: 0.85806452 | P16: 90 | Q16: 43 | R16: 155 | S16: 133 | T16: -1.25 | V16: 8 | W16: PARRA MAXIMILIANO | X16: 281 | Z16: 56 | AA16: JUAN ANDRES SANCHEZ | AB16: 251
A17: 2 - OJEDA NORBERTO | B17: 25959000 | C17: 15605041 | D17: 15500624 | E17: 104417.64 | F17: 0.60114185 | G17: 15605041 | H17: 0.60114185 | I17: 678480.05 | J17: #DIV/0! | K17: 0 | M17: 54 | N17: 54 - CAÑETE DIEGO | O17: 0.82439024 | P17: 92 | Q17: 77 | R17: 205 | S17: 169 | T17: 5.25 | V17: 11 | W17: SANCHEZ RICARDO | X17: 256 | Z17: 26 | AA17: PUJOL ERNESTO | AB17: 273
A18: 3 - VIDAL NAHUEL | B18: 22878600 | C18: 17851343 | D18: 17014009 | E18: 837333.71 | F18: 0.78026378 | G18: 17851343 | H18: 0.78026378 | I18: 776145.35 | J18: #DIV/0! | K18: 0 | M18: 21 | N18: 21 - CATAN MATIAS | O18: 0.86419753 | P18: 88 | Q18: 52 | R18: 162 | S18: 140 | T18: -2.3 | V18: 12 | W18: GUTIERREZ MARCOS DAVID | X18: 409 | Z18: 25 | AA18: KALATAKI GUSTAVO | AB18: 460
A19: 18 - HERRERA PABLO | B19: 22878600 | C19: 10599983 | D19: 10521738 | E19: 78245.206 | F19: 0.46331431 | G19: 10599983 | H19: 0.46331431 | I19: 460868.82 | J19: #DIV/0! | K19: 0 | M19: 23 | N19: 23 - DELGADO JOSÉ | O19: 0.84210526 | P19: 95 | Q19: 33 | R19: 152 | S19: 128 | T19: 1.2 | V19: 16 | W19: GOMEZ MATÍAS | X19: 326 | Z19: 43 | AA19: COLHER DIEGO | AB19: 156
A20: 21 - CATAN MATIAS | B20: 29580000 | C20: 34177594 | D20: 33008585 | E20: 1169009.1 | F20: 1.1554292 | G20: 34177594 | H20: 1.1554292 | I20: 1485982.4 | J20: #DIV/0! | K20: 683551.89 | M20: 18 | N20: 18 - HERRERA PABLO | O20: 0.73563218 | P20: 83 | Q20: 45 | R20: 174 | S20: 128 | T20: 19.9 | V20: 19 | W20: GONZALEZ MARCELO | X20: 376
A21: 23 - DELGADO JOSÉ | B21: 22440000 | C21: 12127167 | D21: 11481794 | E21: 645373.12 | F21: 0.54042634 | G21: 12127167 | H21: 0.54042634 | I21: 527268.14 | J21: #DIV/0! | K21: 0 | M21: 44 | N21: 44 - MONGES CESAR LUIS | O21: 0.73837209 | P21: 64 | Q21: 63 | R21: 172 | S21: 127 | T21: 19.2 | V21: 20 | W21: FLORES JAVIER | X21: 398 | Z21: Vendedores PETS | AB21: Cantidad skus
A22: 31 - BARTSCHAT EMILIANO NAHUEL | B22: 28050000 | C22: 33728905 | D22: 33154330 | E22: 574574.98 | F22: 1.2024565 | G22: 33728905 | H22: 1.2024565 | I22: 1466474.1 | J22: #DIV/0! | K22: 674578.09 | M22: 56 | N22: 56 - JUAN ANDRES SANCHEZ | O22: 0.48924731 | P22: 66 | Q22: 25 | R22: 186 | S22: 91 | T22: 67.1 | V22: Totales | Z22: 52 | AA22: RAVAROTTO EMANUEL | AB22: 134
A23: 44 - MONGES CESAR LUIS | B23: 24276000 | C23: 12651685 | D23: 12317875 | E23: 333810.05 | F23: 0.52116021 | G23: 12651685 | H23: 0.52116021 | I23: 550073.27 | J23: #DIV/0! | K23: 0 | M23: 2 | N23: 2 - OJEDA NORBERTO | O23: 0.72340426 | P23: 70 | Q23: 32 | R23: 141 | S23: 102 | T23: 17.85 | V23: Supervision Corrientes | X23: Cantidad skus | Z23: 53 | AA23: SANDOVAL RODRIGO | AB23: 130
